Workbook
Name IQ_CH: 110000
Name IQ_CQ: 5000
Name IQ_CY: 10000
Name IQ_DAILY: 500000
Name IQ_FH: 100000
Name IQ_FQ: 500
Name IQ_FY: 1000
Name IQ_LTM: 2000
Name IQ_MONTH: 15000
Name IQ_NTM: 6000
Name IQ_WEEK: 50000
Name IQ_YTD: 3000
Name SplitsByYear: DividendHelper!$K$1:$M$12

Sheet Balance Sheet - Standardized
A1: Ticker | C1: LNN | D1: US | M1: Errors on check lines | N1: {=SUM(--ISERROR($C$13:$L$13),--ISERROR($C$17:$L$17),--ISERROR($C$25:$L$25),--ISERROR($C$34:$L$34),--ISERROR($C$36:$L$36),--ISERROR($C$42:$L$42),--ISERROR($C$46:$L$46),--ISERROR($C$58:$L$58),--ISERROR($C$60:$L$60),--ISERROR($C$62:$L$62),--ISERROR($C$69:$L$69),--ISERROR($C$76:$L$76),--ISERROR($C$83:$L$83),--ISERROR($C$85:$L$85),--ISERROR($C$91:$L$91),--ISERROR($C$103:$L$103),--ISERROR($C$105:$L$105),--ISERROR($C$107:$L$107),--ISERROR($C$112:$L$112),--ISERROR($C$119:$L$119),--ISERROR($C$121:$L$121),--ISERROR($C$122:$L$122), COUNT($C$13:$L$13) - COUNTIFS($C$13:$L$13,">-.1",$C$13:$L$13,"<.1"),COUNT($C$17:$L$17) - COUNTIFS($C$17:$L$17,">-.1",$C$17:$L$17,"<.1"),COUNT($C$25:$L$25) - COUNTIFS($C$25:$L$25,">-.1",$C$25:$L$25,"<.1"),COUNT($C$34:$L$34) - COUNTIFS($C$34:$L$34,">-.1",$C$34:$L$34,"<.1"),COUNT($C$36:$L$36) - COUNTIFS($C$36:$L$36,">-.1",$C$36:$L$36,"<.1"),COUNT($C$42:$L$42) - COUNTIFS($C$42:$L$42,">-.1", $C$42:$L$42,"<.1"),COUNT($C$46:$L$46) - COUNTIFS($C$46:$L$46,">-.1", $C$46:$L$46,"<.1"),COUNT($C$58:$L$58) - COUNTIFS($C$58:$L$58,">-.1", $C$58:$L$58,"<.1"),COUNT($C$60:$L$60) - COUNTIFS($C$60:$L$60,">-.1", $C$60:$L$60,"<.1"),COUNT($C$62:$L$62) - COUNTIFS($C$62:$L$62,">-.1", $C$62:$L$62,"<.1"),COUNT($C$69:$L$69) - COUNTIFS($C$69:$L$69,">-.1", $C$69:$L$69,"<.1"),COUNT($C$76:$L$76) - COUNTIFS($C$76:$L$76,">-.1", $C$76:$L$76,"<.1"),COUNT($C$83:$L$83) - COUNTIFS($C$83:$L$83,">-.1", $C$83:$L$83,"<.1"),COUNT($C$85:$L$85) - COUNTIFS($C$85:$L$85,">-.1", $C$85:$L$85,"<.1"),COUNT($C$91:$L$91) - COUNTIFS($C$91:$L$91,">-.1", $C$91:$L$91,"<.1"),COUNT($C$103:$L$103) - COUNTIFS($C$103:$L$103,">-.1", $C$103:$L$103,"<.1"),COUNT($C$105:$L$105) - COUNTIFS($C$105:$L$105,">-.1", $C$105:$L$105,"<.1"),COUNT($C$107:$L$107) - COUNTIFS($C$107:$L$107,">-.1", $C$107:$L$107,"<.1"),COUNT($C$112:$L$112) - COUNTIFS($C$112:$L$112,">-.1", $C$112:$L$112,"<.1"),COUNT($C$119:$L$119) - COUNTIFS($C$119:$L$119,">-.1", $C$119:$L$119,"<.1"),COUNT($C$121:$L$121) - COUNTIFS($C$121:$L$121,">-.1", $C$121:$L$121,"<.1"),COUNT($C$122:$L$122) - COUNTIFS($C$122:$L$122,">-.1", $C$122:$L$122,"<.1"))} -> 0
A2: Start Year | C2: ="FY "&RIGHT(C3,4)-9 -> FY 2016
A3: End Year | C3: ="FY "&IF(O5="Q4",LEFT(N5,4),LEFT(N5,4)-1) -> FY 2025
C4: 42613 | D4: 42978 | E4: 43343 | F4: 43708 | G4: 44074 | H4: 44439 | I4: 44804 | J4: 45169 | K4: 45535 | L4: 45900 | N4: EQY_RECENT_BS_QT | O4: EQY_RECENT_QT_END_QT
C5: 2016 A | D5: 2017 A | E5: 2018 A | F5: 2019 A | G5: 2020 A | H5: 2021 A | I5: 2022 A | J5: 2023 A | K5: 2024 A | L5: 2025 A | N5: 2026 Q3 | O5: Q3
A7: In Millions of USD except Per Share | C7: ="FY "&LEFT(C5,4) -> FY 2016 | D7: ="FY "&LEFT(D5,4) -> FY 2017 | E7: ="FY "&LEFT(E5,4) -> FY 2018 | F7: ="FY "&LEFT(F5,4) -> FY 2019 | G7: ="FY "&LEFT(G5,4) -> FY 2020 | H7: ="FY "&LEFT(H5,4) -> FY 2021 | I7: ="FY "&LEFT(I5,4) -> FY 2022 | J7: ="FY "&LEFT(J5,4) -> FY 2023 | ... L7: ="FY "&LEFT(L5,4) -> FY 2025
A8: 12 Months Ending | C8: =C4 -> 42613 | D8: =D4 -> 42978 | E8: =E4 -> 43343 | F8: =F4 -> 43708 | G8: =G4 -> 44074 | H8: =H4 -> 44439 | I8: =I4 -> 44804 | J8: =J4 -> 45169 | ... L8: =L4 -> 45900
A9: Total Assets | C9: 499.565 | D9: 506.032 | E9: 500.256 | F9: 500.314 | G9: 570.526 | H9: 637.185 | I9: 710.653 | J9: 745.66 | K9: 760.232 | L9: 840.836
A10: + Cash, Cash Equivalents & STI | B10: C&CE_AND_STI_DETAILED | C10: 101.246 | D10: 121.62 | E10: 160.787 | F10: 127.204 | G10: 140.914 | H10: 146.711 | I10: 116.508 | J10: 166.311 | K10: 190.879 | L10: 250.575 | M10: =IF(OR(K10=0,K10=""),"",L10/K10-1) -> 0.31274263
A11: + Cash & Cash Equivalents | B11: BS_CASH_NEAR_CASH_ITEM | C11: 101.246 | D11: 121.62 | E11: 160.787 | F11: 127.204 | G11: 121.403 | H11: 127.107 | I11: 105.048 | J11: 160.755 | K11: 190.879 | L11: 250.575
A12: + ST Investments | B12: BS_MKT_SEC_OTHER_ST_INVEST | C12: 0 | D12: 0 | E12: 0 | F12: 0 | G12: 19.511 | H12: 19.604 | I12: 11.46 | J12: 5.556 | K12: 0 | L12: 0
A13: check | C13: =ROUND(SUM(C11:C12)-IF(C10="",0,C10),1) -> 0 | D13: =ROUND(SUM(D11:D12)-IF(D10="",0,D10),1) -> 0 | E13: =ROUND(SUM(E11:E12)-IF(E10="",0,E10),1) -> 0 | F13: =ROUND(SUM(F11:F12)-IF(F10="",0,F10),1) -> 0 | G13: =ROUND(SUM(G11:G12)-IF(G10="",0,G10),1) -> 0 | H13: =ROUND(SUM(H11:H12)-IF(H10="",0,H10),1) -> 0 | I13: =ROUND(SUM(I11:I12)-IF(I10="",0,I10),1) -> 0 | J13: =ROUND(SUM(J11:J12)-IF(J10="",0,J10),1) -> 0 | ... L13: =ROUND(SUM(L11:L12)-IF(L10="",0,L10),1) -> 0
A14: + Accounts & Notes Receiv | B14: BS_ACCT_NOTE_RCV | C14: 80.61 | D14: 73.85 | E14: 69.107 | F14: 75.551 | G14: 84.604 | H14: 93.609 | I14: 138.2 | J14: 144.774 | K14: 116.601 | L14: 113.027 | M14: =IF(OR(K14=0,K14=""),"",L14/K14-1) -> -0.030651538
A15: + Accounts Receivable, Net | B15: BS_ACCTS_REC_EXCL_NOTES_REC | C15: 80.61 | D15: 73.85 | E15: 69.107 | F15: 75.551 | G15: 84.604 | H15: 93.609 | I15: 138.2 | J15: 144.774 | K15: 116.601 | L15: 113.027
A16: + Notes Receivable, Net | B16: NOTES_RECEIVABLE | C16: 0 | D16: 0 | E16: 0 | F16: 0 | G16: 0 | H16: 0 | I16: 0 | J16: 0 | K16: 0 | L16: 0
A17: check | C17: =IF(AND(C15="",C16=""),0,ROUND(SUM(C15:C16)-IF(C14="",0,C14),1)) -> 0 | D17: =IF(AND(D15="",D16=""),0,ROUND(SUM(D15:D16)-IF(D14="",0,D14),1)) -> 0 | E17: =IF(AND(E15="",E16=""),0,ROUND(SUM(E15:E16)-IF(E14="",0,E14),1)) -> 0 | F17: =IF(AND(F15="",F16=""),0,ROUND(SUM(F15:F16)-IF(F14="",0,F14),1)) -> 0 | G17: =IF(AND(G15="",G16=""),0,ROUND(SUM(G15:G16)-IF(G14="",0,G14),1)) -> 0 | H17: =IF(AND(H15="",H16=""),0,ROUND(SUM(H15:H16)-IF(H14="",0,H14),1)) -> 0 | I17: =IF(AND(I15="",I16=""),0,ROUND(SUM(I15:I16)-IF(I14="",0,I14),1)) -> 0 | J17: =IF(AND(J15="",J16=""),0,ROUND(SUM(J15:J16)-IF(J14="",0,J14),1)) -> 0 | ... L17: =IF(AND(L15="",L16=""),0,ROUND(SUM(L15:L16)-IF(L14="",0,L14),1)) -> 0
A19: + Unbilled Revenues | B19: BS_UNBILLED_REVENUES | M19: =IF(OR(K19=0,K19=""),"",L19/K19-1)
A20: + Inventories | B20: BS_INVENTORIES | C20: 74.75 | D20: 86.155 | E20: 79.233 | F20: 92.287 | G20: 104.792 | H20: 145.244 | I20: 193.776 | J20: 155.932 | K20: 154.453 | L20: 136.859 | M20: =IF(OR(K20=0,K20=""),"",L20/K20-1) -> -0.11391168
A21: + Raw Materials | B21: INVTRY_RAW_MATERIALS | C21: 26.599 | D21: 31.158 | E21: 36.316 | F21: 49.047 | G21: 51.205 | H21: 69.962 | I21: 93.469 | J21: 83.908 | K21: 84.725 | L21: 70.51
A22: + Work In Process | B22: INVTRY_IN_PROGRESS | C22: 5.742 | D22: 7.113 | E22: 9.176 | F22: 4.514 | G22: 6.464 | H22: 8.301 | I22: 12.603 | J22: 7.82 | K22: 10.192 | L22: 7.186
A23: + Finished Goods | B23: INVTRY_FINISHED_GOODS | C23: 47.805 | D23: 52.382 | E23: 40.197 | F23: 46.812 | G23: 51.684 | H23: 75.053 | I23: 110.022 | J23: 86.793 | K23: 80.877 | L23: 78.631
A24: + Other Inventory | B24: BS_OTHER_INV | C24: -5.396 | D24: -4.498 | E24: -6.456 | F24: -8.086 | G24: -4.561 | H24: -8.072 | I24: -22.318 | J24: -22.589 | K24: -21.341 | L24: -19.468
A25: check | C25: =IF(AND(C21="",C22="",C23="",C24=""),0,ROUND(SUM(C21:C24)-IF(C20="",0,C20),1)) -> 0 | D25: =IF(AND(D21="",D22="",D23="",D24=""),0,ROUND(SUM(D21:D24)-IF(D20="",0,D20),1)) -> 0 | E25: =IF(AND(E21="",E22="",E23="",E24=""),0,ROUND(SUM(E21:E24)-IF(E20="",0,E20),1)) -> 0 | F25: =IF(AND(F21="",F22="",F23="",F24=""),0,ROUND(SUM(F21:F24)-IF(F20="",0,F20),1)) -> 0 | G25: =IF(AND(G21="",G22="",G23="",G24=""),0,ROUND(SUM(G21:G24)-IF(G20="",0,G20),1)) -> 0 | H25: =IF(AND(H21="",H22="",H23="",H24=""),0,ROUND(SUM(H21:H24)-IF(H20="",0,H20),1)) -> 0 | I25: =IF(AND(I21="",I22="",I23="",I24=""),0,ROUND(SUM(I21:I24)-IF(I20="",0,I20),1)) -> 0 | J25: =IF(AND(J21="",J22="",J23="",J24=""),0,ROUND(SUM(J21:J24)-IF(J20="",0,J20),1)) -> 0 | ... L25: =IF(AND(L21="",L22="",L23="",L24=""),0,ROUND(SUM(L21:L24)-IF(L20="",0,L20),1)) -> 0
A26: + Other ST Assets | B26: OTHER_CURRENT_ASSETS_DETAILED | C26: 20.169 | D26: 11.309 | E26: 21.924 | F26: 18.448 | G26: 17.625 | H26: 30.539 | I26: 28.617 | J26: 20.467 | K26: 31.279 | L26: 32.303 | M26: =IF(OR(K26=0,K26=""),"",L26/K26-1) -> 0.032737619
A27: + Prepaid Expenses | B27: BS_PREPAY | C27: 3.671 | D27: 4.384 | E27: 3.883
A28: + ST Derivative & Hedging Assets | B28: BS_DERIV_&_HEDGING_ASSETS_ST | C28: 0.073 | D28: 0.009 | E28: 0.898 | F28: 1.112 | G28: 0.021 | H28: 0 | I28: 0 | J28: 0 | L28: 0
A29: + Assets Held-for-Sale | B29: BS_ASSETS_HELD_FOR_SALE_ST | E29: 10.837 | F29: 2.744 | G29: 0 | H29: 0 | I29: 0
A30: + ST Deferred Tax Assets | B30: BS_DEFERRED_TAX_ASSETS_ST
A31: + Taxes Receivable | B31: BS_TAXES_RECEIVABLE_SHORT_TERM
A32: + Assets of Discontinued Operations ST | B32: BS_ASSETS_OF_DISCONTINUED_OPS_ST
A33: + Misc ST Assets | B33: BS_OTHER_CUR_ASSET_LESS_PREPAY | C33: 16.425 | D33: 6.916 | E33: 6.306 | F33: 14.592 | G33: 17.604 | H33: 30.539 | I33: 28.617 | J33: 20.467 | K33: 31.279 | L33: 32.303
A34: check | C34: =ROUND(SUM(C27:C33)-IF(C26="",0,C26),1) -> 0 | D34: =ROUND(SUM(D27:D33)-IF(D26="",0,D26),1) -> 0 | E34: =ROUND(SUM(E27:E33)-IF(E26="",0,E26),1) -> 0 | F34: =ROUND(SUM(F27:F33)-IF(F26="",0,F26),1) -> 0 | G34: =ROUND(SUM(G27:G33)-IF(G26="",0,G26),1) -> 0 | H34: =ROUND(SUM(H27:H33)-IF(H26="",0,H26),1) -> 0 | I34: =ROUND(SUM(I27:I33)-IF(I26="",0,I26),1) -> 0 | J34: =ROUND(SUM(J27:J33)-IF(J26="",0,J26),1) -> 0 | ... L34: =ROUND(SUM(L27:L33)-IF(L26="",0,L26),1) -> 0
A35: Total Current Assets | B35: BS_CUR_ASSET_REPORT | C35: 276.775 | D35: 292.934 | E35: 331.051 | F35: 313.49 | G35: 347.935 | H35: 416.103 | I35: 477.101 | J35: 487.484 | K35: 493.212 | L35: 532.764 | M35: =IF(OR(K35=0,K35=""),"",L35/K35-1) -> 0.080192696
A36: check | C36: =ROUND(IF(C10="",0,C10)+IF(C14="",0,C14)+IF(C19="",0,C19)+IF(C20="",0,C20)+IF(C26="",0,C26)-IF(C35="",0,C35),1) -> 0 | D36: =ROUND(IF(D10="",0,D10)+IF(D14="",0,D14)+IF(D19="",0,D19)+IF(D20="",0,D20)+IF(D26="",0,D26)-IF(D35="",0,D35),1) -> 0 | E36: =ROUND(IF(E10="",0,E10)+IF(E14="",0,E14)+IF(E19="",0,E19)+IF(E20="",0,E20)+IF(E26="",0,E26)-IF(E35="",0,E35),1) -> 0 | F36: =ROUND(IF(F10="",0,F10)+IF(F14="",0,F14)+IF(F19="",0,F19)+IF(F20="",0,F20)+IF(F26="",0,F26)-IF(F35="",0,F35),1) -> 0 | G36: =ROUND(IF(G10="",0,G10)+IF(G14="",0,G14)+IF(G19="",0,G19)+IF(G20="",0,G20)+IF(G26="",0,G26)-IF(G35="",0,G35),1) -> 0 | H36: =ROUND(IF(H10="",0,H10)+IF(H14="",0,H14)+IF(H19="",0,H19)+IF(H20="",0,H20)+IF(H26="",0,H26)-IF(H35="",0,H35),1) -> 0 | I36: =ROUND(IF(I10="",0,I10)+IF(I14="",0,I14)+IF(I19="",0,I19)+IF(I20="",0,I20)+IF(I26="",0,I26)-IF(I35="",0,I35),1) -> 0 | J36: =ROUND(IF(J10="",0,J10)+IF(J14="",0,J14)+IF(J19="",0,J19)+IF(J20="",0,J20)+IF(J26="",0,J26)-IF(J35="",0,J35),1) -> 0 | ... L36: =ROUND(IF(L10="",0,L10)+IF(L14="",0,L14)+IF(L19="",0,L19)+IF(L20="",0,L20)+IF(L26="",0,L26)-IF(L35="",0,L35),1) -> 0
A37: + Property, Plant & Equip, Net (As Reported) | B37: ARD_PROPERTY_PLANT_EQUIP_NET | C37: 77.627 | D37: 74.498 | E37: 57.248 | F37: 68.968 | G37: 79.581 | H37: 91.997 | I37: 94.472 | J37: 99.681 | K37: 112.815 | L37: 142.307 | M37: =IF(OR(K37=0,K37=""),"",L37/K37-1) -> 0.26141914
A38: + Property, Plant & Equip, Net (Standardized) | B38: BS_NET_FIX_ASSET | C38: 77.627 | D38: 74.498 | E38: 57.248 | F38: 68.968 | G38: 107.038 | H38: 110.278 | I38: 113.653 | J38: 116.717 | K38: 128.508 | L38: 160.403
A39: + Property, Plant & Equip (Standardized) | B39: BS_GROSS_FIX_ASSET | C39: 182.696 | D39: 189.14 | E39: 171.45 | F39: 188.695 | G39: 235.564 | H39: 247.281 | I39: 260.162 | J39: 274.777 | K39: 296.308 | L39: 333.156
A40: - Accumulated Depreciation (Standardized) | B40: BS_ACCUM_DEPR | C40: 105.069 | D40: 114.642 | E40: 114.202 | F40: 119.727 | G40: 128.526 | H40: 137.003 | I40: 146.509 | J40: 158.06 | K40: 167.8 | L40: 172.753
A41: Operating Leases | C41: =IF(C38="",0,C38)-IF(C37="",0,C37) -> 0 | D41: =IF(D38="",0,D38)-IF(D37="",0,D37) -> 0 | E41: =IF(E38="",0,E38)-IF(E37="",0,E37) -> 0 | F41: =IF(F38="",0,F38)-IF(F37="",0,F37) -> 0 | G41: =IF(G38="",0,G38)-IF(G37="",0,G37) -> 27.457 | H41: =IF(H38="",0,H38)-IF(H37="",0,H37) -> 18.281 | I41: =IF(I38="",0,I38)-IF(I37="",0,I37) -> 19.181 | J41: =IF(J38="",0,J38)-IF(J37="",0,J37) -> 17.036 | ... L41: =IF(L38="",0,L38)-IF(L37="",0,L37) -> 18.096
A42: check | C42: =ROUND(IF(C39="",0,C39)-IF(C40="",0,C40)-IF(C38="",0,C38),1) -> 0 | D42: =ROUND(IF(D39="",0,D39)-IF(D40="",0,D40)-IF(D38="",0,D38),1) -> 0 | E42: =ROUND(IF(E39="",0,E39)-IF(E40="",0,E40)-IF(E38="",0,E38),1) -> 0 | F42: =ROUND(IF(F39="",0,F39)-IF(F40="",0,F40)-IF(F38="",0,F38),1) -> 0 | G42: =ROUND(IF(G39="",0,G39)-IF(G40="",0,G40)-IF(G38="",0,G38),1) -> 0 | H42: =ROUND(IF(H39="",0,H39)-IF(H40="",0,H40)-IF(H38="",0,H38),1) -> 0 | I42: =ROUND(IF(I39="",0,I39)-IF(I40="",0,I40)-IF(I38="",0,I38),1) -> 0 | J42: =ROUND(IF(J39="",0,J39)-IF(J40="",0,J40)-IF(J38="",0,J38),1) -> 0 | ... L42: =ROUND(IF(L39="",0,L39)-IF(L40="",0,L40)-IF(L38="",0,L38),1) -> 0
A43: + LT Investments & Receivables | B43: BS_LT_INVEST | C43: 0 | D43: 0 | E43: 0 | F43: 0 | G43: 0 | H43: 0 | I43: 0 | J43: 0 | K43: 0 | L43: 0 | M43: =IF(OR(K43=0,K43=""),"",L43/K43-1)
A44: + LT Investments | B44: BS_LONG_TERM_INVESTMENTS
A45: + LT Marketable Securities | B45: BS_LT_MARKETABLE_SECURITIES
A46: check | C46: =IF(AND(C44="",C45=""),0,ROUND(SUM(C44:C45)-IF(C43="",0,C43),1)) -> 0 | D46: =IF(AND(D44="",D45=""),0,ROUND(SUM(D44:D45)-IF(D43="",0,D43),1)) -> 0 | E46: =IF(AND(E44="",E45=""),0,ROUND(SUM(E44:E45)-IF(E43="",0,E43),1)) -> 0 | F46: =IF(AND(F44="",F45=""),0,ROUND(SUM(F44:F45)-IF(F43="",0,F43),1)) -> 0 | G46: =IF(AND(G44="",G45=""),0,ROUND(SUM(G44:G45)-IF(G43="",0,G43),1)) -> 0 | H46: =IF(AND(H44="",H45=""),0,ROUND(SUM(H44:H45)-IF(H43="",0,H43),1)) -> 0 | I46: =IF(AND(I44="",I45=""),0,ROUND(SUM(I44:I45)-IF(I43="",0,I43),1)) -> 0 | J46: =IF(AND(J44="",J45=""),0,ROUND(SUM(J44:J45)-IF(J43="",0,J43),1)) -> 0 | ... L46: =IF(AND(L44="",L45=""),0,ROUND(SUM(L44:L45)-IF(L43="",0,L43),1)) -> 0
A47: + Other LT Assets | B47: BS_OTHER_ASSETS_DEF_CHRG_OTHER | C47: 133.113 | D47: 138.6 | E47: 111.957 | F47: 117.856 | G47: 115.553 | H47: 110.804 | I47: 119.899 | J47: 141.459 | K47: 138.512 | L47: 147.669 | M47: =IF(OR(K47=0,K47=""),"",L47/K47-1) -> 0.066109796
A48: + Total Intangible Assets | B48: BS_DISCLOSED_INTANGIBLES | C48: 124.003 | D48: 119.939 | E48: 92.048 | F48: 88.769 | G48: 91.481 | H48: 88.335 | I48: 85.338 | J48: 110.84 | K48: 109.56 | L48: 107.79
A49: + Goodwill | B49: BS_GOODWILL | C49: 76.803 | D49: 77.131 | E49: 64.671 | F49: 64.387 | G49: 68.004 | H49: 67.968 | I49: 67.13 | J49: 83.121 | K49: 84.194 | L49: 84.459
A50: + Other Intangible Assets | B50: OTHER_INTANGIBLE_ASSETS_DETAILED | C50: 47.2 | D50: 42.808 | E50: 27.377 | F50: 24.382 | G50: 23.477 | H50: 20.367 | I50: 18.208 | J50: 27.719 | K50: 25.366 | L50: 23.331
A51: + Prepaid Expense | B51: BS_PREPAID_EXPENSE_LT
A52: + LT Deferred Tax Assets | B52: BS_DEFERRED_TAX_ASSETS_LT | C52: 4.225 | D52: 5.311 | E52: 6.645 | F52: 11.758 | G52: 9.935 | H52: 8.113 | I52: 9.313 | J52: 10.885 | K52: 14.431 | L52: 19.525
A53: + LT Derivative & Hedging Assets | B53: BS_DERIV_&_HEDGING_ASSETS_LT | C53: 0 | D53: 0 | E53: 0 | F53: 0 | G53: 0 | H53: 0 | I53: 0 | J53: 0 | K53: 0 | L53: 0
A54: + Prepaid Pension Costs | B54: BS_PREPAID_PENSION_COSTS_LT
A55: + Investments in Affiliates | B55: BS_INVEST_IN_ASSOC_CO
A56: + Assets of Discontinued Operations LT | B56: BS_ASSETS_OF_DISCONTINUED_OPS_LT
A57: + Misc LT Assets | B57: OTHER_NONCURRENT_ASSETS_DETAILED | C57: 4.885 | D57: 13.35 | E57: 13.264 | F57: 17.329 | G57: 14.137 | H57: 14.356 | I57: 25.248 | J57: 19.734 | K57: 14.521 | L57: 20.354
A58: check | C58: =ROUND(SUM(C48,C51:C57)-IF(C47="",0,C47),1) -> 0 | D58: =ROUND(SUM(D48,D51:D57)-IF(D47="",0,D47),1) -> 0 | E58: =ROUND(SUM(E48,E51:E57)-IF(E47="",0,E47),1) -> 0 | F58: =ROUND(SUM(F48,F51:F57)-IF(F47="",0,F47),1) -> 0 | G58: =ROUND(SUM(G48,G51:G57)-IF(G47="",0,G47),1) -> 0 | H58: =ROUND(SUM(H48,H51:H57)-IF(H47="",0,H47),1) -> 0 | I58: =ROUND(SUM(I48,I51:I57)-IF(I47="",0,I47),1) -> 0 | J58: =ROUND(SUM(J48,J51:J57)-IF(J47="",0,J47),1) -> 0 | ... L58: =ROUND(SUM(L48,L51:L57)-IF(L47="",0,L47),1) -> 0
A59: Total Noncurrent Assets | B59: BS_TOT_NON_CUR_ASSET | C59: 210.74 | D59: 213.098 | E59: 169.205 | F59: 186.824 | G59: 222.591 | H59: 221.082 | I59: 233.552 | J59: 258.176 | K59: 267.02 | L59: 308.072 | M59: =IF(OR(K59=0,K59=""),"",L59/K59-1) -> 0.15374129
A60: check | C60: =ROUND(IF(C38="",0,C38)+IF(C43="",0,C43)+IF(C47="",0,C47)-IF(C59="",0,C59),1) -> 0 | D60: =ROUND(IF(D38="",0,D38)+IF(D43="",0,D43)+IF(D47="",0,D47)-IF(D59="",0,D59),1) -> 0 | E60: =ROUND(IF(E38="",0,E38)+IF(E43="",0,E43)+IF(E47="",0,E47)-IF(E59="",0,E59),1) -> 0 | F60: =ROUND(IF(F38="",0,F38)+IF(F43="",0,F43)+IF(F47="",0,F47)-IF(F59="",0,F59),1) -> 0 | G60: =ROUND(IF(G38="",0,G38)+IF(G43="",0,G43)+IF(G47="",0,G47)-IF(G59="",0,G59),1) -> 0 | H60: =ROUND(IF(H38="",0,H38)+IF(H43="",0,H43)+IF(H47="",0,H47)-IF(H59="",0,H59),1) -> 0 | I60: =ROUND(IF(I38="",0,I38)+IF(I43="",0,I43)+IF(I47="",0,I47)-IF(I59="",0,I59),1) -> 0 | J60: =ROUND(IF(J38="",0,J38)+IF(J43="",0,J43)+IF(J47="",0,J47)-IF(J59="",0,J59),1) -> 0 | ... L60: =ROUND(IF(L38="",0,L38)+IF(L43="",0,L43)+IF(L47="",0,L47)-IF(L59="",0,L59),1) -> 0
A61: Total Assets | B61: BS_TOT_ASSET | C61: 487.515 | D61: 506.032 | E61: 500.256 | F61: 500.314 | G61: 570.526 | H61: 637.185 | I61: 710.653 | J61: 745.66 | K61: 760.232 | L61: 840.836 | M61: =IF(OR(K61=0,K61=""),"",L61/K61-1) -> 0.10602553
A62: check | C62: =ROUND(IF(C35="",0,C35)+IF(C38="",0,C38)+IF(C43="",0,C43)+IF(C47="",0,C47)-IF(C61="",0,C61),1) -> 0 | D62: =ROUND(IF(D35="",0,D35)+IF(D38="",0,D38)+IF(D43="",0,D43)+IF(D47="",0,D47)-IF(D61="",0,D61),1) -> 0 | E62: =ROUND(IF(E35="",0,E35)+IF(E38="",0,E38)+IF(E43="",0,E43)+IF(E47="",0,E47)-IF(E61="",0,E61),1) -> 0 | F62: =ROUND(IF(F35="",0,F35)+IF(F38="",0,F38)+IF(F43="",0,F43)+IF(F47="",0,F47)-IF(F61="",0,F61),1) -> 0 | G62: =ROUND(IF(G35="",0,G35)+IF(G38="",0,G38)+IF(G43="",0,G43)+IF(G47="",0,G47)-IF(G61="",0,G61),1) -> 0 | H62: =ROUND(IF(H35="",0,H35)+IF(H38="",0,H38)+IF(H43="",0,H43)+IF(H47="",0,H47)-IF(H61="",0,H61),1) -> 0 | I62: =ROUND(IF(I35="",0,I35)+IF(I38="",0,I38)+IF(I43="",0,I43)+IF(I47="",0,I47)-IF(I61="",0,I61),1) -> 0 | J62: =ROUND(IF(J35="",0,J35)+IF(J38="",0,J38)+IF(J43="",0,J43)+IF(J47="",0,J47)-IF(J61="",0,J61),1) -> 0 | ... L62: =ROUND(IF(L35="",0,L35)+IF(L38="",0,L38)+IF(L43="",0,L43)+IF(L47="",0,L47)-IF(L61="",0,L61),1) -> 0
A63: Liabilities & Shareholders' Equity
A64: + Payables & Accruals | B64: ACCT_PAYABLE_&_ACCRUALS_DETAILED | C64: 36.468 | D64: 39.53 | E64: 31.823 | F64: 32.68 | G64: 33.28 | H64: 46.281 | I64: 67.856 | J64: 53.465 | K64: 43.961 | L64: 56.287 | M64: =IF(OR(K64=0,K64=""),"",L64/K64-1) -> 0.28038489
A65: + Accounts Payable | B65: BS_ACCT_PAYABLE | C65: 32.268 | D65: 36.717 | E65: 30.53 | F65: 29.434 | G65: 29.554 | H65: 45.209 | I65: 60.036 | J65: 44.278 | K65: 37.417 | L65: 48.67
A66: + Accrued Taxes | B66: BS_TAXES_PAYABLE | C66: 4.2 | D66: 2.813 | E66: 1.293 | F66: 3.246 | G66: 3.726 | H66: 1.072 | I66: 7.82 | J66: 9.187 | K66: 6.544 | L66: 7.617
A67: + Interest & Dividends Payable | B67: BS_INTEREST_&_DIVIDENDS_PAYABLE
A68: + Other Payables & Accruals | B68: BS_ACCRUAL | C68: 0 | D68: 0 | E68: 0 | F68: 0 | G68: 0 | H68: 0 | I68: 0 | J68: 0 | K68: 0 | L68: 0
A69: check | C69: =ROUND(SUM(C65:C68)-IF(C64="",0,C64),1) -> 0 | D69: =ROUND(SUM(D65:D68)-IF(D64="",0,D64),1) -> 0 | E69: =ROUND(SUM(E65:E68)-IF(E64="",0,E64),1) -> 0 | F69: =ROUND(SUM(F65:F68)-IF(F64="",0,F64),1) -> 0 | G69: =ROUND(SUM(G65:G68)-IF(G64="",0,G64),1) -> 0 | H69: =ROUND(SUM(H65:H68)-IF(H64="",0,H64),1) -> 0 | I69: =ROUND(SUM(I65:I68)-IF(I64="",0,I64),1) -> 0 | J69: =ROUND(SUM(J65:J68)-IF(J64="",0,J64),1) -> 0 | ... L69: =ROUND(SUM(L65:L68)-IF(L64="",0,L64),1) -> 0
A70: + ST Debt | B70: BS_ST_BORROW | C70: 0.197 | D70: 0.201 | E70: 0.205 | F70: 0.209 | G70: 5.318 | H70: 4.208 | I70: 3.381 | J70: 3.254 | K70: 3.851 | L70: 4.346 | M70: =IF(OR(K70=0,K70=""),"",L70/K70-1) -> 0.12853804
A71: + ST Lease Liabilities | B71: ST_CAPITALIZED_LEASE_LIABILITIES | C71: 0 | D71: 0 | E71: 0 | F71: 0 | G71: 5.123 | H71: 3.991 | I71: 3.159 | J71: 3.028 | K71: 3.623 | L71: 4.113
A72: + ST Capital Leases | B72: ST_CAPITAL_LEASE_OBLIGATIONS | C72: 0 | D72: 0 | E72: 0 | F72: 0 | G72: 0 | H72: 0 | I72: 0 | J72: 0 | K72: 0 | L72: 0
A73: + ST Operating Leases | B73: BS_ST_OPERATING_LEASE_LIABS | G73: 5.123 | H73: 3.991 | I73: 3.159 | J73: 3.028 | K73: 3.623 | L73: 4.113
A74: + ST Borrowings | B74: SHORT_TERM_DEBT_DETAILED | C74: 0 | D74: 0 | E74: 0 | F74: 0 | G74: 0 | H74: 0 | I74: 0 | J74: 0 | K74: 0 | L74: 0
A75: + Current Portion of LT Debt | B75: BS_CURR_PORTION_LT_DEBT | C75: 0.197 | D75: 0.201 | E75: 0.205 | F75: 0.209 | G75: 0.195 | H75: 0.217 | I75: 0.222 | J75: 0.226 | K75: 0.228 | L75: 0.233
A76: check | C76: =ROUND(IF(C70="",0,C70)-IF(C71="",0,C71)-IF(C74="",0,C74)-IF(C75="",0,C75),1) -> 0 | D76: =ROUND(IF(D70="",0,D70)-IF(D71="",0,D71)-IF(D74="",0,D74)-IF(D75="",0,D75),1) -> 0 | E76: =ROUND(IF(E70="",0,E70)-IF(E71="",0,E71)-IF(E74="",0,E74)-IF(E75="",0,E75),1) -> 0 | F76: =ROUND(IF(F70="",0,F70)-IF(F71="",0,F71)-IF(F74="",0,F74)-IF(F75="",0,F75),1) -> 0 | G76: =ROUND(IF(G70="",0,G70)-IF(G71="",0,G71)-IF(G74="",0,G74)-IF(G75="",0,G75),1) -> 0 | H76: =ROUND(IF(H70="",0,H70)-IF(H71="",0,H71)-IF(H74="",0,H74)-IF(H75="",0,H75),1) -> 0 | I76: =ROUND(IF(I70="",0,I70)-IF(I71="",0,I71)-IF(I74="",0,I74)-IF(I75="",0,I75),1) -> 0 | J76: =ROUND(IF(J70="",0,J70)-IF(J71="",0,J71)-IF(J74="",0,J74)-IF(J75="",0,J75),1) -> 0 | ... L76: =ROUND(IF(L70="",0,L70)-IF(L71="",0,L71)-IF(L74="",0,L74)-IF(L75="",0,L75),1) -> 0
A77: + Other ST Liabilities | B77: OTHER_CURRENT_LIABS_SUB_DETAILED | C77: 51.195 | D77: 52.306 | E77: 48.066 | F77: 49.242 | G77: 63.797 | H77: 87.751 | I77: 89.705 | J77: 79.389 | K77: 78.004 | L77: 82.959 | M77: =IF(OR(K77=0,K77=""),"",L77/K77-1) -> 0.063522383
A78: + ST Deferred Revenue | B78: ST_DEFERRED_REVENUE | C78: 7.594 | D78: 6.166 | E78: 6.337 | F78: 0 | G78: 1.822 | H78: 3.456 | I78: 1.064 | J78: 2.83 | K78: 23.236 | L78: 17.939
A79: + ST Derivatives & Hedging | B79: BS_DERIVATIVE_&_HEDGING_LIABS_ST | C79: 0.595 | D79: 1.747 | E79: 0.012 | F79: 0 | G79: 0 | H79: 0 | I79: 0 | J79: 0 | K79: 0 | L79: 0
A80: + ST Deferred Tax Liabilities | B80: BS_DEFERRED_TAX_LIABS_ST
A81: + Liabilities of Discontinued Operations ST | B81: BS_LIABS_OF_DISCONTINUED_OPS_ST
A82: + Misc ST Liabilities | B82: OTHER_CURRENT_LIABS_DETAILED | C82: 43.006 | D82: 44.393 | E82: 41.717 | F82: 49.242 | G82: 61.975 | H82: 84.295 | I82: 88.641 | J82: 76.559 | K82: 54.768 | L82: 65.02
A83: check | C83: =ROUND(SUM(C78:C82)-IF(C77="",0,C77),1) -> 0 | D83: =ROUND(SUM(D78:D82)-IF(D77="",0,D77),1) -> 0 | E83: =ROUND(SUM(E78:E82)-IF(E77="",0,E77),1) -> 0 | F83: =ROUND(SUM(F78:F82)-IF(F77="",0,F77),1) -> 0 | G83: =ROUND(SUM(G78:G82)-IF(G77="",0,G77),1) -> 0 | H83: =ROUND(SUM(H78:H82)-IF(H77="",0,H77),1) -> 0 | I83: =ROUND(SUM(I78:I82)-IF(I77="",0,I77),1) -> 0 | J83: =ROUND(SUM(J78:J82)-IF(J77="",0,J77),1) -> 0 | ... L83: =ROUND(SUM(L78:L82)-IF(L77="",0,L77),1) -> 0
A84: Total Current Liabilities | B84: BS_CUR_LIAB | C84: 87.86 | D84: 92.037 | E84: 80.094 | F84: 82.131 | G84: 102.395 | H84: 138.24 | I84: 160.942 | J84: 136.108 | K84: 125.816 | L84: 143.592 | M84: =IF(OR(K84=0,K84=""),"",L84/K84-1) -> 0.14128569
A85: check | C85: =ROUND(IF(C64="",0,C64)+IF(C70="",0,C70)+IF(C77="",0,C77)-IF(C84="",0,C84),1) -> 0 | D85: =ROUND(IF(D64="",0,D64)+IF(D70="",0,D70)+IF(D77="",0,D77)-IF(D84="",0,D84),1) -> 0 | E85: =ROUND(IF(E64="",0,E64)+IF(E70="",0,E70)+IF(E77="",0,E77)-IF(E84="",0,E84),1) -> 0 | F85: =ROUND(IF(F64="",0,F64)+IF(F70="",0,F70)+IF(F77="",0,F77)-IF(F84="",0,F84),1) -> 0 | G85: =ROUND(IF(G64="",0,G64)+IF(G70="",0,G70)+IF(G77="",0,G77)-IF(G84="",0,G84),1) -> 0 | H85: =ROUND(IF(H64="",0,H64)+IF(H70="",0,H70)+IF(H77="",0,H77)-IF(H84="",0,H84),1) -> 0 | I85: =ROUND(IF(I64="",0,I64)+IF(I70="",0,I70)+IF(I77="",0,I77)-IF(I84="",0,I84),1) -> 0 | J85: =ROUND(IF(J64="",0,J64)+IF(J70="",0,J70)+IF(J77="",0,J77)-IF(J84="",0,J84),1) -> 0 | ... L85: =ROUND(IF(L64="",0,L64)+IF(L70="",0,L70)+IF(L77="",0,L77)-IF(L84="",0,L84),1) -> 0
A86: + LT Debt | B86: BS_LT_BORROW | C86: 116.976 | D86: 116.775 | E86: 116.57 | F86: 115.846 | G86: 141.544 | H86: 133.815 | I86: 135.151 | J86: 132.853 | K86: 130.535 | L86: 132.164 | M86: =IF(OR(K86=0,K86=""),"",L86/K86-1) -> 0.012479412
A87: + LT Borrowings | B87: LONG_TERM_BORROWINGS_DETAILED | C87: 116.976 | D87: 116.775 | E87: 116.57 | F87: 115.846 | G87: 115.682 | H87: 115.514 | I87: 115.341 | J87: 115.164 | K87: 114.994 | L87: 114.81
A88: + LT Lease Liabilities | B88: LT_CAPITALIZED_LEASE_LIABILITIES | C88: 0 | D88: 0 | E88: 0 | F88: 0 | G88: 25.862 | H88: 18.301 | I88: 19.81 | J88: 17.689 | K88: 15.541 | L88: 17.354
A89: + LT Capital Leases | B89: LT_CAPITAL_LEASE_OBLIGATIONS | C89: 0 | D89: 0 | E89: 0 | F89: 0 | G89: 0 | H89: 0 | I89: 0 | J89: 0 | K89: 0 | L89: 0
A90: + LT Operating Leases | B90: BS_LT_OPERATING_LEASE_LIABS | G90: 25.862 | H90: 18.301 | I90: 19.81 | J90: 17.689 | K90: 15.541 | L90: 17.354
A91: check | C91: =ROUND(SUM(C87:C88)-IF(C86="",0,C86),1) -> 0 | D91: =ROUND(SUM(D87:D88)-IF(D86="",0,D86),1) -> 0 | E91: =ROUND(SUM(E87:E88)-IF(E86="",0,E86),1) -> 0 | F91: =ROUND(SUM(F87:F88)-IF(F86="",0,F86),1) -> 0 | G91: =ROUND(SUM(G87:G88)-IF(G86="",0,G86),1) -> 0 | H91: =ROUND(SUM(H87:H88)-IF(H86="",0,H86),1) -> 0 | I91: =ROUND(SUM(I87:I88)-IF(I86="",0,I86),1) -> 0 | J91: =ROUND(SUM(J87:J88)-IF(J86="",0,J86),1) -> 0 | ... L91: =ROUND(SUM(L87:L88)-IF(L86="",0,L86),1) -> 0
A92: + Other LT Liabilities | B92: OTHER_NONCUR_LIABS_SUB_DETAILED | C92: 31.112 | D92: 27.165 | E92: 26.726 | F92: 34.128 | G92: 28.069 | H92: 26.685 | I92: 21.202 | J92: 21.048 | K92: 22.988 | L92: 32.23 | M92: =IF(OR(K92=0,K92=""),"",L92/K92-1) -> 0.40203584
A93: + Accrued Liabilities | B93: BS_ACCRUED_LIABILITIES | C93: 0 | D93: 0 | E93: 0 | F93: 0 | G93: 0 | H93: 0 | I93: 0 | J93: 0 | K93: 0 | L93: 0
A94: + Pension Liabilities | B94: PENSION_LIABILITIES | C94: 6.869 | D94: 6.295 | E94: 5.874 | F94: 6.029 | G94: 6.374 | H94: 5.754 | I94: 4.892 | J94: 4.382 | K94: 4.167 | L94: 3.418
A95: + Pensions | B95: BS_PENSIONS_LT_LIABS
A96: + Other Post-Ret Benefits | B96: BS_OPRB_LT_LIABS
A97: + Deferred Compensation | B97: BS_DEFERRED_COMP_LT_LIABS
A98: + LT Deferred Revenue | B98: LT_DEFERRED_REVENUE | C98: 0 | D98: 0 | E98: 0 | F98: 0 | G98: 0 | H98: 0 | I98: 0 | J98: 0 | K98: 0 | L98: 0
A99: + LT Deferred Tax Liabilities | B99: BS_DEFERRED_TAX_LIABILITIES_LT | C99: 1.223 | D99: 1.191 | E99: 1.083 | F99: 0.872 | G99: 0.889 | H99: 0.832 | I99: 1.054 | J99: 0.689 | K99: 0.678 | L99: 1.024
A100: + LT Derivatives & Hedging | B100: BS_DERIVATIVE_&_HEDGING_LIABS_LT | C100: 0 | D100: 0 | E100: 0 | F100: 0 | G100: 0 | H100: 0 | I100: 0 | J100: 0 | K100: 0 | L100: 0
A101: + Liabilities of Discontinued Operations LT | B101: BS_LIABS_OF_DISCONTINUED_OPS_LT
A102: + Misc LT Liabilities | B102: OTHER_NONCURRENT_LIABS_DETAILED | C102: 23.02 | D102: 19.679 | E102: 19.769 | F102: 27.227 | G102: 20.806 | H102: 20.099 | I102: 15.256 | J102: 15.977 | K102: 18.143 | L102: 27.788
...

Sheet BS%
A1: ='Balance Sheet - Standardized'!A1 -> Ticker | C1: =IF('Balance Sheet - Standardized'!C1="","",'Balance Sheet - Standardized'!C1) -> LNN
A2: ='Balance Sheet - Standardized'!A2 -> Start Year | C2: ='Balance Sheet - Standardized'!C2 -> FY 2016
A3: ='Balance Sheet - Standardized'!A3 -> End Year
C4: ='Balance Sheet - Standardized'!C4 -> 42613 | D4: ='Balance Sheet - Standardized'!D4 -> 42978 | E4: ='Balance Sheet - Standardized'!E4 -> 43343 | F4: ='Balance Sheet - Standardized'!F4 -> 43708 | G4: ='Balance Sheet - Standardized'!G4 -> 44074 | H4: ='Balance Sheet - Standardized'!H4 -> 44439 | I4: ='Balance Sheet - Standardized'!I4 -> 44804 | J4: ='Balance Sheet - Standardized'!J4 -> 45169 | ... L4: ='Balance Sheet - Standardized'!L4 -> 45900
C5: ='Balance Sheet - Standardized'!C5 -> 2016 A | D5: ='Balance Sheet - Standardized'!D5 -> 2017 A | E5: ='Balance Sheet - Standardized'!E5 -> 2018 A | F5: ='Balance Sheet - Standardized'!F5 -> 2019 A | G5: ='Balance Sheet - Standardized'!G5 -> 2020 A | H5: ='Balance Sheet - Standardized'!H5 -> 2021 A | I5: ='Balance Sheet - Standardized'!I5 -> 2022 A | J5: ='Balance Sheet - Standardized'!J5 -> 2023 A | ... L5: ='Balance Sheet - Standardized'!L5 -> 2025 A
A7: ='Balance Sheet - Standardized'!A7 -> In Millions of USD except Per Share | C7: ='Balance Sheet - Standardized'!C7 -> FY 2016 | D7: ='Balance Sheet - Standardized'!D7 -> FY 2017 | E7: ='Balance Sheet - Standardized'!E7 -> FY 2018 | F7: ='Balance Sheet - Standardized'!F7 -> FY 2019 | G7: ='Balance Sheet - Standardized'!G7 -> FY 2020 | H7: ='Balance Sheet - Standardized'!H7 -> FY 2021 | I7: ='Balance Sheet - Standardized'!I7 -> FY 2022 | J7: ='Balance Sheet - Standardized'!J7 -> FY 2023 | ... L7: ='Balance Sheet - Standardized'!L7 -> FY 2025
A8: ='Balance Sheet - Standardized'!A8 -> 12 Months Ending | C8: ='Balance Sheet - Standardized'!C8 -> 42613 | D8: ='Balance Sheet - Standardized'!D8 -> 42978 | E8: ='Balance Sheet - Standardized'!E8 -> 43343 | F8: ='Balance Sheet - Standardized'!F8 -> 43708 | G8: ='Balance Sheet - Standardized'!G8 -> 44074 | H8: ='Balance Sheet - Standardized'!H8 -> 44439 | I8: ='Balance Sheet - Standardized'!I8 -> 44804 | J8: ='Balance Sheet - Standardized'!J8 -> 45169 | ... L8: ='Balance Sheet - Standardized'!L8 -> 45900
A9: ='Balance Sheet - Standardized'!A9 -> Total Assets
A10: ='Balance Sheet - Standardized'!A10 -> + Cash, Cash Equivalents & STI | B10: ='Balance Sheet - Standardized'!B10 -> C&CE_AND_STI_DETAILED | C10: =IF('Balance Sheet - Standardized'!C10="",0,'Balance Sheet - Standardized'!C10)/'Balance Sheet - Standardized'!C$61 -> 0.20767771 | D10: =IF('Balance Sheet - Standardized'!D10="",0,'Balance Sheet - Standardized'!D10)/'Balance Sheet - Standardized'!D$61 -> 0.24034053 | E10: =IF('Balance Sheet - Standardized'!E10="",0,'Balance Sheet - Standardized'!E10)/'Balance Sheet - Standardized'!E$61 -> 0.32140944 | F10: =IF('Balance Sheet - Standardized'!F10="",0,'Balance Sheet - Standardized'!F10)/'Balance Sheet - Standardized'!F$61 -> 0.25424833 | G10: =IF('Balance Sheet - Standardized'!G10="",0,'Balance Sheet - Standardized'!G10)/'Balance Sheet - Standardized'!G$61 -> 0.24698962 | H10: =IF('Balance Sheet - Standardized'!H10="",0,'Balance Sheet - Standardized'!H10)/'Balance Sheet - Standardized'!H$61 -> 0.23024867 | I10: =IF('Balance Sheet - Standardized'!I10="",0,'Balance Sheet - Standardized'!I10)/'Balance Sheet - Standardized'!I$61 -> 0.16394499 | J10: =IF('Balance Sheet - Standardized'!J10="",0,'Balance Sheet - Standardized'!J10)/'Balance Sheet - Standardized'!J$61 -> 0.22303865 | ... L10: =IF('Balance Sheet - Standardized'!L10="",0,'Balance Sheet - Standardized'!L10)/'Balance Sheet - Standardized'!L$61 -> 0.29800698
A11: ='Balance Sheet - Standardized'!A11 -> + Cash & Cash Equivalents | B11: ='Balance Sheet - Standardized'!B11 -> BS_CASH_NEAR_CASH_ITEM | C11: =IF('Balance Sheet - Standardized'!C11="",0,'Balance Sheet - Standardized'!C11)/'Balance Sheet - Standardized'!C$61 -> 0.20767771 | D11: =IF('Balance Sheet - Standardized'!D11="",0,'Balance Sheet - Standardized'!D11)/'Balance Sheet - Standardized'!D$61 -> 0.24034053 | E11: =IF('Balance Sheet - Standardized'!E11="",0,'Balance Sheet - Standardized'!E11)/'Balance Sheet - Standardized'!E$61 -> 0.32140944 | F11: =IF('Balance Sheet - Standardized'!F11="",0,'Balance Sheet - Standardized'!F11)/'Balance Sheet - Standardized'!F$61 -> 0.25424833 | G11: =IF('Balance Sheet - Standardized'!G11="",0,'Balance Sheet - Standardized'!G11)/'Balance Sheet - Standardized'!G$61 -> 0.21279135 | H11: =IF('Balance Sheet - Standardized'!H11="",0,'Balance Sheet - Standardized'!H11)/'Balance Sheet - Standardized'!H$61 -> 0.1994821 | I11: =IF('Balance Sheet - Standardized'!I11="",0,'Balance Sheet - Standardized'!I11)/'Balance Sheet - Standardized'!I$61 -> 0.14781898 | J11: =IF('Balance Sheet - Standardized'!J11="",0,'Balance Sheet - Standardized'!J11)/'Balance Sheet - Standardized'!J$61 -> 0.21558753 | ... L11: =IF('Balance Sheet - Standardized'!L11="",0,'Balance Sheet - Standardized'!L11)/'Balance Sheet - Standardized'!L$61 -> 0.29800698
A12: ='Balance Sheet - Standardized'!A12 -> + ST Investments | B12: ='Balance Sheet - Standardized'!B12 -> BS_MKT_SEC_OTHER_ST_INVEST | C12: =IF('Balance Sheet - Standardized'!C12="",0,'Balance Sheet - Standardized'!C12)/'Balance Sheet - Standardized'!C$61 -> 0 | D12: =IF('Balance Sheet - Standardized'!D12="",0,'Balance Sheet - Standardized'!D12)/'Balance Sheet - Standardized'!D$61 -> 0 | E12: =IF('Balance Sheet - Standardized'!E12="",0,'Balance Sheet - Standardized'!E12)/'Balance Sheet - Standardized'!E$61 -> 0 | F12: =IF('Balance Sheet - Standardized'!F12="",0,'Balance Sheet - Standardized'!F12)/'Balance Sheet - Standardized'!F$61 -> 0 | G12: =IF('Balance Sheet - Standardized'!G12="",0,'Balance Sheet - Standardized'!G12)/'Balance Sheet - Standardized'!G$61 -> 0.034198266 | H12: =IF('Balance Sheet - Standardized'!H12="",0,'Balance Sheet - Standardized'!H12)/'Balance Sheet - Standardized'!H$61 -> 0.030766575 | I12: =IF('Balance Sheet - Standardized'!I12="",0,'Balance Sheet - Standardized'!I12)/'Balance Sheet - Standardized'!I$61 -> 0.016126014 | J12: =IF('Balance Sheet - Standardized'!J12="",0,'Balance Sheet - Standardized'!J12)/'Balance Sheet - Standardized'!J$61 -> 0.0074511171 | ... L12: =IF('Balance Sheet - Standardized'!L12="",0,'Balance Sheet - Standardized'!L12)/'Balance Sheet - Standardized'!L$61 -> 0
A13: ='Balance Sheet - Standardized'!A13 -> check
A14: ='Balance Sheet - Standardized'!A14 -> + Accounts & Notes Receiv | B14: ='Balance Sheet - Standardized'!B14 -> BS_ACCT_NOTE_RCV | C14: =IF('Balance Sheet - Standardized'!C14="",0,'Balance Sheet - Standardized'!C14)/'Balance Sheet - Standardized'!C$61 -> 0.16534876 | D14: =IF('Balance Sheet - Standardized'!D14="",0,'Balance Sheet - Standardized'!D14)/'Balance Sheet - Standardized'!D$61 -> 0.14593939 | E14: =IF('Balance Sheet - Standardized'!E14="",0,'Balance Sheet - Standardized'!E14)/'Balance Sheet - Standardized'!E$61 -> 0.13814327 | F14: =IF('Balance Sheet - Standardized'!F14="",0,'Balance Sheet - Standardized'!F14)/'Balance Sheet - Standardized'!F$61 -> 0.15100717 | G14: =IF('Balance Sheet - Standardized'!G14="",0,'Balance Sheet - Standardized'!G14)/'Balance Sheet - Standardized'!G$61 -> 0.14829123 | H14: =IF('Balance Sheet - Standardized'!H14="",0,'Balance Sheet - Standardized'!H14)/'Balance Sheet - Standardized'!H$61 -> 0.14691024 | I14: =IF('Balance Sheet - Standardized'!I14="",0,'Balance Sheet - Standardized'!I14)/'Balance Sheet - Standardized'!I$61 -> 0.19446903 | J14: =IF('Balance Sheet - Standardized'!J14="",0,'Balance Sheet - Standardized'!J14)/'Balance Sheet - Standardized'!J$61 -> 0.19415551 | ... L14: =IF('Balance Sheet - Standardized'!L14="",0,'Balance Sheet - Standardized'!L14)/'Balance Sheet - Standardized'!L$61 -> 0.13442217
A15: ='Balance Sheet - Standardized'!A15 -> + Accounts Receivable, Net | B15: ='Balance Sheet - Standardized'!B15 -> BS_ACCTS_REC_EXCL_NOTES_REC | C15: =IF('Balance Sheet - Standardized'!C15="",0,'Balance Sheet - Standardized'!C15)/'Balance Sheet - Standardized'!C$61 -> 0.16534876 | D15: =IF('Balance Sheet - Standardized'!D15="",0,'Balance Sheet - Standardized'!D15)/'Balance Sheet - Standardized'!D$61 -> 0.14593939 | E15: =IF('Balance Sheet - Standardized'!E15="",0,'Balance Sheet - Standardized'!E15)/'Balance Sheet - Standardized'!E$61 -> 0.13814327 | F15: =IF('Balance Sheet - Standardized'!F15="",0,'Balance Sheet - Standardized'!F15)/'Balance Sheet - Standardized'!F$61 -> 0.15100717 | G15: =IF('Balance Sheet - Standardized'!G15="",0,'Balance Sheet - Standardized'!G15)/'Balance Sheet - Standardized'!G$61 -> 0.14829123 | H15: =IF('Balance Sheet - Standardized'!H15="",0,'Balance Sheet - Standardized'!H15)/'Balance Sheet - Standardized'!H$61 -> 0.14691024 | I15: =IF('Balance Sheet - Standardized'!I15="",0,'Balance Sheet - Standardized'!I15)/'Balance Sheet - Standardized'!I$61 -> 0.19446903 | J15: =IF('Balance Sheet - Standardized'!J15="",0,'Balance Sheet - Standardized'!J15)/'Balance Sheet - Standardized'!J$61 -> 0.19415551 | ... L15: =IF('Balance Sheet - Standardized'!L15="",0,'Balance Sheet - Standardized'!L15)/'Balance Sheet - Standardized'!L$61 -> 0.13442217
A16: ='Balance Sheet - Standardized'!A16 -> + Notes Receivable, Net | B16: ='Balance Sheet - Standardized'!B16 -> NOTES_RECEIVABLE | C16: =IF('Balance Sheet - Standardized'!C16="",0,'Balance Sheet - Standardized'!C16)/'Balance Sheet - Standardized'!C$61 -> 0 | D16: =IF('Balance Sheet - Standardized'!D16="",0,'Balance Sheet - Standardized'!D16)/'Balance Sheet - Standardized'!D$61 -> 0 | E16: =IF('Balance Sheet - Standardized'!E16="",0,'Balance Sheet - Standardized'!E16)/'Balance Sheet - Standardized'!E$61 -> 0 | F16: =IF('Balance Sheet - Standardized'!F16="",0,'Balance Sheet - Standardized'!F16)/'Balance Sheet - Standardized'!F$61 -> 0 | G16: =IF('Balance Sheet - Standardized'!G16="",0,'Balance Sheet - Standardized'!G16)/'Balance Sheet - Standardized'!G$61 -> 0 | H16: =IF('Balance Sheet - Standardized'!H16="",0,'Balance Sheet - Standardized'!H16)/'Balance Sheet - Standardized'!H$61 -> 0 | I16: =IF('Balance Sheet - Standardized'!I16="",0,'Balance Sheet - Standardized'!I16)/'Balance Sheet - Standardized'!I$61 -> 0 | J16: =IF('Balance Sheet - Standardized'!J16="",0,'Balance Sheet - Standardized'!J16)/'Balance Sheet - Standardized'!J$61 -> 0 | ... L16: =IF('Balance Sheet - Standardized'!L16="",0,'Balance Sheet - Standardized'!L16)/'Balance Sheet - Standardized'!L$61 -> 0
A17: ='Balance Sheet - Standardized'!A17 -> check
A18: ='Balance Sheet - Standardized'!A20 -> + Inventories | B18: ='Balance Sheet - Standardized'!B20 -> BS_INVENTORIES | C18: =IF('Balance Sheet - Standardized'!C20="",0,'Balance Sheet - Standardized'!C20)/'Balance Sheet - Standardized'!C$61 -> 0.15332862 | D18: =IF('Balance Sheet - Standardized'!D20="",0,'Balance Sheet - Standardized'!D20)/'Balance Sheet - Standardized'!D$61 -> 0.17025603 | E18: =IF('Balance Sheet - Standardized'!E20="",0,'Balance Sheet - Standardized'!E20)/'Balance Sheet - Standardized'!E$61 -> 0.15838491 | F18: =IF('Balance Sheet - Standardized'!F20="",0,'Balance Sheet - Standardized'!F20)/'Balance Sheet - Standardized'!F$61 -> 0.18445816 | G18: =IF('Balance Sheet - Standardized'!G20="",0,'Balance Sheet - Standardized'!G20)/'Balance Sheet - Standardized'!G$61 -> 0.18367612 | H18: =IF('Balance Sheet - Standardized'!H20="",0,'Balance Sheet - Standardized'!H20)/'Balance Sheet - Standardized'!H$61 -> 0.22794636 | I18: =IF('Balance Sheet - Standardized'!I20="",0,'Balance Sheet - Standardized'!I20)/'Balance Sheet - Standardized'!I$61 -> 0.27267316 | J18: =IF('Balance Sheet - Standardized'!J20="",0,'Balance Sheet - Standardized'!J20)/'Balance Sheet - Standardized'!J$61 -> 0.20911944 | ... L18: =IF('Balance Sheet - Standardized'!L20="",0,'Balance Sheet - Standardized'!L20)/'Balance Sheet - Standardized'!L$61 -> 0.16276539
A19: ='Balance Sheet - Standardized'!A21 -> + Raw Materials | B19: ='Balance Sheet - Standardized'!B21 -> INVTRY_RAW_MATERIALS | C19: =IF('Balance Sheet - Standardized'!C21="",0,'Balance Sheet - Standardized'!C21)/'Balance Sheet - Standardized'!C$61 -> 0.054560373 | D19: =IF('Balance Sheet - Standardized'!D21="",0,'Balance Sheet - Standardized'!D21)/'Balance Sheet - Standardized'!D$61 -> 0.061573181 | E19: =IF('Balance Sheet - Standardized'!E21="",0,'Balance Sheet - Standardized'!E21)/'Balance Sheet - Standardized'!E$61 -> 0.072594831 | F19: =IF('Balance Sheet - Standardized'!F21="",0,'Balance Sheet - Standardized'!F21)/'Balance Sheet - Standardized'!F$61 -> 0.098032436 | G19: =IF('Balance Sheet - Standardized'!G21="",0,'Balance Sheet - Standardized'!G21)/'Balance Sheet - Standardized'!G$61 -> 0.089750511 | H19: =IF('Balance Sheet - Standardized'!H21="",0,'Balance Sheet - Standardized'!H21)/'Balance Sheet - Standardized'!H$61 -> 0.10979857 | I19: =IF('Balance Sheet - Standardized'!I21="",0,'Balance Sheet - Standardized'!I21)/'Balance Sheet - Standardized'!I$61 -> 0.13152551 | J19: =IF('Balance Sheet - Standardized'!J21="",0,'Balance Sheet - Standardized'!J21)/'Balance Sheet - Standardized'!J$61 -> 0.1125285 | ... L19: =IF('Balance Sheet - Standardized'!L21="",0,'Balance Sheet - Standardized'!L21)/'Balance Sheet - Standardized'!L$61 -> 0.083857018
A20: ='Balance Sheet - Standardized'!A22 -> + Work In Process | B20: ='Balance Sheet - Standardized'!B22 -> INVTRY_IN_PROGRESS | C20: =IF('Balance Sheet - Standardized'!C22="",0,'Balance Sheet - Standardized'!C22)/'Balance Sheet - Standardized'!C$61 -> 0.011778099 | D20: =IF('Balance Sheet - Standardized'!D22="",0,'Balance Sheet - Standardized'!D22)/'Balance Sheet - Standardized'!D$61 -> 0.014056423 | E20: =IF('Balance Sheet - Standardized'!E22="",0,'Balance Sheet - Standardized'!E22)/'Balance Sheet - Standardized'!E$61 -> 0.018342609 | F20: =IF('Balance Sheet - Standardized'!F22="",0,'Balance Sheet - Standardized'!F22)/'Balance Sheet - Standardized'!F$61 -> 0.009022334 | G20: =IF('Balance Sheet - Standardized'!G22="",0,'Balance Sheet - Standardized'!G22)/'Balance Sheet - Standardized'!G$61 -> 0.011329896 | H20: =IF('Balance Sheet - Standardized'!H22="",0,'Balance Sheet - Standardized'!H22)/'Balance Sheet - Standardized'!H$61 -> 0.013027614 | I20: =IF('Balance Sheet - Standardized'!I22="",0,'Balance Sheet - Standardized'!I22)/'Balance Sheet - Standardized'!I$61 -> 0.017734394 | J20: =IF('Balance Sheet - Standardized'!J22="",0,'Balance Sheet - Standardized'!J22)/'Balance Sheet - Standardized'!J$61 -> 0.010487353 | ... L20: =IF('Balance Sheet - Standardized'!L22="",0,'Balance Sheet - Standardized'!L22)/'Balance Sheet - Standardized'!L$61 -> 0.0085462563
A21: ='Balance Sheet - Standardized'!A23 -> + Finished Goods | B21: ='Balance Sheet - Standardized'!B23 -> INVTRY_FINISHED_GOODS | C21: =IF('Balance Sheet - Standardized'!C23="",0,'Balance Sheet - Standardized'!C23)/'Balance Sheet - Standardized'!C$61 -> 0.098058521 | D21: =IF('Balance Sheet - Standardized'!D23="",0,'Balance Sheet - Standardized'!D23)/'Balance Sheet - Standardized'!D$61 -> 0.10351519 | E21: =IF('Balance Sheet - Standardized'!E23="",0,'Balance Sheet - Standardized'!E23)/'Balance Sheet - Standardized'!E$61 -> 0.080352859 | F21: =IF('Balance Sheet - Standardized'!F23="",0,'Balance Sheet - Standardized'!F23)/'Balance Sheet - Standardized'!F$61 -> 0.093565241 | G21: =IF('Balance Sheet - Standardized'!G23="",0,'Balance Sheet - Standardized'!G23)/'Balance Sheet - Standardized'!G$61 -> 0.090590087 | H21: =IF('Balance Sheet - Standardized'!H23="",0,'Balance Sheet - Standardized'!H23)/'Balance Sheet - Standardized'!H$61 -> 0.1177884 | I21: =IF('Balance Sheet - Standardized'!I23="",0,'Balance Sheet - Standardized'!I23)/'Balance Sheet - Standardized'!I$61 -> 0.15481817 | J21: =IF('Balance Sheet - Standardized'!J23="",0,'Balance Sheet - Standardized'!J23)/'Balance Sheet - Standardized'!J$61 -> 0.11639755 | ... L21: =IF('Balance Sheet - Standardized'!L23="",0,'Balance Sheet - Standardized'!L23)/'Balance Sheet - Standardized'!L$61 -> 0.093515263
A22: ='Balance Sheet - Standardized'!A24 -> + Other Inventory | B22: ='Balance Sheet - Standardized'!B24 -> BS_OTHER_INV | C22: =IF('Balance Sheet - Standardized'!C24="",0,'Balance Sheet - Standardized'!C24)/'Balance Sheet - Standardized'!C$61 -> -0.011068377 | D22: =IF('Balance Sheet - Standardized'!D24="",0,'Balance Sheet - Standardized'!D24)/'Balance Sheet - Standardized'!D$61 -> -0.0088887659 | E22: =IF('Balance Sheet - Standardized'!E24="",0,'Balance Sheet - Standardized'!E24)/'Balance Sheet - Standardized'!E$61 -> -0.012905392 | F22: =IF('Balance Sheet - Standardized'!F24="",0,'Balance Sheet - Standardized'!F24)/'Balance Sheet - Standardized'!F$61 -> -0.01616185 | G22: =IF('Balance Sheet - Standardized'!G24="",0,'Balance Sheet - Standardized'!G24)/'Balance Sheet - Standardized'!G$61 -> -0.0079943771 | H22: =IF('Balance Sheet - Standardized'!H24="",0,'Balance Sheet - Standardized'!H24)/'Balance Sheet - Standardized'!H$61 -> -0.01266822 | I22: =IF('Balance Sheet - Standardized'!I24="",0,'Balance Sheet - Standardized'!I24)/'Balance Sheet - Standardized'!I$61 -> -0.031404919 | J22: =IF('Balance Sheet - Standardized'!J24="",0,'Balance Sheet - Standardized'!J24)/'Balance Sheet - Standardized'!J$61 -> -0.030293968 | ... L22: =IF('Balance Sheet - Standardized'!L24="",0,'Balance Sheet - Standardized'!L24)/'Balance Sheet - Standardized'!L$61 -> -0.023153148
A23: ='Balance Sheet - Standardized'!A25 -> check
A24: ='Balance Sheet - Standardized'!A26 -> + Other ST Assets | B24: ='Balance Sheet - Standardized'!B26 -> OTHER_CURRENT_ASSETS_DETAILED | C24: =IF('Balance Sheet - Standardized'!C26="",0,'Balance Sheet - Standardized'!C26)/'Balance Sheet - Standardized'!C$61 -> 0.041371035 | D24: =IF('Balance Sheet - Standardized'!D26="",0,'Balance Sheet - Standardized'!D26)/'Balance Sheet - Standardized'!D$61 -> 0.022348389 | E24: =IF('Balance Sheet - Standardized'!E26="",0,'Balance Sheet - Standardized'!E26)/'Balance Sheet - Standardized'!E$61 -> 0.043825561 | F24: =IF('Balance Sheet - Standardized'!F26="",0,'Balance Sheet - Standardized'!F26)/'Balance Sheet - Standardized'!F$61 -> 0.036872844 | G24: =IF('Balance Sheet - Standardized'!G26="",0,'Balance Sheet - Standardized'!G26)/'Balance Sheet - Standardized'!G$61 -> 0.030892545 | H24: =IF('Balance Sheet - Standardized'!H26="",0,'Balance Sheet - Standardized'!H26)/'Balance Sheet - Standardized'!H$61 -> 0.047927996 | I24: =IF('Balance Sheet - Standardized'!I26="",0,'Balance Sheet - Standardized'!I26)/'Balance Sheet - Standardized'!I$61 -> 0.040268598 | J24: =IF('Balance Sheet - Standardized'!J26="",0,'Balance Sheet - Standardized'!J26)/'Balance Sheet - Standardized'!J$61 -> 0.027448167 | ... L24: =IF('Balance Sheet - Standardized'!L26="",0,'Balance Sheet - Standardized'!L26)/'Balance Sheet - Standardized'!L$61 -> 0.038417718
A25: ='Balance Sheet - Standardized'!A27 -> + Prepaid Expenses | B25: ='Balance Sheet - Standardized'!B27 -> BS_PREPAY | C25: =IF('Balance Sheet - Standardized'!C27="",0,'Balance Sheet - Standardized'!C27)/'Balance Sheet - Standardized'!C$61 -> 0.0075300247 | D25: =IF('Balance Sheet - Standardized'!D27="",0,'Balance Sheet - Standardized'!D27)/'Balance Sheet - Standardized'!D$61 -> 0.0086634837 | E25: =IF('Balance Sheet - Standardized'!E27="",0,'Balance Sheet - Standardized'!E27)/'Balance Sheet - Standardized'!E$61 -> 0.0077620258 | F25: =IF('Balance Sheet - Standardized'!F27="",0,'Balance Sheet - Standardized'!F27)/'Balance Sheet - Standardized'!F$61 -> 0 | G25: =IF('Balance Sheet - Standardized'!G27="",0,'Balance Sheet - Standardized'!G27)/'Balance Sheet - Standardized'!G$61 -> 0 | H25: =IF('Balance Sheet - Standardized'!H27="",0,'Balance Sheet - Standardized'!H27)/'Balance Sheet - Standardized'!H$61 -> 0 | I25: =IF('Balance Sheet - Standardized'!I27="",0,'Balance Sheet - Standardized'!I27)/'Balance Sheet - Standardized'!I$61 -> 0 | J25: =IF('Balance Sheet - Standardized'!J27="",0,'Balance Sheet - Standardized'!J27)/'Balance Sheet - Standardized'!J$61 -> 0 | ... L25: =IF('Balance Sheet - Standardized'!L27="",0,'Balance Sheet - Standardized'!L27)/'Balance Sheet - Standardized'!L$61 -> 0
A26: ='Balance Sheet - Standardized'!A28 -> + ST Derivative & Hedging Assets | B26: ='Balance Sheet - Standardized'!B28 -> BS_DERIV_&_HEDGING_ASSETS_ST | C26: =IF('Balance Sheet - Standardized'!C28="",0,'Balance Sheet - Standardized'!C28)/'Balance Sheet - Standardized'!C$61 -> 0.00014973898 | D26: =IF('Balance Sheet - Standardized'!D28="",0,'Balance Sheet - Standardized'!D28)/'Balance Sheet - Standardized'!D$61 -> 1.7785436e-05 | E26: =IF('Balance Sheet - Standardized'!E28="",0,'Balance Sheet - Standardized'!E28)/'Balance Sheet - Standardized'!E$61 -> 0.0017950809 | F26: =IF('Balance Sheet - Standardized'!F28="",0,'Balance Sheet - Standardized'!F28)/'Balance Sheet - Standardized'!F$61 -> 0.0022226042 | G26: =IF('Balance Sheet - Standardized'!G28="",0,'Balance Sheet - Standardized'!G28)/'Balance Sheet - Standardized'!G$61 -> 3.6808138e-05 | H26: =IF('Balance Sheet - Standardized'!H28="",0,'Balance Sheet - Standardized'!H28)/'Balance Sheet - Standardized'!H$61 -> 0 | I26: =IF('Balance Sheet - Standardized'!I28="",0,'Balance Sheet - Standardized'!I28)/'Balance Sheet - Standardized'!I$61 -> 0 | J26: =IF('Balance Sheet - Standardized'!J28="",0,'Balance Sheet - Standardized'!J28)/'Balance Sheet - Standardized'!J$61 -> 0 | ... L26: =IF('Balance Sheet - Standardized'!L28="",0,'Balance Sheet - Standardized'!L28)/'Balance Sheet - Standardized'!L$61 -> 0
A27: ='Balance Sheet - Standardized'!A29 -> + Assets Held-for-Sale | B27: ='Balance Sheet - Standardized'!B29 -> BS_ASSETS_HELD_FOR_SALE_ST | C27: =IF('Balance Sheet - Standardized'!C29="",0,'Balance Sheet - Standardized'!C29)/'Balance Sheet - Standardized'!C$61 -> 0 | D27: =IF('Balance Sheet - Standardized'!D29="",0,'Balance Sheet - Standardized'!D29)/'Balance Sheet - Standardized'!D$61 -> 0 | E27: =IF('Balance Sheet - Standardized'!E29="",0,'Balance Sheet - Standardized'!E29)/'Balance Sheet - Standardized'!E$61 -> 0.021662909 | F27: =IF('Balance Sheet - Standardized'!F29="",0,'Balance Sheet - Standardized'!F29)/'Balance Sheet - Standardized'!F$61 -> 0.0054845557 | G27: =IF('Balance Sheet - Standardized'!G29="",0,'Balance Sheet - Standardized'!G29)/'Balance Sheet - Standardized'!G$61 -> 0 | H27: =IF('Balance Sheet - Standardized'!H29="",0,'Balance Sheet - Standardized'!H29)/'Balance Sheet - Standardized'!H$61 -> 0 | I27: =IF('Balance Sheet - Standardized'!I29="",0,'Balance Sheet - Standardized'!I29)/'Balance Sheet - Standardized'!I$61 -> 0 | J27: =IF('Balance Sheet - Standardized'!J29="",0,'Balance Sheet - Standardized'!J29)/'Balance Sheet - Standardized'!J$61 -> 0 | ... L27: =IF('Balance Sheet - Standardized'!L29="",0,'Balance Sheet - Standardized'!L29)/'Balance Sheet - Standardized'!L$61 -> 0
A28: ='Balance Sheet - Standardized'!A30 -> + ST Deferred Tax Assets | B28: ='Balance Sheet - Standardized'!B30 -> BS_DEFERRED_TAX_ASSETS_ST | C28: =IF('Balance Sheet - Standardized'!C30="",0,'Balance Sheet - Standardized'!C30)/'Balance Sheet - Standardized'!C$61 -> 0 | D28: =IF('Balance Sheet - Standardized'!D30="",0,'Balance Sheet - Standardized'!D30)/'Balance Sheet - Standardized'!D$61 -> 0 | E28: =IF('Balance Sheet - Standardized'!E30="",0,'Balance Sheet - Standardized'!E30)/'Balance Sheet - Standardized'!E$61 -> 0 | F28: =IF('Balance Sheet - Standardized'!F30="",0,'Balance Sheet - Standardized'!F30)/'Balance Sheet - Standardized'!F$61 -> 0 | G28: =IF('Balance Sheet - Standardized'!G30="",0,'Balance Sheet - Standardized'!G30)/'Balance Sheet - Standardized'!G$61 -> 0 | H28: =IF('Balance Sheet - Standardized'!H30="",0,'Balance Sheet - Standardized'!H30)/'Balance Sheet - Standardized'!H$61 -> 0 | I28: =IF('Balance Sheet - Standardized'!I30="",0,'Balance Sheet - Standardized'!I30)/'Balance Sheet - Standardized'!I$61 -> 0 | J28: =IF('Balance Sheet - Standardized'!J30="",0,'Balance Sheet - Standardized'!J30)/'Balance Sheet - Standardized'!J$61 -> 0 | ... L28: =IF('Balance Sheet - Standardized'!L30="",0,'Balance Sheet - Standardized'!L30)/'Balance Sheet - Standardized'!L$61 -> 0
A29: ='Balance Sheet - Standardized'!A31 -> + Taxes Receivable | B29: ='Balance Sheet - Standardized'!B31 -> BS_TAXES_RECEIVABLE_SHORT_TERM | C29: =IF('Balance Sheet - Standardized'!C31="",0,'Balance Sheet - Standardized'!C31)/'Balance Sheet - Standardized'!C$61 -> 0 | D29: =IF('Balance Sheet - Standardized'!D31="",0,'Balance Sheet - Standardized'!D31)/'Balance Sheet - Standardized'!D$61 -> 0 | E29: =IF('Balance Sheet - Standardized'!E31="",0,'Balance Sheet - Standardized'!E31)/'Balance Sheet - Standardized'!E$61 -> 0 | F29: =IF('Balance Sheet - Standardized'!F31="",0,'Balance Sheet - Standardized'!F31)/'Balance Sheet - Standardized'!F$61 -> 0 | G29: =IF('Balance Sheet - Standardized'!G31="",0,'Balance Sheet - Standardized'!G31)/'Balance Sheet - Standardized'!G$61 -> 0 | H29: =IF('Balance Sheet - Standardized'!H31="",0,'Balance Sheet - Standardized'!H31)/'Balance Sheet - Standardized'!H$61 -> 0 | I29: =IF('Balance Sheet - Standardized'!I31="",0,'Balance Sheet - Standardized'!I31)/'Balance Sheet - Standardized'!I$61 -> 0 | J29: =IF('Balance Sheet - Standardized'!J31="",0,'Balance Sheet - Standardized'!J31)/'Balance Sheet - Standardized'!J$61 -> 0 | ... L29: =IF('Balance Sheet - Standardized'!L31="",0,'Balance Sheet - Standardized'!L31)/'Balance Sheet - Standardized'!L$61 -> 0
A30: + Assets of Discontinued Operations ST | B30: ='Balance Sheet - Standardized'!B32 -> BS_ASSETS_OF_DISCONTINUED_OPS_ST | C30: =IF('Balance Sheet - Standardized'!C32="",0,'Balance Sheet - Standardized'!C32)/'Balance Sheet - Standardized'!C$61 -> 0 | D30: =IF('Balance Sheet - Standardized'!D32="",0,'Balance Sheet - Standardized'!D32)/'Balance Sheet - Standardized'!D$61 -> 0 | E30: =IF('Balance Sheet - Standardized'!E32="",0,'Balance Sheet - Standardized'!E32)/'Balance Sheet - Standardized'!E$61 -> 0 | F30: =IF('Balance Sheet - Standardized'!F32="",0,'Balance Sheet - Standardized'!F32)/'Balance Sheet - Standardized'!F$61 -> 0 | G30: =IF('Balance Sheet - Standardized'!G32="",0,'Balance Sheet - Standardized'!G32)/'Balance Sheet - Standardized'!G$61 -> 0 | H30: =IF('Balance Sheet - Standardized'!H32="",0,'Balance Sheet - Standardized'!H32)/'Balance Sheet - Standardized'!H$61 -> 0 | I30: =IF('Balance Sheet - Standardized'!I32="",0,'Balance Sheet - Standardized'!I32)/'Balance Sheet - Standardized'!I$61 -> 0 | J30: =IF('Balance Sheet - Standardized'!J32="",0,'Balance Sheet - Standardized'!J32)/'Balance Sheet - Standardized'!J$61 -> 0 | ... L30: =IF('Balance Sheet - Standardized'!L32="",0,'Balance Sheet - Standardized'!L32)/'Balance Sheet - Standardized'!L$61 -> 0
A31: ='Balance Sheet - Standardized'!A33 -> + Misc ST Assets | B31: ='Balance Sheet - Standardized'!B33 -> BS_OTHER_CUR_ASSET_LESS_PREPAY | C31: =IF('Balance Sheet - Standardized'!C33="",0,'Balance Sheet - Standardized'!C33)/'Balance Sheet - Standardized'!C$61 -> 0.033691271 | D31: =IF('Balance Sheet - Standardized'!D33="",0,'Balance Sheet - Standardized'!D33)/'Balance Sheet - Standardized'!D$61 -> 0.01366712 | E31: =IF('Balance Sheet - Standardized'!E33="",0,'Balance Sheet - Standardized'!E33)/'Balance Sheet - Standardized'!E$61 -> 0.012605546 | F31: =IF('Balance Sheet - Standardized'!F33="",0,'Balance Sheet - Standardized'!F33)/'Balance Sheet - Standardized'!F$61 -> 0.029165684 | G31: =IF('Balance Sheet - Standardized'!G33="",0,'Balance Sheet - Standardized'!G33)/'Balance Sheet - Standardized'!G$61 -> 0.030855737 | H31: =IF('Balance Sheet - Standardized'!H33="",0,'Balance Sheet - Standardized'!H33)/'Balance Sheet - Standardized'!H$61 -> 0.047927996 | I31: =IF('Balance Sheet - Standardized'!I33="",0,'Balance Sheet - Standardized'!I33)/'Balance Sheet - Standardized'!I$61 -> 0.040268598 | J31: =IF('Balance Sheet - Standardized'!J33="",0,'Balance Sheet - Standardized'!J33)/'Balance Sheet - Standardized'!J$61 -> 0.027448167 | ... L31: =IF('Balance Sheet - Standardized'!L33="",0,'Balance Sheet - Standardized'!L33)/'Balance Sheet - Standardized'!L$61 -> 0.038417718
A32: ='Balance Sheet - Standardized'!A34 -> check
A33: ='Balance Sheet - Standardized'!A35 -> Total Current Assets | B33: ='Balance Sheet - Standardized'!B35 -> BS_CUR_ASSET_REPORT | C33: =IF('Balance Sheet - Standardized'!C35="",0,'Balance Sheet - Standardized'!C35)/'Balance Sheet - Standardized'!C$61 -> 0.56772612 | D33: =IF('Balance Sheet - Standardized'!D35="",0,'Balance Sheet - Standardized'!D35)/'Balance Sheet - Standardized'!D$61 -> 0.57888434 | E33: =IF('Balance Sheet - Standardized'!E35="",0,'Balance Sheet - Standardized'!E35)/'Balance Sheet - Standardized'!E$61 -> 0.66176318 | F33: =IF('Balance Sheet - Standardized'!F35="",0,'Balance Sheet - Standardized'!F35)/'Balance Sheet - Standardized'!F$61 -> 0.6265865 | G33: =IF('Balance Sheet - Standardized'!G35="",0,'Balance Sheet - Standardized'!G35)/'Balance Sheet - Standardized'!G$61 -> 0.60984951 | H33: =IF('Balance Sheet - Standardized'!H35="",0,'Balance Sheet - Standardized'!H35)/'Balance Sheet - Standardized'!H$61 -> 0.65303326 | I33: =IF('Balance Sheet - Standardized'!I35="",0,'Balance Sheet - Standardized'!I35)/'Balance Sheet - Standardized'!I$61 -> 0.67135578 | J33: =IF('Balance Sheet - Standardized'!J35="",0,'Balance Sheet - Standardized'!J35)/'Balance Sheet - Standardized'!J$61 -> 0.65376177 | ... L33: =IF('Balance Sheet - Standardized'!L35="",0,'Balance Sheet - Standardized'!L35)/'Balance Sheet - Standardized'!L$61 -> 0.63361226
A34: ='Balance Sheet - Standardized'!A36 -> check
A35: ='Balance Sheet - Standardized'!A37 -> + Property, Plant & Equip, Net (As Reported) | B35: ='Balance Sheet - Standardized'!B37 -> ARD_PROPERTY_PLANT_EQUIP_NET | C35: =IF('Balance Sheet - Standardized'!C37="",0,'Balance Sheet - Standardized'!C37)/'Balance Sheet - Standardized'!C$61 -> 0.15922997 | D35: =IF('Balance Sheet - Standardized'!D37="",0,'Balance Sheet - Standardized'!D37)/'Balance Sheet - Standardized'!D$61 -> 0.14721994 | E35: =IF('Balance Sheet - Standardized'!E37="",0,'Balance Sheet - Standardized'!E37)/'Balance Sheet - Standardized'!E$61 -> 0.11443741 | F35: =IF('Balance Sheet - Standardized'!F37="",0,'Balance Sheet - Standardized'!F37)/'Balance Sheet - Standardized'!F$61 -> 0.13784943 | G35: =IF('Balance Sheet - Standardized'!G37="",0,'Balance Sheet - Standardized'!G37)/'Balance Sheet - Standardized'!G$61 -> 0.13948707 | H35: =IF('Balance Sheet - Standardized'!H37="",0,'Balance Sheet - Standardized'!H37)/'Balance Sheet - Standardized'!H$61 -> 0.14438036 | I35: =IF('Balance Sheet - Standardized'!I37="",0,'Balance Sheet - Standardized'!I37)/'Balance Sheet - Standardized'!I$61 -> 0.13293689 | J35: =IF('Balance Sheet - Standardized'!J37="",0,'Balance Sheet - Standardized'!J37)/'Balance Sheet - Standardized'!J$61 -> 0.13368157 | ... L35: =IF('Balance Sheet - Standardized'!L37="",0,'Balance Sheet - Standardized'!L37)/'Balance Sheet - Standardized'!L$61 -> 0.16924466
A36: ='Balance Sheet - Standardized'!A38 -> + Property, Plant & Equip, Net (Standardized) | B36: ='Balance Sheet - Standardized'!B38 -> BS_NET_FIX_ASSET | C36: =IF('Balance Sheet - Standardized'!C38="",0,'Balance Sheet - Standardized'!C38)/'Balance Sheet - Standardized'!C$61 -> 0.15922997 | D36: =IF('Balance Sheet - Standardized'!D38="",0,'Balance Sheet - Standardized'!D38)/'Balance Sheet - Standardized'!D$61 -> 0.14721994 | E36: =IF('Balance Sheet - Standardized'!E38="",0,'Balance Sheet - Standardized'!E38)/'Balance Sheet - Standardized'!E$61 -> 0.11443741 | F36: =IF('Balance Sheet - Standardized'!F38="",0,'Balance Sheet - Standardized'!F38)/'Balance Sheet - Standardized'!F$61 -> 0.13784943 | G36: =IF('Balance Sheet - Standardized'!G38="",0,'Balance Sheet - Standardized'!G38)/'Balance Sheet - Standardized'!G$61 -> 0.18761283 | H36: =IF('Balance Sheet - Standardized'!H38="",0,'Balance Sheet - Standardized'!H38)/'Balance Sheet - Standardized'!H$61 -> 0.17307062 | I36: =IF('Balance Sheet - Standardized'!I38="",0,'Balance Sheet - Standardized'!I38)/'Balance Sheet - Standardized'!I$61 -> 0.15992756 | J36: =IF('Balance Sheet - Standardized'!J38="",0,'Balance Sheet - Standardized'!J38)/'Balance Sheet - Standardized'!J$61 -> 0.15652844 | ... L36: =IF('Balance Sheet - Standardized'!L38="",0,'Balance Sheet - Standardized'!L38)/'Balance Sheet - Standardized'!L$61 -> 0.19076609
A37: ='Balance Sheet - Standardized'!A39 -> + Property, Plant & Equip (Standardized) | B37: ='Balance Sheet - Standardized'!B39 -> BS_GROSS_FIX_ASSET | C37: =IF('Balance Sheet - Standardized'!C39="",0,'Balance Sheet - Standardized'!C39)/'Balance Sheet - Standardized'!C$61 -> 0.37474949 | D37: =IF('Balance Sheet - Standardized'!D39="",0,'Balance Sheet - Standardized'!D39)/'Balance Sheet - Standardized'!D$61 -> 0.37377083 | E37: =IF('Balance Sheet - Standardized'!E39="",0,'Balance Sheet - Standardized'!E39)/'Balance Sheet - Standardized'!E$61 -> 0.34272453 | F37: =IF('Balance Sheet - Standardized'!F39="",0,'Balance Sheet - Standardized'!F39)/'Balance Sheet - Standardized'!F$61 -> 0.37715315 | G37: =IF('Balance Sheet - Standardized'!G39="",0,'Balance Sheet - Standardized'!G39)/'Balance Sheet - Standardized'!G$61 -> 0.41288916 | H37: =IF('Balance Sheet - Standardized'!H39="",0,'Balance Sheet - Standardized'!H39)/'Balance Sheet - Standardized'!H$61 -> 0.38808352 | I37: =IF('Balance Sheet - Standardized'!I39="",0,'Balance Sheet - Standardized'!I39)/'Balance Sheet - Standardized'!I$61 -> 0.36608865 | J37: =IF('Balance Sheet - Standardized'!J39="",0,'Balance Sheet - Standardized'!J39)/'Balance Sheet - Standardized'!J$61 -> 0.36850173 | ... L37: =IF('Balance Sheet - Standardized'!L39="",0,'Balance Sheet - Standardized'!L39)/'Balance Sheet - Standardized'!L$61 -> 0.39621995
A38: ='Balance Sheet - Standardized'!A40 -> - Accumulated Depreciation (Standardized) | B38: ='Balance Sheet - Standardized'!B40 -> BS_ACCUM_DEPR | C38: =IF('Balance Sheet - Standardized'!C40="",0,'Balance Sheet - Standardized'!C40)/'Balance Sheet - Standardized'!C$61 -> 0.21551952 | D38: =IF('Balance Sheet - Standardized'!D40="",0,'Balance Sheet - Standardized'!D40)/'Balance Sheet - Standardized'!D$61 -> 0.22655089 | E38: =IF('Balance Sheet - Standardized'!E40="",0,'Balance Sheet - Standardized'!E40)/'Balance Sheet - Standardized'!E$61 -> 0.22828712 | F38: =IF('Balance Sheet - Standardized'!F40="",0,'Balance Sheet - Standardized'!F40)/'Balance Sheet - Standardized'!F$61 -> 0.23930372 | G38: =IF('Balance Sheet - Standardized'!G40="",0,'Balance Sheet - Standardized'!G40)/'Balance Sheet - Standardized'!G$61 -> 0.22527632 | H38: =IF('Balance Sheet - Standardized'!H40="",0,'Balance Sheet - Standardized'!H40)/'Balance Sheet - Standardized'!H$61 -> 0.21501291 | I38: =IF('Balance Sheet - Standardized'!I40="",0,'Balance Sheet - Standardized'!I40)/'Balance Sheet - Standardized'!I$61 -> 0.20616109 | J38: =IF('Balance Sheet - Standardized'!J40="",0,'Balance Sheet - Standardized'!J40)/'Balance Sheet - Standardized'!J$61 -> 0.21197329 | ... L38: =IF('Balance Sheet - Standardized'!L40="",0,'Balance Sheet - Standardized'!L40)/'Balance Sheet - Standardized'!L$61 -> 0.20545386
A39: ='Balance Sheet - Standardized'!A41 -> Operating Leases | C39: =IF('Balance Sheet - Standardized'!C41="",0,'Balance Sheet - Standardized'!C41)/'Balance Sheet - Standardized'!C$61 -> 0 | D39: =IF('Balance Sheet - Standardized'!D41="",0,'Balance Sheet - Standardized'!D41)/'Balance Sheet - Standardized'!D$61 -> 0 | E39: =IF('Balance Sheet - Standardized'!E41="",0,'Balance Sheet - Standardized'!E41)/'Balance Sheet - Standardized'!E$61 -> 0 | F39: =IF('Balance Sheet - Standardized'!F41="",0,'Balance Sheet - Standardized'!F41)/'Balance Sheet - Standardized'!F$61 -> 0 | G39: =IF('Balance Sheet - Standardized'!G41="",0,'Balance Sheet - Standardized'!G41)/'Balance Sheet - Standardized'!G$61 -> 0.048125765 | H39: =IF('Balance Sheet - Standardized'!H41="",0,'Balance Sheet - Standardized'!H41)/'Balance Sheet - Standardized'!H$61 -> 0.028690255 | I39: =IF('Balance Sheet - Standardized'!I41="",0,'Balance Sheet - Standardized'!I41)/'Balance Sheet - Standardized'!I$61 -> 0.026990669 | J39: =IF('Balance Sheet - Standardized'!J41="",0,'Balance Sheet - Standardized'!J41)/'Balance Sheet - Standardized'!J$61 -> 0.022846874 | ... L39: =IF('Balance Sheet - Standardized'!L41="",0,'Balance Sheet - Standardized'!L41)/'Balance Sheet - Standardized'!L$61 -> 0.021521438
A40: ='Balance Sheet - Standardized'!A42 -> check
A41: ='Balance Sheet - Standardized'!A43 -> + LT Investments & Receivables | B41: ='Balance Sheet - Standardized'!B43 -> BS_LT_INVEST | C41: =IF('Balance Sheet - Standardized'!C43="",0,'Balance Sheet - Standardized'!C43)/'Balance Sheet - Standardized'!C$61 -> 0 | D41: =IF('Balance Sheet - Standardized'!D43="",0,'Balance Sheet - Standardized'!D43)/'Balance Sheet - Standardized'!D$61 -> 0 | E41: =IF('Balance Sheet - Standardized'!E43="",0,'Balance Sheet - Standardized'!E43)/'Balance Sheet - Standardized'!E$61 -> 0 | F41: =IF('Balance Sheet - Standardized'!F43="",0,'Balance Sheet - Standardized'!F43)/'Balance Sheet - Standardized'!F$61 -> 0 | G41: =IF('Balance Sheet - Standardized'!G43="",0,'Balance Sheet - Standardized'!G43)/'Balance Sheet - Standardized'!G$61 -> 0 | H41: =IF('Balance Sheet - Standardized'!H43="",0,'Balance Sheet - Standardized'!H43)/'Balance Sheet - Standardized'!H$61 -> 0 | I41: =IF('Balance Sheet - Standardized'!I43="",0,'Balance Sheet - Standardized'!I43)/'Balance Sheet - Standardized'!I$61 -> 0 | J41: =IF('Balance Sheet - Standardized'!J43="",0,'Balance Sheet - Standardized'!J43)/'Balance Sheet - Standardized'!J$61 -> 0 | ... L41: =IF('Balance Sheet - Standardized'!L43="",0,'Balance Sheet - Standardized'!L43)/'Balance Sheet - Standardized'!L$61 -> 0
A42: ='Balance Sheet - Standardized'!A44 -> + LT Investments | B42: ='Balance Sheet - Standardized'!B44 -> BS_LONG_TERM_INVESTMENTS | C42: =IF('Balance Sheet - Standardized'!C44="",0,'Balance Sheet - Standardized'!C44)/'Balance Sheet - Standardized'!C$61 -> 0 | D42: =IF('Balance Sheet - Standardized'!D44="",0,'Balance Sheet - Standardized'!D44)/'Balance Sheet - Standardized'!D$61 -> 0 | E42: =IF('Balance Sheet - Standardized'!E44="",0,'Balance Sheet - Standardized'!E44)/'Balance Sheet - Standardized'!E$61 -> 0 | F42: =IF('Balance Sheet - Standardized'!F44="",0,'Balance Sheet - Standardized'!F44)/'Balance Sheet - Standardized'!F$61 -> 0 | G42: =IF('Balance Sheet - Standardized'!G44="",0,'Balance Sheet - Standardized'!G44)/'Balance Sheet - Standardized'!G$61 -> 0 | H42: =IF('Balance Sheet - Standardized'!H44="",0,'Balance Sheet - Standardized'!H44)/'Balance Sheet - Standardized'!H$61 -> 0 | I42: =IF('Balance Sheet - Standardized'!I44="",0,'Balance Sheet - Standardized'!I44)/'Balance Sheet - Standardized'!I$61 -> 0 | J42: =IF('Balance Sheet - Standardized'!J44="",0,'Balance Sheet - Standardized'!J44)/'Balance Sheet - Standardized'!J$61 -> 0 | ... L42: =IF('Balance Sheet - Standardized'!L44="",0,'Balance Sheet - Standardized'!L44)/'Balance Sheet - Standardized'!L$61 -> 0
A43: ='Balance Sheet - Standardized'!A45 -> + LT Marketable Securities | B43: ='Balance Sheet - Standardized'!B45 -> BS_LT_MARKETABLE_SECURITIES | C43: =IF('Balance Sheet - Standardized'!C45="",0,'Balance Sheet - Standardized'!C45)/'Balance Sheet - Standardized'!C$61 -> 0 | D43: =IF('Balance Sheet - Standardized'!D45="",0,'Balance Sheet - Standardized'!D45)/'Balance Sheet - Standardized'!D$61 -> 0 | E43: =IF('Balance Sheet - Standardized'!E45="",0,'Balance Sheet - Standardized'!E45)/'Balance Sheet - Standardized'!E$61 -> 0 | F43: =IF('Balance Sheet - Standardized'!F45="",0,'Balance Sheet - Standardized'!F45)/'Balance Sheet - Standardized'!F$61 -> 0 | G43: =IF('Balance Sheet - Standardized'!G45="",0,'Balance Sheet - Standardized'!G45)/'Balance Sheet - Standardized'!G$61 -> 0 | H43: =IF('Balance Sheet - Standardized'!H45="",0,'Balance Sheet - Standardized'!H45)/'Balance Sheet - Standardized'!H$61 -> 0 | I43: =IF('Balance Sheet - Standardized'!I45="",0,'Balance Sheet - Standardized'!I45)/'Balance Sheet - Standardized'!I$61 -> 0 | J43: =IF('Balance Sheet - Standardized'!J45="",0,'Balance Sheet - Standardized'!J45)/'Balance Sheet - Standardized'!J$61 -> 0 | ... L43: =IF('Balance Sheet - Standardized'!L45="",0,'Balance Sheet - Standardized'!L45)/'Balance Sheet - Standardized'!L$61 -> 0
A44: ='Balance Sheet - Standardized'!A46 -> check
A45: ='Balance Sheet - Standardized'!A47 -> + Other LT Assets | B45: ='Balance Sheet - Standardized'!B47 -> BS_OTHER_ASSETS_DEF_CHRG_OTHER | C45: =IF('Balance Sheet - Standardized'!C47="",0,'Balance Sheet - Standardized'!C47)/'Balance Sheet - Standardized'!C$61 -> 0.27304391 | D45: =IF('Balance Sheet - Standardized'!D47="",0,'Balance Sheet - Standardized'!D47)/'Balance Sheet - Standardized'!D$61 -> 0.27389572 | E45: =IF('Balance Sheet - Standardized'!E47="",0,'Balance Sheet - Standardized'!E47)/'Balance Sheet - Standardized'!E$61 -> 0.22379941 | F45: =IF('Balance Sheet - Standardized'!F47="",0,'Balance Sheet - Standardized'!F47)/'Balance Sheet - Standardized'!F$61 -> 0.23556407 | G45: =IF('Balance Sheet - Standardized'!G47="",0,'Balance Sheet - Standardized'!G47)/'Balance Sheet - Standardized'!G$61 -> 0.20253766 | H45: =IF('Balance Sheet - Standardized'!H47="",0,'Balance Sheet - Standardized'!H47)/'Balance Sheet - Standardized'!H$61 -> 0.17389612 | I45: =IF('Balance Sheet - Standardized'!I47="",0,'Balance Sheet - Standardized'!I47)/'Balance Sheet - Standardized'!I$61 -> 0.16871666 | J45: =IF('Balance Sheet - Standardized'!J47="",0,'Balance Sheet - Standardized'!J47)/'Balance Sheet - Standardized'!J$61 -> 0.18970979 | ... L45: =IF('Balance Sheet - Standardized'!L47="",0,'Balance Sheet - Standardized'!L47)/'Balance Sheet - Standardized'!L$61 -> 0.17562164
A46: ='Balance Sheet - Standardized'!A48 -> + Total Intangible Assets | B46: ='Balance Sheet - Standardized'!B48 -> BS_DISCLOSED_INTANGIBLES | C46: =IF('Balance Sheet - Standardized'!C48="",0,'Balance Sheet - Standardized'!C48)/'Balance Sheet - Standardized'!C$61 -> 0.2543573 | D46: =IF('Balance Sheet - Standardized'!D48="",0,'Balance Sheet - Standardized'!D48)/'Balance Sheet - Standardized'!D$61 -> 0.23701861 | E46: =IF('Balance Sheet - Standardized'!E48="",0,'Balance Sheet - Standardized'!E48)/'Balance Sheet - Standardized'!E$61 -> 0.18400179 | F46: =IF('Balance Sheet - Standardized'!F48="",0,'Balance Sheet - Standardized'!F48)/'Balance Sheet - Standardized'!F$61 -> 0.17742658 | G46: =IF('Balance Sheet - Standardized'!G48="",0,'Balance Sheet - Standardized'!G48)/'Balance Sheet - Standardized'!G$61 -> 0.16034501 | H46: =IF('Balance Sheet - Standardized'!H48="",0,'Balance Sheet - Standardized'!H48)/'Balance Sheet - Standardized'!H$61 -> 0.13863321 | I46: =IF('Balance Sheet - Standardized'!I48="",0,'Balance Sheet - Standardized'!I48)/'Balance Sheet - Standardized'!I$61 -> 0.12008392 | J46: =IF('Balance Sheet - Standardized'!J48="",0,'Balance Sheet - Standardized'!J48)/'Balance Sheet - Standardized'!J$61 -> 0.14864684 | ... L46: =IF('Balance Sheet - Standardized'!L48="",0,'Balance Sheet - Standardized'!L48)/'Balance Sheet - Standardized'!L$61 -> 0.12819385
A47: ='Balance Sheet - Standardized'!A49 -> + Goodwill | B47: ='Balance Sheet - Standardized'!B49 -> BS_GOODWILL | C47: =IF('Balance Sheet - Standardized'!C49="",0,'Balance Sheet - Standardized'!C49)/'Balance Sheet - Standardized'!C$61 -> 0.15753977 | D47: =IF('Balance Sheet - Standardized'!D49="",0,'Balance Sheet - Standardized'!D49)/'Balance Sheet - Standardized'!D$61 -> 0.15242317 | E47: =IF('Balance Sheet - Standardized'!E49="",0,'Balance Sheet - Standardized'!E49)/'Balance Sheet - Standardized'!E$61 -> 0.12927581 | F47: =IF('Balance Sheet - Standardized'!F49="",0,'Balance Sheet - Standardized'!F49)/'Balance Sheet - Standardized'!F$61 -> 0.12869318 | G47: =IF('Balance Sheet - Standardized'!G49="",0,'Balance Sheet - Standardized'!G49)/'Balance Sheet - Standardized'!G$61 -> 0.11919527 | H47: =IF('Balance Sheet - Standardized'!H49="",0,'Balance Sheet - Standardized'!H49)/'Balance Sheet - Standardized'!H$61 -> 0.10666918 | I47: =IF('Balance Sheet - Standardized'!I49="",0,'Balance Sheet - Standardized'!I49)/'Balance Sheet - Standardized'!I$61 -> 0.094462417 | J47: =IF('Balance Sheet - Standardized'!J49="",0,'Balance Sheet - Standardized'!J49)/'Balance Sheet - Standardized'!J$61 -> 0.11147306 | ... L47: =IF('Balance Sheet - Standardized'!L49="",0,'Balance Sheet - Standardized'!L49)/'Balance Sheet - Standardized'!L$61 -> 0.10044646
A48: ='Balance Sheet - Standardized'!A50 -> + Other Intangible Assets | B48: ='Balance Sheet - Standardized'!B50 -> OTHER_INTANGIBLE_ASSETS_DETAILED | C48: =IF('Balance Sheet - Standardized'!C50="",0,'Balance Sheet - Standardized'!C50)/'Balance Sheet - Standardized'!C$61 -> 0.096817534 | D48: =IF('Balance Sheet - Standardized'!D50="",0,'Balance Sheet - Standardized'!D50)/'Balance Sheet - Standardized'!D$61 -> 0.084595441 | E48: =IF('Balance Sheet - Standardized'!E50="",0,'Balance Sheet - Standardized'!E50)/'Balance Sheet - Standardized'!E$61 -> 0.05472598 | F48: =IF('Balance Sheet - Standardized'!F50="",0,'Balance Sheet - Standardized'!F50)/'Balance Sheet - Standardized'!F$61 -> 0.048733395 | G48: =IF('Balance Sheet - Standardized'!G50="",0,'Balance Sheet - Standardized'!G50)/'Balance Sheet - Standardized'!G$61 -> 0.041149746 | H48: =IF('Balance Sheet - Standardized'!H50="",0,'Balance Sheet - Standardized'!H50)/'Balance Sheet - Standardized'!H$61 -> 0.031964029 | I48: =IF('Balance Sheet - Standardized'!I50="",0,'Balance Sheet - Standardized'!I50)/'Balance Sheet - Standardized'!I$61 -> 0.025621506 | J48: =IF('Balance Sheet - Standardized'!J50="",0,'Balance Sheet - Standardized'!J50)/'Balance Sheet - Standardized'!J$61 -> 0.037173779 | ... L48: =IF('Balance Sheet - Standardized'!L50="",0,'Balance Sheet - Standardized'!L50)/'Balance Sheet - Standardized'!L$61 -> 0.027747385
A49: ='Balance Sheet - Standardized'!A51 -> + Prepaid Expense | B49: ='Balance Sheet - Standardized'!B51 -> BS_PREPAID_EXPENSE_LT | C49: =IF('Balance Sheet - Standardized'!C51="",0,'Balance Sheet - Standardized'!C51)/'Balance Sheet - Standardized'!C$61 -> 0 | D49: =IF('Balance Sheet - Standardized'!D51="",0,'Balance Sheet - Standardized'!D51)/'Balance Sheet - Standardized'!D$61 -> 0 | E49: =IF('Balance Sheet - Standardized'!E51="",0,'Balance Sheet - Standardized'!E51)/'Balance Sheet - Standardized'!E$61 -> 0 | F49: =IF('Balance Sheet - Standardized'!F51="",0,'Balance Sheet - Standardized'!F51)/'Balance Sheet - Standardized'!F$61 -> 0 | G49: =IF('Balance Sheet - Standardized'!G51="",0,'Balance Sheet - Standardized'!G51)/'Balance Sheet - Standardized'!G$61 -> 0 | H49: =IF('Balance Sheet - Standardized'!H51="",0,'Balance Sheet - Standardized'!H51)/'Balance Sheet - Standardized'!H$61 -> 0 | I49: =IF('Balance Sheet - Standardized'!I51="",0,'Balance Sheet - Standardized'!I51)/'Balance Sheet - Standardized'!I$61 -> 0 | J49: =IF('Balance Sheet - Standardized'!J51="",0,'Balance Sheet - Standardized'!J51)/'Balance Sheet - Standardized'!J$61 -> 0 | ... L49: =IF('Balance Sheet - Standardized'!L51="",0,'Balance Sheet - Standardized'!L51)/'Balance Sheet - Standardized'!L$61 -> 0
A50: ='Balance Sheet - Standardized'!A52 -> + LT Deferred Tax Assets | B50: ='Balance Sheet - Standardized'!B52 -> BS_DEFERRED_TAX_ASSETS_LT | C50: =IF('Balance Sheet - Standardized'!C52="",0,'Balance Sheet - Standardized'!C52)/'Balance Sheet - Standardized'!C$61 -> 0.0086664 | D50: =IF('Balance Sheet - Standardized'!D52="",0,'Balance Sheet - Standardized'!D52)/'Balance Sheet - Standardized'!D$61 -> 0.010495384 | E50: =IF('Balance Sheet - Standardized'!E52="",0,'Balance Sheet - Standardized'!E52)/'Balance Sheet - Standardized'!E$61 -> 0.013283199 | F50: =IF('Balance Sheet - Standardized'!F52="",0,'Balance Sheet - Standardized'!F52)/'Balance Sheet - Standardized'!F$61 -> 0.023501241 | G50: =IF('Balance Sheet - Standardized'!G52="",0,'Balance Sheet - Standardized'!G52)/'Balance Sheet - Standardized'!G$61 -> 0.017413755 | H50: =IF('Balance Sheet - Standardized'!H52="",0,'Balance Sheet - Standardized'!H52)/'Balance Sheet - Standardized'!H$61 -> 0.012732566 | I50: =IF('Balance Sheet - Standardized'!I52="",0,'Balance Sheet - Standardized'!I52)/'Balance Sheet - Standardized'!I$61 -> 0.013104849 | J50: =IF('Balance Sheet - Standardized'!J52="",0,'Balance Sheet - Standardized'!J52)/'Balance Sheet - Standardized'!J$61 -> 0.014597806 | ... L50: =IF('Balance Sheet - Standardized'!L52="",0,'Balance Sheet - Standardized'!L52)/'Balance Sheet - Standardized'!L$61 -> 0.023220937
A51: ='Balance Sheet - Standardized'!A53 -> + LT Derivative & Hedging Assets | B51: ='Balance Sheet - Standardized'!B53 -> BS_DERIV_&_HEDGING_ASSETS_LT | C51: =IF('Balance Sheet - Standardized'!C53="",0,'Balance Sheet - Standardized'!C53)/'Balance Sheet - Standardized'!C$61 -> 0 | D51: =IF('Balance Sheet - Standardized'!D53="",0,'Balance Sheet - Standardized'!D53)/'Balance Sheet - Standardized'!D$61 -> 0 | E51: =IF('Balance Sheet - Standardized'!E53="",0,'Balance Sheet - Standardized'!E53)/'Balance Sheet - Standardized'!E$61 -> 0 | F51: =IF('Balance Sheet - Standardized'!F53="",0,'Balance Sheet - Standardized'!F53)/'Balance Sheet - Standardized'!F$61 -> 0 | G51: =IF('Balance Sheet - Standardized'!G53="",0,'Balance Sheet - Standardized'!G53)/'Balance Sheet - Standardized'!G$61 -> 0 | H51: =IF('Balance Sheet - Standardized'!H53="",0,'Balance Sheet - Standardized'!H53)/'Balance Sheet - Standardized'!H$61 -> 0 | I51: =IF('Balance Sheet - Standardized'!I53="",0,'Balance Sheet - Standardized'!I53)/'Balance Sheet - Standardized'!I$61 -> 0 | J51: =IF('Balance Sheet - Standardized'!J53="",0,'Balance Sheet - Standardized'!J53)/'Balance Sheet - Standardized'!J$61 -> 0 | ... L51: =IF('Balance Sheet - Standardized'!L53="",0,'Balance Sheet - Standardized'!L53)/'Balance Sheet - Standardized'!L$61 -> 0
A52: ='Balance Sheet - Standardized'!A54 -> + Prepaid Pension Costs | B52: ='Balance Sheet - Standardized'!B54 -> BS_PREPAID_PENSION_COSTS_LT | C52: =IF('Balance Sheet - Standardized'!C54="",0,'Balance Sheet - Standardized'!C54)/'Balance Sheet - Standardized'!C$61 -> 0 | D52: =IF('Balance Sheet - Standardized'!D54="",0,'Balance Sheet - Standardized'!D54)/'Balance Sheet - Standardized'!D$61 -> 0 | E52: =IF('Balance Sheet - Standardized'!E54="",0,'Balance Sheet - Standardized'!E54)/'Balance Sheet - Standardized'!E$61 -> 0 | F52: =IF('Balance Sheet - Standardized'!F54="",0,'Balance Sheet - Standardized'!F54)/'Balance Sheet - Standardized'!F$61 -> 0 | G52: =IF('Balance Sheet - Standardized'!G54="",0,'Balance Sheet - Standardized'!G54)/'Balance Sheet - Standardized'!G$61 -> 0 | H52: =IF('Balance Sheet - Standardized'!H54="",0,'Balance Sheet - Standardized'!H54)/'Balance Sheet - Standardized'!H$61 -> 0 | I52: =IF('Balance Sheet - Standardized'!I54="",0,'Balance Sheet - Standardized'!I54)/'Balance Sheet - Standardized'!I$61 -> 0 | J52: =IF('Balance Sheet - Standardized'!J54="",0,'Balance Sheet - Standardized'!J54)/'Balance Sheet - Standardized'!J$61 -> 0 | ... L52: =IF('Balance Sheet - Standardized'!L54="",0,'Balance Sheet - Standardized'!L54)/'Balance Sheet - Standardized'!L$61 -> 0
A53: ='Balance Sheet - Standardized'!A55 -> + Investments in Affiliates | B53: ='Balance Sheet - Standardized'!B55 -> BS_INVEST_IN_ASSOC_CO | C53: =IF('Balance Sheet - Standardized'!C55="",0,'Balance Sheet - Standardized'!C55)/'Balance Sheet - Standardized'!C$61 -> 0 | D53: =IF('Balance Sheet - Standardized'!D55="",0,'Balance Sheet - Standardized'!D55)/'Balance Sheet - Standardized'!D$61 -> 0 | E53: =IF('Balance Sheet - Standardized'!E55="",0,'Balance Sheet - Standardized'!E55)/'Balance Sheet - Standardized'!E$61 -> 0 | F53: =IF('Balance Sheet - Standardized'!F55="",0,'Balance Sheet - Standardized'!F55)/'Balance Sheet - Standardized'!F$61 -> 0 | G53: =IF('Balance Sheet - Standardized'!G55="",0,'Balance Sheet - Standardized'!G55)/'Balance Sheet - Standardized'!G$61 -> 0 | H53: =IF('Balance Sheet - Standardized'!H55="",0,'Balance Sheet - Standardized'!H55)/'Balance Sheet - Standardized'!H$61 -> 0 | I53: =IF('Balance Sheet - Standardized'!I55="",0,'Balance Sheet - Standardized'!I55)/'Balance Sheet - Standardized'!I$61 -> 0 | J53: =IF('Balance Sheet - Standardized'!J55="",0,'Balance Sheet - Standardized'!J55)/'Balance Sheet - Standardized'!J$61 -> 0 | ... L53: =IF('Balance Sheet - Standardized'!L55="",0,'Balance Sheet - Standardized'!L55)/'Balance Sheet - Standardized'!L$61 -> 0
A54: ='Balance Sheet - Standardized'!A56 -> + Assets of Discontinued Operations LT | B54: ='Balance Sheet - Standardized'!B56 -> BS_ASSETS_OF_DISCONTINUED_OPS_LT | C54: =IF('Balance Sheet - Standardized'!C56="",0,'Balance Sheet - Standardized'!C56)/'Balance Sheet - Standardized'!C$61 -> 0 | D54: =IF('Balance Sheet - Standardized'!D56="",0,'Balance Sheet - Standardized'!D56)/'Balance Sheet - Standardized'!D$61 -> 0 | E54: =IF('Balance Sheet - Standardized'!E56="",0,'Balance Sheet - Standardized'!E56)/'Balance Sheet - Standardized'!E$61 -> 0 | F54: =IF('Balance Sheet - Standardized'!F56="",0,'Balance Sheet - Standardized'!F56)/'Balance Sheet - Standardized'!F$61 -> 0 | G54: =IF('Balance Sheet - Standardized'!G56="",0,'Balance Sheet - Standardized'!G56)/'Balance Sheet - Standardized'!G$61 -> 0 | H54: =IF('Balance Sheet - Standardized'!H56="",0,'Balance Sheet - Standardized'!H56)/'Balance Sheet - Standardized'!H$61 -> 0 | I54: =IF('Balance Sheet - Standardized'!I56="",0,'Balance Sheet - Standardized'!I56)/'Balance Sheet - Standardized'!I$61 -> 0 | J54: =IF('Balance Sheet - Standardized'!J56="",0,'Balance Sheet - Standardized'!J56)/'Balance Sheet - Standardized'!J$61 -> 0 | ... L54: =IF('Balance Sheet - Standardized'!L56="",0,'Balance Sheet - Standardized'!L56)/'Balance Sheet - Standardized'!L$61 -> 0
A55: ='Balance Sheet - Standardized'!A57 -> + Misc LT Assets | B55: ='Balance Sheet - Standardized'!B57 -> OTHER_NONCURRENT_ASSETS_DETAILED | C55: =IF('Balance Sheet - Standardized'!C57="",0,'Balance Sheet - Standardized'!C57)/'Balance Sheet - Standardized'!C$61 -> 0.010020205 | D55: =IF('Balance Sheet - Standardized'!D57="",0,'Balance Sheet - Standardized'!D57)/'Balance Sheet - Standardized'!D$61 -> 0.026381731 | E55: =IF('Balance Sheet - Standardized'!E57="",0,'Balance Sheet - Standardized'!E57)/'Balance Sheet - Standardized'!E$61 -> 0.026514425 | F55: =IF('Balance Sheet - Standardized'!F57="",0,'Balance Sheet - Standardized'!F57)/'Balance Sheet - Standardized'!F$61 -> 0.034636248 | G55: =IF('Balance Sheet - Standardized'!G57="",0,'Balance Sheet - Standardized'!G57)/'Balance Sheet - Standardized'!G$61 -> 0.024778888 | H55: =IF('Balance Sheet - Standardized'!H57="",0,'Balance Sheet - Standardized'!H57)/'Balance Sheet - Standardized'!H$61 -> 0.022530348 | I55: =IF('Balance Sheet - Standardized'!I57="",0,'Balance Sheet - Standardized'!I57)/'Balance Sheet - Standardized'!I$61 -> 0.035527888 | J55: =IF('Balance Sheet - Standardized'!J57="",0,'Balance Sheet - Standardized'!J57)/'Balance Sheet - Standardized'!J$61 -> 0.026465145 | ... L55: =IF('Balance Sheet - Standardized'!L57="",0,'Balance Sheet - Standardized'!L57)/'Balance Sheet - Standardized'!L$61 -> 0.024206861
A56: ='Balance Sheet - Standardized'!A58 -> check
A57: ='Balance Sheet - Standardized'!A59 -> Total Noncurrent Assets | B57: ='Balance Sheet - Standardized'!B59 -> BS_TOT_NON_CUR_ASSET | C57: =IF('Balance Sheet - Standardized'!C59="",0,'Balance Sheet - Standardized'!C59)/'Balance Sheet - Standardized'!C$61 -> 0.43227388 | D57: =IF('Balance Sheet - Standardized'!D59="",0,'Balance Sheet - Standardized'!D59)/'Balance Sheet - Standardized'!D$61 -> 0.42111566 | E57: =IF('Balance Sheet - Standardized'!E59="",0,'Balance Sheet - Standardized'!E59)/'Balance Sheet - Standardized'!E$61 -> 0.33823682 | F57: =IF('Balance Sheet - Standardized'!F59="",0,'Balance Sheet - Standardized'!F59)/'Balance Sheet - Standardized'!F$61 -> 0.3734135 | G57: =IF('Balance Sheet - Standardized'!G59="",0,'Balance Sheet - Standardized'!G59)/'Balance Sheet - Standardized'!G$61 -> 0.39015049 | H57: =IF('Balance Sheet - Standardized'!H59="",0,'Balance Sheet - Standardized'!H59)/'Balance Sheet - Standardized'!H$61 -> 0.34696674 | I57: =IF('Balance Sheet - Standardized'!I59="",0,'Balance Sheet - Standardized'!I59)/'Balance Sheet - Standardized'!I$61 -> 0.32864422 | J57: =IF('Balance Sheet - Standardized'!J59="",0,'Balance Sheet - Standardized'!J59)/'Balance Sheet - Standardized'!J$61 -> 0.34623823 | ... L57: =IF('Balance Sheet - Standardized'!L59="",0,'Balance Sheet - Standardized'!L59)/'Balance Sheet - Standardized'!L$61 -> 0.36638774
A58: ='Balance Sheet - Standardized'!A60 -> check
A59: ='Balance Sheet - Standardized'!A61 -> Total Assets | B59: ='Balance Sheet - Standardized'!B61 -> BS_TOT_ASSET | C59: =IF('Balance Sheet - Standardized'!C61="",0,'Balance Sheet - Standardized'!C61)/'Balance Sheet - Standardized'!C$61 -> 1 | D59: =IF('Balance Sheet - Standardized'!D61="",0,'Balance Sheet - Standardized'!D61)/'Balance Sheet - Standardized'!D$61 -> 1 | E59: =IF('Balance Sheet - Standardized'!E61="",0,'Balance Sheet - Standardized'!E61)/'Balance Sheet - Standardized'!E$61 -> 1 | F59: =IF('Balance Sheet - Standardized'!F61="",0,'Balance Sheet - Standardized'!F61)/'Balance Sheet - Standardized'!F$61 -> 1 | G59: =IF('Balance Sheet - Standardized'!G61="",0,'Balance Sheet - Standardized'!G61)/'Balance Sheet - Standardized'!G$61 -> 1 | H59: =IF('Balance Sheet - Standardized'!H61="",0,'Balance Sheet - Standardized'!H61)/'Balance Sheet - Standardized'!H$61 -> 1 | I59: =IF('Balance Sheet - Standardized'!I61="",0,'Balance Sheet - Standardized'!I61)/'Balance Sheet - Standardized'!I$61 -> 1 | J59: =IF('Balance Sheet - Standardized'!J61="",0,'Balance Sheet - Standardized'!J61)/'Balance Sheet - Standardized'!J$61 -> 1 | ... L59: =IF('Balance Sheet - Standardized'!L61="",0,'Balance Sheet - Standardized'!L61)/'Balance Sheet - Standardized'!L$61 -> 1
A60: ='Balance Sheet - Standardized'!A62 -> check
A61: ='Balance Sheet - Standardized'!A63 -> Liabilities & Shareholders' Equity
A62: ='Balance Sheet - Standardized'!A64 -> + Payables & Accruals | B62: ='Balance Sheet - Standardized'!B64 -> ACCT_PAYABLE_&_ACCRUALS_DETAILED | C62: =IF('Balance Sheet - Standardized'!C64="",0,'Balance Sheet - Standardized'!C64)/'Balance Sheet - Standardized'!C$106 -> 0.15455948 | D62: =IF('Balance Sheet - Standardized'!D64="",0,'Balance Sheet - Standardized'!D64)/'Balance Sheet - Standardized'!D$106 -> 0.16751633 | E62: =IF('Balance Sheet - Standardized'!E64="",0,'Balance Sheet - Standardized'!E64)/'Balance Sheet - Standardized'!E$106 -> 0.1424549 | F62: =IF('Balance Sheet - Standardized'!F64="",0,'Balance Sheet - Standardized'!F64)/'Balance Sheet - Standardized'!F$106 -> 0.14079835 | G62: =IF('Balance Sheet - Standardized'!G64="",0,'Balance Sheet - Standardized'!G64)/'Balance Sheet - Standardized'!G$106 -> 0.12234934 | H62: =IF('Balance Sheet - Standardized'!H64="",0,'Balance Sheet - Standardized'!H64)/'Balance Sheet - Standardized'!H$106 -> 0.15492067 | I62: =IF('Balance Sheet - Standardized'!I64="",0,'Balance Sheet - Standardized'!I64)/'Balance Sheet - Standardized'!I$106 -> 0.21385777 | J62: =IF('Balance Sheet - Standardized'!J64="",0,'Balance Sheet - Standardized'!J64)/'Balance Sheet - Standardized'!J$106 -> 0.18435635 | ... L62: =IF('Balance Sheet - Standardized'!L64="",0,'Balance Sheet - Standardized'!L64)/'Balance Sheet - Standardized'!L$106 -> 0.18275831
A63: ='Balance Sheet - Standardized'!A65 -> + Accounts Payable | B63: ='Balance Sheet - Standardized'!B65 -> BS_ACCT_PAYABLE | C63: =IF('Balance Sheet - Standardized'!C65="",0,'Balance Sheet - Standardized'!C65)/'Balance Sheet - Standardized'!C$106 -> 0.13675895 | D63: =IF('Balance Sheet - Standardized'!D65="",0,'Balance Sheet - Standardized'!D65)/'Balance Sheet - Standardized'!D$106 -> 0.15559567 | E63: =IF('Balance Sheet - Standardized'!E65="",0,'Balance Sheet - Standardized'!E65)/'Balance Sheet - Standardized'!E$106 -> 0.13666682 | F63: =IF('Balance Sheet - Standardized'!F65="",0,'Balance Sheet - Standardized'!F65)/'Balance Sheet - Standardized'!F$106 -> 0.1268133 | G63: =IF('Balance Sheet - Standardized'!G65="",0,'Balance Sheet - Standardized'!G65)/'Balance Sheet - Standardized'!G$106 -> 0.10865122 | H63: =IF('Balance Sheet - Standardized'!H65="",0,'Balance Sheet - Standardized'!H65)/'Balance Sheet - Standardized'!H$106 -> 0.15133226 | I63: =IF('Balance Sheet - Standardized'!I65="",0,'Balance Sheet - Standardized'!I65)/'Balance Sheet - Standardized'!I$106 -> 0.18921193 | J63: =IF('Balance Sheet - Standardized'!J65="",0,'Balance Sheet - Standardized'!J65)/'Balance Sheet - Standardized'!J$106 -> 0.15267802 | ... L63: =IF('Balance Sheet - Standardized'!L65="",0,'Balance Sheet - Standardized'!L65)/'Balance Sheet - Standardized'!L$106 -> 0.15802666
A64: ='Balance Sheet - Standardized'!A66 -> + Accrued Taxes | B64: ='Balance Sheet - Standardized'!B66 -> BS_TAXES_PAYABLE | C64: =IF('Balance Sheet - Standardized'!C66="",0,'Balance Sheet - Standardized'!C66)/'Balance Sheet - Standardized'!C$106 -> 0.017800532 | D64: =IF('Balance Sheet - Standardized'!D66="",0,'Balance Sheet - Standardized'!D66)/'Balance Sheet - Standardized'!D$106 -> 0.011920653 | E64: =IF('Balance Sheet - Standardized'!E66="",0,'Balance Sheet - Standardized'!E66)/'Balance Sheet - Standardized'!E$106 -> 0.0057880836 | F64: =IF('Balance Sheet - Standardized'!F66="",0,'Balance Sheet - Standardized'!F66)/'Balance Sheet - Standardized'!F$106 -> 0.01398505 | G64: =IF('Balance Sheet - Standardized'!G66="",0,'Balance Sheet - Standardized'!G66)/'Balance Sheet - Standardized'!G$106 -> 0.013698127 | H64: =IF('Balance Sheet - Standardized'!H66="",0,'Balance Sheet - Standardized'!H66)/'Balance Sheet - Standardized'!H$106 -> 0.0035884046 | I64: =IF('Balance Sheet - Standardized'!I66="",0,'Balance Sheet - Standardized'!I66)/'Balance Sheet - Standardized'!I$106 -> 0.024645834 | J64: =IF('Balance Sheet - Standardized'!J66="",0,'Balance Sheet - Standardized'!J66)/'Balance Sheet - Standardized'!J$106 -> 0.031678327 | ... L64: =IF('Balance Sheet - Standardized'!L66="",0,'Balance Sheet - Standardized'!L66)/'Balance Sheet - Standardized'!L$106 -> 0.024731644
A65: ='Balance Sheet - Standardized'!A67 -> + Interest & Dividends Payable | B65: ='Balance Sheet - Standardized'!B67 -> BS_INTEREST_&_DIVIDENDS_PAYABLE | C65: =IF('Balance Sheet - Standardized'!C67="",0,'Balance Sheet - Standardized'!C67)/'Balance Sheet - Standardized'!C$106 -> 0 | D65: =IF('Balance Sheet - Standardized'!D67="",0,'Balance Sheet - Standardized'!D67)/'Balance Sheet - Standardized'!D$106 -> 0 | E65: =IF('Balance Sheet - Standardized'!E67="",0,'Balance Sheet - Standardized'!E67)/'Balance Sheet - Standardized'!E$106 -> 0 | F65: =IF('Balance Sheet - Standardized'!F67="",0,'Balance Sheet - Standardized'!F67)/'Balance Sheet - Standardized'!F$106 -> 0 | G65: =IF('Balance Sheet - Standardized'!G67="",0,'Balance Sheet - Standardized'!G67)/'Balance Sheet - Standardized'!G$106 -> 0 | H65: =IF('Balance Sheet - Standardized'!H67="",0,'Balance Sheet - Standardized'!H67)/'Balance Sheet - Standardized'!H$106 -> 0 | I65: =IF('Balance Sheet - Standardized'!I67="",0,'Balance Sheet - Standardized'!I67)/'Balance Sheet - Standardized'!I$106 -> 0 | J65: =IF('Balance Sheet - Standardized'!J67="",0,'Balance Sheet - Standardized'!J67)/'Balance Sheet - Standardized'!J$106 -> 0 | ... L65: =IF('Balance Sheet - Standardized'!L67="",0,'Balance Sheet - Standardized'!L67)/'Balance Sheet - Standardized'!L$106 -> 0
A66: ='Balance Sheet - Standardized'!A68 -> + Other Payables & Accruals | B66: ='Balance Sheet - Standardized'!B68 -> BS_ACCRUAL | C66: =IF('Balance Sheet - Standardized'!C68="",0,'Balance Sheet - Standardized'!C68)/'Balance Sheet - Standardized'!C$106 -> 0 | D66: =IF('Balance Sheet - Standardized'!D68="",0,'Balance Sheet - Standardized'!D68)/'Balance Sheet - Standardized'!D$106 -> 0 | E66: =IF('Balance Sheet - Standardized'!E68="",0,'Balance Sheet - Standardized'!E68)/'Balance Sheet - Standardized'!E$106 -> 0 | F66: =IF('Balance Sheet - Standardized'!F68="",0,'Balance Sheet - Standardized'!F68)/'Balance Sheet - Standardized'!F$106 -> 0 | G66: =IF('Balance Sheet - Standardized'!G68="",0,'Balance Sheet - Standardized'!G68)/'Balance Sheet - Standardized'!G$106 -> 0 | H66: =IF('Balance Sheet - Standardized'!H68="",0,'Balance Sheet - Standardized'!H68)/'Balance Sheet - Standardized'!H$106 -> 0 | I66: =IF('Balance Sheet - Standardized'!I68="",0,'Balance Sheet - Standardized'!I68)/'Balance Sheet - Standardized'!I$106 -> 0 | J66: =IF('Balance Sheet - Standardized'!J68="",0,'Balance Sheet - Standardized'!J68)/'Balance Sheet - Standardized'!J$106 -> 0 | ... L66: =IF('Balance Sheet - Standardized'!L68="",0,'Balance Sheet - Standardized'!L68)/'Balance Sheet - Standardized'!L$106 -> 0
A67: ='Balance Sheet - Standardized'!A69 -> check
A68: ='Balance Sheet - Standardized'!A70 -> + ST Debt | B68: ='Balance Sheet - Standardized'!B70 -> BS_ST_BORROW | C68: =IF('Balance Sheet - Standardized'!C70="",0,'Balance Sheet - Standardized'!C70)/'Balance Sheet - Standardized'!C$106 -> 0.00083492973 | D68: =IF('Balance Sheet - Standardized'!D70="",0,'Balance Sheet - Standardized'!D70)/'Balance Sheet - Standardized'!D$106 -> 0.00085177793 | E68: =IF('Balance Sheet - Standardized'!E70="",0,'Balance Sheet - Standardized'!E70)/'Balance Sheet - Standardized'!E$106 -> 0.0009176776 | F68: =IF('Balance Sheet - Standardized'!F70="",0,'Balance Sheet - Standardized'!F70)/'Balance Sheet - Standardized'!F$106 -> 0.00090045454 | G68: =IF('Balance Sheet - Standardized'!G70="",0,'Balance Sheet - Standardized'!G70)/'Balance Sheet - Standardized'!G$106 -> 0.019550896 | H68: =IF('Balance Sheet - Standardized'!H70="",0,'Balance Sheet - Standardized'!H70)/'Balance Sheet - Standardized'!H$106 -> 0.014085827 | I68: =IF('Balance Sheet - Standardized'!I70="",0,'Balance Sheet - Standardized'!I70)/'Balance Sheet - Standardized'!I$106 -> 0.010655699 | J68: =IF('Balance Sheet - Standardized'!J70="",0,'Balance Sheet - Standardized'!J70)/'Balance Sheet - Standardized'!J$106 -> 0.011220341 | ... L68: =IF('Balance Sheet - Standardized'!L70="",0,'Balance Sheet - Standardized'!L70)/'Balance Sheet - Standardized'!L$106 -> 0.014111031
A69: ='Balance Sheet - Standardized'!A71 -> + ST Lease Liabilities | B69: ='Balance Sheet - Standardized'!B71 -> ST_CAPITALIZED_LEASE_LIABILITIES | C69: =IF('Balance Sheet - Standardized'!C71="",0,'Balance Sheet - Standardized'!C71)/'Balance Sheet - Standardized'!C$106 -> 0 | D69: =IF('Balance Sheet - Standardized'!D71="",0,'Balance Sheet - Standardized'!D71)/'Balance Sheet - Standardized'!D$106 -> 0 | E69: =IF('Balance Sheet - Standardized'!E71="",0,'Balance Sheet - Standardized'!E71)/'Balance Sheet - Standardized'!E$106 -> 0 | F69: =IF('Balance Sheet - Standardized'!F71="",0,'Balance Sheet - Standardized'!F71)/'Balance Sheet - Standardized'!F$106 -> 0 | G69: =IF('Balance Sheet - Standardized'!G71="",0,'Balance Sheet - Standardized'!G71)/'Balance Sheet - Standardized'!G$106 -> 0.018834005 | H69: =IF('Balance Sheet - Standardized'!H71="",0,'Balance Sheet - Standardized'!H71)/'Balance Sheet - Standardized'!H$106 -> 0.013359443 | I69: =IF('Balance Sheet - Standardized'!I71="",0,'Balance Sheet - Standardized'!I71)/'Balance Sheet - Standardized'!I$106 -> 0.0099560346 | J69: =IF('Balance Sheet - Standardized'!J71="",0,'Balance Sheet - Standardized'!J71)/'Balance Sheet - Standardized'!J$106 -> 0.010441055 | ... L69: =IF('Balance Sheet - Standardized'!L71="",0,'Balance Sheet - Standardized'!L71)/'Balance Sheet - Standardized'!L$106 -> 0.013354503
A70: ='Balance Sheet - Standardized'!A72 -> + ST Capital Leases | B70: ='Balance Sheet - Standardized'!B72 -> ST_CAPITAL_LEASE_OBLIGATIONS | C70: =IF('Balance Sheet - Standardized'!C72="",0,'Balance Sheet - Standardized'!C72)/'Balance Sheet - Standardized'!C$106 -> 0 | D70: =IF('Balance Sheet - Standardized'!D72="",0,'Balance Sheet - Standardized'!D72)/'Balance Sheet - Standardized'!D$106 -> 0 | E70: =IF('Balance Sheet - Standardized'!E72="",0,'Balance Sheet - Standardized'!E72)/'Balance Sheet - Standardized'!E$106 -> 0 | F70: =IF('Balance Sheet - Standardized'!F72="",0,'Balance Sheet - Standardized'!F72)/'Balance Sheet - Standardized'!F$106 -> 0 | G70: =IF('Balance Sheet - Standardized'!G72="",0,'Balance Sheet - Standardized'!G72)/'Balance Sheet - Standardized'!G$106 -> 0 | H70: =IF('Balance Sheet - Standardized'!H72="",0,'Balance Sheet - Standardized'!H72)/'Balance Sheet - Standardized'!H$106 -> 0 | I70: =IF('Balance Sheet - Standardized'!I72="",0,'Balance Sheet - Standardized'!I72)/'Balance Sheet - Standardized'!I$106 -> 0 | J70: =IF('Balance Sheet - Standardized'!J72="",0,'Balance Sheet - Standardized'!J72)/'Balance Sheet - Standardized'!J$106 -> 0 | ... L70: =IF('Balance Sheet - Standardized'!L72="",0,'Balance Sheet - Standardized'!L72)/'Balance Sheet - Standardized'!L$106 -> 0
A71: ='Balance Sheet - Standardized'!A73 -> + ST Operating Leases | B71: ='Balance Sheet - Standardized'!B73 -> BS_ST_OPERATING_LEASE_LIABS | C71: =IF('Balance Sheet - Standardized'!C73="",0,'Balance Sheet - Standardized'!C73)/'Balance Sheet - Standardized'!C$106 -> 0 | D71: =IF('Balance Sheet - Standardized'!D73="",0,'Balance Sheet - Standardized'!D73)/'Balance Sheet - Standardized'!D$106 -> 0 | E71: =IF('Balance Sheet - Standardized'!E73="",0,'Balance Sheet - Standardized'!E73)/'Balance Sheet - Standardized'!E$106 -> 0 | F71: =IF('Balance Sheet - Standardized'!F73="",0,'Balance Sheet - Standardized'!F73)/'Balance Sheet - Standardized'!F$106 -> 0 | G71: =IF('Balance Sheet - Standardized'!G73="",0,'Balance Sheet - Standardized'!G73)/'Balance Sheet - Standardized'!G$106 -> 0.018834005 | H71: =IF('Balance Sheet - Standardized'!H73="",0,'Balance Sheet - Standardized'!H73)/'Balance Sheet - Standardized'!H$106 -> 0.013359443 | I71: =IF('Balance Sheet - Standardized'!I73="",0,'Balance Sheet - Standardized'!I73)/'Balance Sheet - Standardized'!I$106 -> 0.0099560346 | J71: =IF('Balance Sheet - Standardized'!J73="",0,'Balance Sheet - Standardized'!J73)/'Balance Sheet - Standardized'!J$106 -> 0.010441055 | ... L71: =IF('Balance Sheet - Standardized'!L73="",0,'Balance Sheet - Standardized'!L73)/'Balance Sheet - Standardized'!L$106 -> 0.013354503
A72: ='Balance Sheet - Standardized'!A74 -> + ST Borrowings | B72: ='Balance Sheet - Standardized'!B74 -> SHORT_TERM_DEBT_DETAILED | C72: =IF('Balance Sheet - Standardized'!C74="",0,'Balance Sheet - Standardized'!C74)/'Balance Sheet - Standardized'!C$106 -> 0 | D72: =IF('Balance Sheet - Standardized'!D74="",0,'Balance Sheet - Standardized'!D74)/'Balance Sheet - Standardized'!D$106 -> 0 | E72: =IF('Balance Sheet - Standardized'!E74="",0,'Balance Sheet - Standardized'!E74)/'Balance Sheet - Standardized'!E$106 -> 0 | F72: =IF('Balance Sheet - Standardized'!F74="",0,'Balance Sheet - Standardized'!F74)/'Balance Sheet - Standardized'!F$106 -> 0 | G72: =IF('Balance Sheet - Standardized'!G74="",0,'Balance Sheet - Standardized'!G74)/'Balance Sheet - Standardized'!G$106 -> 0 | H72: =IF('Balance Sheet - Standardized'!H74="",0,'Balance Sheet - Standardized'!H74)/'Balance Sheet - Standardized'!H$106 -> 0 | I72: =IF('Balance Sheet - Standardized'!I74="",0,'Balance Sheet - Standardized'!I74)/'Balance Sheet - Standardized'!I$106 -> 0 | J72: =IF('Balance Sheet - Standardized'!J74="",0,'Balance Sheet - Standardized'!J74)/'Balance Sheet - Standardized'!J$106 -> 0 | ... L72: =IF('Balance Sheet - Standardized'!L74="",0,'Balance Sheet - Standardized'!L74)/'Balance Sheet - Standardized'!L$106 -> 0
A73: ='Balance Sheet - Standardized'!A75 -> + Current Portion of LT Debt | B73: ='Balance Sheet - Standardized'!B75 -> BS_CURR_PORTION_LT_DEBT | C73: =IF('Balance Sheet - Standardized'!C75="",0,'Balance Sheet - Standardized'!C75)/'Balance Sheet - Standardized'!C$106 -> 0.00083492973 | D73: =IF('Balance Sheet - Standardized'!D75="",0,'Balance Sheet - Standardized'!D75)/'Balance Sheet - Standardized'!D$106 -> 0.00085177793 | E73: =IF('Balance Sheet - Standardized'!E75="",0,'Balance Sheet - Standardized'!E75)/'Balance Sheet - Standardized'!E$106 -> 0.0009176776 | F73: =IF('Balance Sheet - Standardized'!F75="",0,'Balance Sheet - Standardized'!F75)/'Balance Sheet - Standardized'!F$106 -> 0.00090045454 | G73: =IF('Balance Sheet - Standardized'!G75="",0,'Balance Sheet - Standardized'!G75)/'Balance Sheet - Standardized'!G$106 -> 0.00071689068 | H73: =IF('Balance Sheet - Standardized'!H75="",0,'Balance Sheet - Standardized'!H75)/'Balance Sheet - Standardized'!H$106 -> 0.00072638415 | I73: =IF('Balance Sheet - Standardized'!I75="",0,'Balance Sheet - Standardized'!I75)/'Balance Sheet - Standardized'!I$106 -> 0.00069966435 | J73: =IF('Balance Sheet - Standardized'!J75="",0,'Balance Sheet - Standardized'!J75)/'Balance Sheet - Standardized'!J$106 -> 0.00077928616 | ... L73: =IF('Balance Sheet - Standardized'!L75="",0,'Balance Sheet - Standardized'!L75)/'Balance Sheet - Standardized'!L$106 -> 0.00075652789
A74: ='Balance Sheet - Standardized'!A76 -> check
A75: ='Balance Sheet - Standardized'!A77 -> + Other ST Liabilities | B75: ='Balance Sheet - Standardized'!B77 -> OTHER_CURRENT_LIABS_SUB_DETAILED | C75: =IF('Balance Sheet - Standardized'!C77="",0,'Balance Sheet - Standardized'!C77)/'Balance Sheet - Standardized'!C$106 -> 0.21697577 | D75: =IF('Balance Sheet - Standardized'!D77="",0,'Balance Sheet - Standardized'!D77)/'Balance Sheet - Standardized'!D$106 -> 0.2216572 | E75: =IF('Balance Sheet - Standardized'!E77="",0,'Balance Sheet - Standardized'!E77)/'Balance Sheet - Standardized'!E$106 -> 0.2151663 | F75: =IF('Balance Sheet - Standardized'!F77="",0,'Balance Sheet - Standardized'!F77)/'Balance Sheet - Standardized'!F$106 -> 0.21215398 | G75: =IF('Balance Sheet - Standardized'!G77="",0,'Balance Sheet - Standardized'!G77)/'Balance Sheet - Standardized'!G$106 -> 0.2345409 | H75: =IF('Balance Sheet - Standardized'!H77="",0,'Balance Sheet - Standardized'!H77)/'Balance Sheet - Standardized'!H$106 -> 0.29373703 | I75: =IF('Balance Sheet - Standardized'!I77="",0,'Balance Sheet - Standardized'!I77)/'Balance Sheet - Standardized'!I$106 -> 0.28271798 | J75: =IF('Balance Sheet - Standardized'!J77="",0,'Balance Sheet - Standardized'!J77)/'Balance Sheet - Standardized'!J$106 -> 0.27374668 | ... L75: =IF('Balance Sheet - Standardized'!L77="",0,'Balance Sheet - Standardized'!L77)/'Balance Sheet - Standardized'!L$106 -> 0.26935965
A76: ='Balance Sheet - Standardized'!A78 -> + ST Deferred Revenue | B76: ='Balance Sheet - Standardized'!B78 -> ST_DEFERRED_REVENUE | C76: =IF('Balance Sheet - Standardized'!C78="",0,'Balance Sheet - Standardized'!C78)/'Balance Sheet - Standardized'!C$106 -> 0.032185058 | D76: =IF('Balance Sheet - Standardized'!D78="",0,'Balance Sheet - Standardized'!D78)/'Balance Sheet - Standardized'!D$106 -> 0.026129665 | E76: =IF('Balance Sheet - Standardized'!E78="",0,'Balance Sheet - Standardized'!E78)/'Balance Sheet - Standardized'!E$106 -> 0.028367429 | F76: =IF('Balance Sheet - Standardized'!F78="",0,'Balance Sheet - Standardized'!F78)/'Balance Sheet - Standardized'!F$106 -> 0 | G76: =IF('Balance Sheet - Standardized'!G78="",0,'Balance Sheet - Standardized'!G78)/'Balance Sheet - Standardized'!G$106 -> 0.0066983324 | H76: =IF('Balance Sheet - Standardized'!H78="",0,'Balance Sheet - Standardized'!H78)/'Balance Sheet - Standardized'!H$106 -> 0.011568588 | I76: =IF('Balance Sheet - Standardized'!I78="",0,'Balance Sheet - Standardized'!I78)/'Balance Sheet - Standardized'!I$106 -> 0.0033533463 | J76: =IF('Balance Sheet - Standardized'!J78="",0,'Balance Sheet - Standardized'!J78)/'Balance Sheet - Standardized'!J$106 -> 0.0097583178 | ... L76: =IF('Balance Sheet - Standardized'!L78="",0,'Balance Sheet - Standardized'!L78)/'Balance Sheet - Standardized'!L$106 -> 0.058246154
A77: ='Balance Sheet - Standardized'!A79 -> + ST Derivatives & Hedging | B77: ='Balance Sheet - Standardized'!B79 -> BS_DERIVATIVE_&_HEDGING_LIABS_ST | C77: =IF('Balance Sheet - Standardized'!C79="",0,'Balance Sheet - Standardized'!C79)/'Balance Sheet - Standardized'!C$106 -> 0.0025217421 | D77: =IF('Balance Sheet - Standardized'!D79="",0,'Balance Sheet - Standardized'!D79)/'Balance Sheet - Standardized'!D$106 -> 0.0074032639 | E77: =IF('Balance Sheet - Standardized'!E79="",0,'Balance Sheet - Standardized'!E79)/'Balance Sheet - Standardized'!E$106 -> 5.3717713e-05 | F77: =IF('Balance Sheet - Standardized'!F79="",0,'Balance Sheet - Standardized'!F79)/'Balance Sheet - Standardized'!F$106 -> 0 | G77: =IF('Balance Sheet - Standardized'!G79="",0,'Balance Sheet - Standardized'!G79)/'Balance Sheet - Standardized'!G$106 -> 0 | H77: =IF('Balance Sheet - Standardized'!H79="",0,'Balance Sheet - Standardized'!H79)/'Balance Sheet - Standardized'!H$106 -> 0 | I77: =IF('Balance Sheet - Standardized'!I79="",0,'Balance Sheet - Standardized'!I79)/'Balance Sheet - Standardized'!I$106 -> 0 | J77: =IF('Balance Sheet - Standardized'!J79="",0,'Balance Sheet - Standardized'!J79)/'Balance Sheet - Standardized'!J$106 -> 0 | ... L77: =IF('Balance Sheet - Standardized'!L79="",0,'Balance Sheet - Standardized'!L79)/'Balance Sheet - Standardized'!L$106 -> 0
A78: ='Balance Sheet - Standardized'!A80 -> + ST Deferred Tax Liabilities | B78: ='Balance Sheet - Standardized'!B80 -> BS_DEFERRED_TAX_LIABS_ST | C78: =IF('Balance Sheet - Standardized'!C80="",0,'Balance Sheet - Standardized'!C80)/'Balance Sheet - Standardized'!C$106 -> 0 | D78: =IF('Balance Sheet - Standardized'!D80="",0,'Balance Sheet - Standardized'!D80)/'Balance Sheet - Standardized'!D$106 -> 0 | E78: =IF('Balance Sheet - Standardized'!E80="",0,'Balance Sheet - Standardized'!E80)/'Balance Sheet - Standardized'!E$106 -> 0 | F78: =IF('Balance Sheet - Standardized'!F80="",0,'Balance Sheet - Standardized'!F80)/'Balance Sheet - Standardized'!F$106 -> 0 | G78: =IF('Balance Sheet - Standardized'!G80="",0,'Balance Sheet - Standardized'!G80)/'Balance Sheet - Standardized'!G$106 -> 0 | H78: =IF('Balance Sheet - Standardized'!H80="",0,'Balance Sheet - Standardized'!H80)/'Balance Sheet - Standardized'!H$106 -> 0 | I78: =IF('Balance Sheet - Standardized'!I80="",0,'Balance Sheet - Standardized'!I80)/'Balance Sheet - Standardized'!I$106 -> 0 | J78: =IF('Balance Sheet - Standardized'!J80="",0,'Balance Sheet - Standardized'!J80)/'Balance Sheet - Standardized'!J$106 -> 0 | ... L78: =IF('Balance Sheet - Standardized'!L80="",0,'Balance Sheet - Standardized'!L80)/'Balance Sheet - Standardized'!L$106 -> 0
A79: ='Balance Sheet - Standardized'!A81 -> + Liabilities of Discontinued Operations ST | B79: ='Balance Sheet - Standardized'!B81 -> BS_LIABS_OF_DISCONTINUED_OPS_ST | C79: =IF('Balance Sheet - Standardized'!C81="",0,'Balance Sheet - Standardized'!C81)/'Balance Sheet - Standardized'!C$106 -> 0 | D79: =IF('Balance Sheet - Standardized'!D81="",0,'Balance Sheet - Standardized'!D81)/'Balance Sheet - Standardized'!D$106 -> 0 | E79: =IF('Balance Sheet - Standardized'!E81="",0,'Balance Sheet - Standardized'!E81)/'Balance Sheet - Standardized'!E$106 -> 0 | F79: =IF('Balance Sheet - Standardized'!F81="",0,'Balance Sheet - Standardized'!F81)/'Balance Sheet - Standardized'!F$106 -> 0 | G79: =IF('Balance Sheet - Standardized'!G81="",0,'Balance Sheet - Standardized'!G81)/'Balance Sheet - Standardized'!G$106 -> 0 | H79: =IF('Balance Sheet - Standardized'!H81="",0,'Balance Sheet - Standardized'!H81)/'Balance Sheet - Standardized'!H$106 -> 0 | I79: =IF('Balance Sheet - Standardized'!I81="",0,'Balance Sheet - Standardized'!I81)/'Balance Sheet - Standardized'!I$106 -> 0 | J79: =IF('Balance Sheet - Standardized'!J81="",0,'Balance Sheet - Standardized'!J81)/'Balance Sheet - Standardized'!J$106 -> 0 | ... L79: =IF('Balance Sheet - Standardized'!L81="",0,'Balance Sheet - Standardized'!L81)/'Balance Sheet - Standardized'!L$106 -> 0
A80: ='Balance Sheet - Standardized'!A82 -> + Misc ST Liabilities | B80: ='Balance Sheet - Standardized'!B82 -> OTHER_CURRENT_LIABS_DETAILED | C80: =IF('Balance Sheet - Standardized'!C82="",0,'Balance Sheet - Standardized'!C82)/'Balance Sheet - Standardized'!C$106 -> 0.18226897 | D80: =IF('Balance Sheet - Standardized'!D82="",0,'Balance Sheet - Standardized'!D82)/'Balance Sheet - Standardized'!D$106 -> 0.18812427 | E80: =IF('Balance Sheet - Standardized'!E82="",0,'Balance Sheet - Standardized'!E82)/'Balance Sheet - Standardized'!E$106 -> 0.18674515 | F80: =IF('Balance Sheet - Standardized'!F82="",0,'Balance Sheet - Standardized'!F82)/'Balance Sheet - Standardized'!F$106 -> 0.21215398 | G80: =IF('Balance Sheet - Standardized'!G82="",0,'Balance Sheet - Standardized'!G82)/'Balance Sheet - Standardized'!G$106 -> 0.22784256 | H80: =IF('Balance Sheet - Standardized'!H82="",0,'Balance Sheet - Standardized'!H82)/'Balance Sheet - Standardized'!H$106 -> 0.28216844 | I80: =IF('Balance Sheet - Standardized'!I82="",0,'Balance Sheet - Standardized'!I82)/'Balance Sheet - Standardized'!I$106 -> 0.27936463 | J80: =IF('Balance Sheet - Standardized'!J82="",0,'Balance Sheet - Standardized'!J82)/'Balance Sheet - Standardized'!J$106 -> 0.26398836 | ... L80: =IF('Balance Sheet - Standardized'!L82="",0,'Balance Sheet - Standardized'!L82)/'Balance Sheet - Standardized'!L$106 -> 0.21111349
A81: ='Balance Sheet - Standardized'!A83 -> check
A82: ='Balance Sheet - Standardized'!A84 -> Total Current Liabilities | B82: ='Balance Sheet - Standardized'!B84 -> BS_CUR_LIAB | C82: =IF('Balance Sheet - Standardized'!C84="",0,'Balance Sheet - Standardized'!C84)/'Balance Sheet - Standardized'!C$106 -> 0.37237018 | D82: =IF('Balance Sheet - Standardized'!D84="",0,'Balance Sheet - Standardized'!D84)/'Balance Sheet - Standardized'!D$106 -> 0.3900253 | E82: =IF('Balance Sheet - Standardized'!E84="",0,'Balance Sheet - Standardized'!E84)/'Balance Sheet - Standardized'!E$106 -> 0.35853888 | F82: =IF('Balance Sheet - Standardized'!F84="",0,'Balance Sheet - Standardized'!F84)/'Balance Sheet - Standardized'!F$106 -> 0.35385278 | G82: =IF('Balance Sheet - Standardized'!G84="",0,'Balance Sheet - Standardized'!G84)/'Balance Sheet - Standardized'!G$106 -> 0.37644113 | H82: =IF('Balance Sheet - Standardized'!H84="",0,'Balance Sheet - Standardized'!H84)/'Balance Sheet - Standardized'!H$106 -> 0.46274352 | I82: =IF('Balance Sheet - Standardized'!I84="",0,'Balance Sheet - Standardized'!I84)/'Balance Sheet - Standardized'!I$106 -> 0.50723144 | J82: =IF('Balance Sheet - Standardized'!J84="",0,'Balance Sheet - Standardized'!J84)/'Balance Sheet - Standardized'!J$106 -> 0.46932337 | ... L82: =IF('Balance Sheet - Standardized'!L84="",0,'Balance Sheet - Standardized'!L84)/'Balance Sheet - Standardized'!L$106 -> 0.46622898
A83: ='Balance Sheet - Standardized'!A85 -> check
A84: ='Balance Sheet - Standardized'!A86 -> + LT Debt | B84: ='Balance Sheet - Standardized'!B86 -> BS_LT_BORROW | C84: =IF('Balance Sheet - Standardized'!C86="",0,'Balance Sheet - Standardized'!C86)/'Balance Sheet - Standardized'!C$106 -> 0.49577025 | D84: =IF('Balance Sheet - Standardized'!D86="",0,'Balance Sheet - Standardized'!D86)/'Balance Sheet - Standardized'!D$106 -> 0.49485755 | E84: =IF('Balance Sheet - Standardized'!E86="",0,'Balance Sheet - Standardized'!E86)/'Balance Sheet - Standardized'!E$106 -> 0.52182282 | F84: =IF('Balance Sheet - Standardized'!F86="",0,'Balance Sheet - Standardized'!F86)/'Balance Sheet - Standardized'!F$106 -> 0.49911032 | G84: =IF('Balance Sheet - Standardized'!G86="",0,'Balance Sheet - Standardized'!G86)/'Balance Sheet - Standardized'!G$106 -> 0.52036705 | H84: =IF('Balance Sheet - Standardized'!H86="",0,'Balance Sheet - Standardized'!H86)/'Balance Sheet - Standardized'!H$106 -> 0.44793131 | I84: =IF('Balance Sheet - Standardized'!I86="",0,'Balance Sheet - Standardized'!I86)/'Balance Sheet - Standardized'!I$106 -> 0.42594746 | J84: =IF('Balance Sheet - Standardized'!J86="",0,'Balance Sheet - Standardized'!J86)/'Balance Sheet - Standardized'!J$106 -> 0.45809958 | ... L84: =IF('Balance Sheet - Standardized'!L86="",0,'Balance Sheet - Standardized'!L86)/'Balance Sheet - Standardized'!L$106 -> 0.4291234
A85: ='Balance Sheet - Standardized'!A87 -> + LT Borrowings | B85: ='Balance Sheet - Standardized'!B87 -> LONG_TERM_BORROWINGS_DETAILED | C85: =IF('Balance Sheet - Standardized'!C87="",0,'Balance Sheet - Standardized'!C87)/'Balance Sheet - Standardized'!C$106 -> 0.49577025 | D85: =IF('Balance Sheet - Standardized'!D87="",0,'Balance Sheet - Standardized'!D87)/'Balance Sheet - Standardized'!D$106 -> 0.49485755 | E85: =IF('Balance Sheet - Standardized'!E87="",0,'Balance Sheet - Standardized'!E87)/'Balance Sheet - Standardized'!E$106 -> 0.52182282 | F85: =IF('Balance Sheet - Standardized'!F87="",0,'Balance Sheet - Standardized'!F87)/'Balance Sheet - Standardized'!F$106 -> 0.49911032 | G85: =IF('Balance Sheet - Standardized'!G87="",0,'Balance Sheet - Standardized'!G87)/'Balance Sheet - Standardized'!G$106 -> 0.42528896 | H85: =IF('Balance Sheet - Standardized'!H87="",0,'Balance Sheet - Standardized'!H87)/'Balance Sheet - Standardized'!H$106 -> 0.38667068 | I85: =IF('Balance Sheet - Standardized'!I87="",0,'Balance Sheet - Standardized'!I87)/'Balance Sheet - Standardized'!I$106 -> 0.36351345 | J85: =IF('Balance Sheet - Standardized'!J87="",0,'Balance Sheet - Standardized'!J87)/'Balance Sheet - Standardized'!J$106 -> 0.39710492 | ... L85: =IF('Balance Sheet - Standardized'!L87="",0,'Balance Sheet - Standardized'!L87)/'Balance Sheet - Standardized'!L$106 -> 0.37277668
A86: ='Balance Sheet - Standardized'!A88 -> + LT Lease Liabilities | B86: ='Balance Sheet - Standardized'!B88 -> LT_CAPITALIZED_LEASE_LIABILITIES | C86: =IF('Balance Sheet - Standardized'!C88="",0,'Balance Sheet - Standardized'!C88)/'Balance Sheet - Standardized'!C$106 -> 0 | D86: =IF('Balance Sheet - Standardized'!D88="",0,'Balance Sheet - Standardized'!D88)/'Balance Sheet - Standardized'!D$106 -> 0 | E86: =IF('Balance Sheet - Standardized'!E88="",0,'Balance Sheet - Standardized'!E88)/'Balance Sheet - Standardized'!E$106 -> 0 | F86: =IF('Balance Sheet - Standardized'!F88="",0,'Balance Sheet - Standardized'!F88)/'Balance Sheet - Standardized'!F$106 -> 0 | G86: =IF('Balance Sheet - Standardized'!G88="",0,'Balance Sheet - Standardized'!G88)/'Balance Sheet - Standardized'!G$106 -> 0.095078086 | H86: =IF('Balance Sheet - Standardized'!H88="",0,'Balance Sheet - Standardized'!H88)/'Balance Sheet - Standardized'!H$106 -> 0.061260628 | I86: =IF('Balance Sheet - Standardized'!I88="",0,'Balance Sheet - Standardized'!I88)/'Balance Sheet - Standardized'!I$106 -> 0.062434013 | J86: =IF('Balance Sheet - Standardized'!J88="",0,'Balance Sheet - Standardized'!J88)/'Balance Sheet - Standardized'!J$106 -> 0.060994659 | ... L86: =IF('Balance Sheet - Standardized'!L88="",0,'Balance Sheet - Standardized'!L88)/'Balance Sheet - Standardized'!L$106 -> 0.056346717
A87: ='Balance Sheet - Standardized'!A89 -> + LT Capital Leases | B87: ='Balance Sheet - Standardized'!B89 -> LT_CAPITAL_LEASE_OBLIGATIONS | C87: =IF('Balance Sheet - Standardized'!C89="",0,'Balance Sheet - Standardized'!C89)/'Balance Sheet - Standardized'!C$106 -> 0 | D87: =IF('Balance Sheet - Standardized'!D89="",0,'Balance Sheet - Standardized'!D89)/'Balance Sheet - Standardized'!D$106 -> 0 | E87: =IF('Balance Sheet - Standardized'!E89="",0,'Balance Sheet - Standardized'!E89)/'Balance Sheet - Standardized'!E$106 -> 0 | F87: =IF('Balance Sheet - Standardized'!F89="",0,'Balance Sheet - Standardized'!F89)/'Balance Sheet - Standardized'!F$106 -> 0 | G87: =IF('Balance Sheet - Standardized'!G89="",0,'Balance Sheet - Standardized'!G89)/'Balance Sheet - Standardized'!G$106 -> 0 | H87: =IF('Balance Sheet - Standardized'!H89="",0,'Balance Sheet - Standardized'!H89)/'Balance Sheet - Standardized'!H$106 -> 0 | I87: =IF('Balance Sheet - Standardized'!I89="",0,'Balance Sheet - Standardized'!I89)/'Balance Sheet - Standardized'!I$106 -> 0 | J87: =IF('Balance Sheet - Standardized'!J89="",0,'Balance Sheet - Standardized'!J89)/'Balance Sheet - Standardized'!J$106 -> 0 | ... L87: =IF('Balance Sheet - Standardized'!L89="",0,'Balance Sheet - Standardized'!L89)/'Balance Sheet - Standardized'!L$106 -> 0
A88: ='Balance Sheet - Standardized'!A90 -> + LT Operating Leases | B88: ='Balance Sheet - Standardized'!B90 -> BS_LT_OPERATING_LEASE_LIABS | C88: =IF('Balance Sheet - Standardized'!C90="",0,'Balance Sheet - Standardized'!C90)/'Balance Sheet - Standardized'!C$106 -> 0 | D88: =IF('Balance Sheet - Standardized'!D90="",0,'Balance Sheet - Standardized'!D90)/'Balance Sheet - Standardized'!D$106 -> 0 | E88: =IF('Balance Sheet - Standardized'!E90="",0,'Balance Sheet - Standardized'!E90)/'Balance Sheet - Standardized'!E$106 -> 0 | F88: =IF('Balance Sheet - Standardized'!F90="",0,'Balance Sheet - Standardized'!F90)/'Balance Sheet - Standardized'!F$106 -> 0 | G88: =IF('Balance Sheet - Standardized'!G90="",0,'Balance Sheet - Standardized'!G90)/'Balance Sheet - Standardized'!G$106 -> 0.095078086 | H88: =IF('Balance Sheet - Standardized'!H90="",0,'Balance Sheet - Standardized'!H90)/'Balance Sheet - Standardized'!H$106 -> 0.061260628 | I88: =IF('Balance Sheet - Standardized'!I90="",0,'Balance Sheet - Standardized'!I90)/'Balance Sheet - Standardized'!I$106 -> 0.062434013 | J88: =IF('Balance Sheet - Standardized'!J90="",0,'Balance Sheet - Standardized'!J90)/'Balance Sheet - Standardized'!J$106 -> 0.060994659 | ... L88: =IF('Balance Sheet - Standardized'!L90="",0,'Balance Sheet - Standardized'!L90)/'Balance Sheet - Standardized'!L$106 -> 0.056346717
A89: ='Balance Sheet - Standardized'!A91 -> check
A90: ='Balance Sheet - Standardized'!A92 -> + Other LT Liabilities | B90: ='Balance Sheet - Standardized'!B92 -> OTHER_NONCUR_LIABS_SUB_DETAILED | C90: =IF('Balance Sheet - Standardized'!C92="",0,'Balance Sheet - Standardized'!C92)/'Balance Sheet - Standardized'!C$106 -> 0.13185956 | D90: =IF('Balance Sheet - Standardized'!D92="",0,'Balance Sheet - Standardized'!D92)/'Balance Sheet - Standardized'!D$106 -> 0.11511715 | E90: =IF('Balance Sheet - Standardized'!E92="",0,'Balance Sheet - Standardized'!E92)/'Balance Sheet - Standardized'!E$106 -> 0.1196383 | F90: =IF('Balance Sheet - Standardized'!F92="",0,'Balance Sheet - Standardized'!F92)/'Balance Sheet - Standardized'!F$106 -> 0.1470369 | G90: =IF('Balance Sheet - Standardized'!G92="",0,'Balance Sheet - Standardized'!G92)/'Balance Sheet - Standardized'!G$106 -> 0.10319182 | H90: =IF('Balance Sheet - Standardized'!H92="",0,'Balance Sheet - Standardized'!H92)/'Balance Sheet - Standardized'!H$106 -> 0.089325166 | I90: =IF('Balance Sheet - Standardized'!I92="",0,'Balance Sheet - Standardized'!I92)/'Balance Sheet - Standardized'!I$106 -> 0.066821097 | J90: =IF('Balance Sheet - Standardized'!J92="",0,'Balance Sheet - Standardized'!J92)/'Balance Sheet - Standardized'!J$106 -> 0.072577058 | ... L90: =IF('Balance Sheet - Standardized'!L92="",0,'Balance Sheet - Standardized'!L92)/'Balance Sheet - Standardized'!L$106 -> 0.10464761
A91: ='Balance Sheet - Standardized'!A93 -> + Accrued Liabilities | B91: ='Balance Sheet - Standardized'!B93 -> BS_ACCRUED_LIABILITIES | C91: =IF('Balance Sheet - Standardized'!C93="",0,'Balance Sheet - Standardized'!C93)/'Balance Sheet - Standardized'!C$106 -> 0 | D91: =IF('Balance Sheet - Standardized'!D93="",0,'Balance Sheet - Standardized'!D93)/'Balance Sheet - Standardized'!D$106 -> 0 | E91: =IF('Balance Sheet - Standardized'!E93="",0,'Balance Sheet - Standardized'!E93)/'Balance Sheet - Standardized'!E$106 -> 0 | F91: =IF('Balance Sheet - Standardized'!F93="",0,'Balance Sheet - Standardized'!F93)/'Balance Sheet - Standardized'!F$106 -> 0 | G91: =IF('Balance Sheet - Standardized'!G93="",0,'Balance Sheet - Standardized'!G93)/'Balance Sheet - Standardized'!G$106 -> 0 | H91: =IF('Balance Sheet - Standardized'!H93="",0,'Balance Sheet - Standardized'!H93)/'Balance Sheet - Standardized'!H$106 -> 0 | I91: =IF('Balance Sheet - Standardized'!I93="",0,'Balance Sheet - Standardized'!I93)/'Balance Sheet - Standardized'!I$106 -> 0 | J91: =IF('Balance Sheet - Standardized'!J93="",0,'Balance Sheet - Standardized'!J93)/'Balance Sheet - Standardized'!J$106 -> 0 | ... L91: =IF('Balance Sheet - Standardized'!L93="",0,'Balance Sheet - Standardized'!L93)/'Balance Sheet - Standardized'!L$106 -> 0
A92: ='Balance Sheet - Standardized'!A94 -> + Pension Liabilities | B92: ='Balance Sheet - Standardized'!B94 -> PENSION_LIABILITIES | C92: =IF('Balance Sheet - Standardized'!C94="",0,'Balance Sheet - Standardized'!C94)/'Balance Sheet - Standardized'!C$106 -> 0.029112347 | D92: =IF('Balance Sheet - Standardized'!D94="",0,'Balance Sheet - Standardized'!D94)/'Balance Sheet - Standardized'!D$106 -> 0.026676329 | E92: =IF('Balance Sheet - Standardized'!E94="",0,'Balance Sheet - Standardized'!E94)/'Balance Sheet - Standardized'!E$106 -> 0.026294821 | F92: =IF('Balance Sheet - Standardized'!F94="",0,'Balance Sheet - Standardized'!F94)/'Balance Sheet - Standardized'!F$106 -> 0.025975313 | G92: =IF('Balance Sheet - Standardized'!G94="",0,'Balance Sheet - Standardized'!G94)/'Balance Sheet - Standardized'!G$106 -> 0.023433134 | H92: =IF('Balance Sheet - Standardized'!H94="",0,'Balance Sheet - Standardized'!H94)/'Balance Sheet - Standardized'!H$106 -> 0.019260896 | I92: =IF('Balance Sheet - Standardized'!I94="",0,'Balance Sheet - Standardized'!I94)/'Balance Sheet - Standardized'!I$106 -> 0.015417829 | J92: =IF('Balance Sheet - Standardized'!J94="",0,'Balance Sheet - Standardized'!J94)/'Balance Sheet - Standardized'!J$106 -> 0.015109876 | ... L92: =IF('Balance Sheet - Standardized'!L94="",0,'Balance Sheet - Standardized'!L94)/'Balance Sheet - Standardized'!L$106 -> 0.011097907
A93: ='Balance Sheet - Standardized'!A95 -> + Pensions | B93: ='Balance Sheet - Standardized'!B95 -> BS_PENSIONS_LT_LIABS | C93: =IF('Balance Sheet - Standardized'!C95="",0,'Balance Sheet - Standardized'!C95)/'Balance Sheet - Standardized'!C$106 -> 0 | D93: =IF('Balance Sheet - Standardized'!D95="",0,'Balance Sheet - Standardized'!D95)/'Balance Sheet - Standardized'!D$106 -> 0 | E93: =IF('Balance Sheet - Standardized'!E95="",0,'Balance Sheet - Standardized'!E95)/'Balance Sheet - Standardized'!E$106 -> 0 | F93: =IF('Balance Sheet - Standardized'!F95="",0,'Balance Sheet - Standardized'!F95)/'Balance Sheet - Standardized'!F$106 -> 0 | G93: =IF('Balance Sheet - Standardized'!G95="",0,'Balance Sheet - Standardized'!G95)/'Balance Sheet - Standardized'!G$106 -> 0 | H93: =IF('Balance Sheet - Standardized'!H95="",0,'Balance Sheet - Standardized'!H95)/'Balance Sheet - Standardized'!H$106 -> 0 | I93: =IF('Balance Sheet - Standardized'!I95="",0,'Balance Sheet - Standardized'!I95)/'Balance Sheet - Standardized'!I$106 -> 0 | J93: =IF('Balance Sheet - Standardized'!J95="",0,'Balance Sheet - Standardized'!J95)/'Balance Sheet - Standardized'!J$106 -> 0 | ... L93: =IF('Balance Sheet - Standardized'!L95="",0,'Balance Sheet - Standardized'!L95)/'Balance Sheet - Standardized'!L$106 -> 0
A94: ='Balance Sheet - Standardized'!A96 -> + Other Post-Ret Benefits | B94: ='Balance Sheet - Standardized'!B96 -> BS_OPRB_LT_LIABS | C94: =IF('Balance Sheet - Standardized'!C96="",0,'Balance Sheet - Standardized'!C96)/'Balance Sheet - Standardized'!C$106 -> 0 | D94: =IF('Balance Sheet - Standardized'!D96="",0,'Balance Sheet - Standardized'!D96)/'Balance Sheet - Standardized'!D$106 -> 0 | E94: =IF('Balance Sheet - Standardized'!E96="",0,'Balance Sheet - Standardized'!E96)/'Balance Sheet - Standardized'!E$106 -> 0 | F94: =IF('Balance Sheet - Standardized'!F96="",0,'Balance Sheet - Standardized'!F96)/'Balance Sheet - Standardized'!F$106 -> 0 | G94: =IF('Balance Sheet - Standardized'!G96="",0,'Balance Sheet - Standardized'!G96)/'Balance Sheet - Standardized'!G$106 -> 0 | H94: =IF('Balance Sheet - Standardized'!H96="",0,'Balance Sheet - Standardized'!H96)/'Balance Sheet - Standardized'!H$106 -> 0 | I94: =IF('Balance Sheet - Standardized'!I96="",0,'Balance Sheet - Standardized'!I96)/'Balance Sheet - Standardized'!I$106 -> 0 | J94: =IF('Balance Sheet - Standardized'!J96="",0,'Balance Sheet - Standardized'!J96)/'Balance Sheet - Standardized'!J$106 -> 0 | ... L94: =IF('Balance Sheet - Standardized'!L96="",0,'Balance Sheet - Standardized'!L96)/'Balance Sheet - Standardized'!L$106 -> 0
A95: ='Balance Sheet - Standardized'!A97 -> + Deferred Compensation | B95: ='Balance Sheet - Standardized'!B97 -> BS_DEFERRED_COMP_LT_LIABS | C95: =IF('Balance Sheet - Standardized'!C97="",0,'Balance Sheet - Standardized'!C97)/'Balance Sheet - Standardized'!C$106 -> 0 | D95: =IF('Balance Sheet - Standardized'!D97="",0,'Balance Sheet - Standardized'!D97)/'Balance Sheet - Standardized'!D$106 -> 0 | E95: =IF('Balance Sheet - Standardized'!E97="",0,'Balance Sheet - Standardized'!E97)/'Balance Sheet - Standardized'!E$106 -> 0 | F95: =IF('Balance Sheet - Standardized'!F97="",0,'Balance Sheet - Standardized'!F97)/'Balance Sheet - Standardized'!F$106 -> 0 | G95: =IF('Balance Sheet - Standardized'!G97="",0,'Balance Sheet - Standardized'!G97)/'Balance Sheet - Standardized'!G$106 -> 0 | H95: =IF('Balance Sheet - Standardized'!H97="",0,'Balance Sheet - Standardized'!H97)/'Balance Sheet - Standardized'!H$106 -> 0 | I95: =IF('Balance Sheet - Standardized'!I97="",0,'Balance Sheet - Standardized'!I97)/'Balance Sheet - Standardized'!I$106 -> 0 | J95: =IF('Balance Sheet - Standardized'!J97="",0,'Balance Sheet - Standardized'!J97)/'Balance Sheet - Standardized'!J$106 -> 0 | ... L95: =IF('Balance Sheet - Standardized'!L97="",0,'Balance Sheet - Standardized'!L97)/'Balance Sheet - Standardized'!L$106 -> 0
A96: ='Balance Sheet - Standardized'!A98 -> + LT Deferred Revenue | B96: ='Balance Sheet - Standardized'!B98 -> LT_DEFERRED_REVENUE | C96: =IF('Balance Sheet - Standardized'!C98="",0,'Balance Sheet - Standardized'!C98)/'Balance Sheet - Standardized'!C$106 -> 0 | D96: =IF('Balance Sheet - Standardized'!D98="",0,'Balance Sheet - Standardized'!D98)/'Balance Sheet - Standardized'!D$106 -> 0 | E96: =IF('Balance Sheet - Standardized'!E98="",0,'Balance Sheet - Standardized'!E98)/'Balance Sheet - Standardized'!E$106 -> 0 | F96: =IF('Balance Sheet - Standardized'!F98="",0,'Balance Sheet - Standardized'!F98)/'Balance Sheet - Standardized'!F$106 -> 0 | G96: =IF('Balance Sheet - Standardized'!G98="",0,'Balance Sheet - Standardized'!G98)/'Balance Sheet - Standardized'!G$106 -> 0 | H96: =IF('Balance Sheet - Standardized'!H98="",0,'Balance Sheet - Standardized'!H98)/'Balance Sheet - Standardized'!H$106 -> 0 | I96: =IF('Balance Sheet - Standardized'!I98="",0,'Balance Sheet - Standardized'!I98)/'Balance Sheet - Standardized'!I$106 -> 0 | J96: =IF('Balance Sheet - Standardized'!J98="",0,'Balance Sheet - Standardized'!J98)/'Balance Sheet - Standardized'!J$106 -> 0 | ... L96: =IF('Balance Sheet - Standardized'!L98="",0,'Balance Sheet - Standardized'!L98)/'Balance Sheet - Standardized'!L$106 -> 0
A97: ='Balance Sheet - Standardized'!A99 -> + LT Deferred Tax Liabilities | B97: ='Balance Sheet - Standardized'!B99 -> BS_DEFERRED_TAX_LIABILITIES_LT | C97: =IF('Balance Sheet - Standardized'!C99="",0,'Balance Sheet - Standardized'!C99)/'Balance Sheet - Standardized'!C$106 -> 0.0051833455 | D97: =IF('Balance Sheet - Standardized'!D99="",0,'Balance Sheet - Standardized'!D99)/'Balance Sheet - Standardized'!D$106 -> 0.005047102 | E97: =IF('Balance Sheet - Standardized'!E99="",0,'Balance Sheet - Standardized'!E99)/'Balance Sheet - Standardized'!E$106 -> 0.0048480236 | F97: =IF('Balance Sheet - Standardized'!F99="",0,'Balance Sheet - Standardized'!F99)/'Balance Sheet - Standardized'!F$106 -> 0.0037569204 | G97: =IF('Balance Sheet - Standardized'!G99="",0,'Balance Sheet - Standardized'!G99)/'Balance Sheet - Standardized'!G$106 -> 0.0032682862 | H97: =IF('Balance Sheet - Standardized'!H99="",0,'Balance Sheet - Standardized'!H99)/'Balance Sheet - Standardized'!H$106 -> 0.0027850305 | I97: =IF('Balance Sheet - Standardized'!I99="",0,'Balance Sheet - Standardized'!I99)/'Balance Sheet - Standardized'!I$106 -> 0.0033218298 | J97: =IF('Balance Sheet - Standardized'!J99="",0,'Balance Sheet - Standardized'!J99)/'Balance Sheet - Standardized'!J$106 -> 0.0023757883 | ... L97: =IF('Balance Sheet - Standardized'!L99="",0,'Balance Sheet - Standardized'!L99)/'Balance Sheet - Standardized'!L$106 -> 0.0033248265
A98: ='Balance Sheet - Standardized'!A100 -> + LT Derivatives & Hedging | B98: ='Balance Sheet - Standardized'!B100 -> BS_DERIVATIVE_&_HEDGING_LIABS_LT | C98: =IF('Balance Sheet - Standardized'!C100="",0,'Balance Sheet - Standardized'!C100)/'Balance Sheet - Standardized'!C$106 -> 0 | D98: =IF('Balance Sheet - Standardized'!D100="",0,'Balance Sheet - Standardized'!D100)/'Balance Sheet - Standardized'!D$106 -> 0 | E98: =IF('Balance Sheet - Standardized'!E100="",0,'Balance Sheet - Standardized'!E100)/'Balance Sheet - Standardized'!E$106 -> 0 | F98: =IF('Balance Sheet - Standardized'!F100="",0,'Balance Sheet - Standardized'!F100)/'Balance Sheet - Standardized'!F$106 -> 0 | G98: =IF('Balance Sheet - Standardized'!G100="",0,'Balance Sheet - Standardized'!G100)/'Balance Sheet - Standardized'!G$106 -> 0 | H98: =IF('Balance Sheet - Standardized'!H100="",0,'Balance Sheet - Standardized'!H100)/'Balance Sheet - Standardized'!H$106 -> 0 | I98: =IF('Balance Sheet - Standardized'!I100="",0,'Balance Sheet - Standardized'!I100)/'Balance Sheet - Standardized'!I$106 -> 0 | J98: =IF('Balance Sheet - Standardized'!J100="",0,'Balance Sheet - Standardized'!J100)/'Balance Sheet - Standardized'!J$106 -> 0 | ... L98: =IF('Balance Sheet - Standardized'!L100="",0,'Balance Sheet - Standardized'!L100)/'Balance Sheet - Standardized'!L$106 -> 0
A99: ='Balance Sheet - Standardized'!A101 -> + Liabilities of Discontinued Operations LT | B99: ='Balance Sheet - Standardized'!B101 -> BS_LIABS_OF_DISCONTINUED_OPS_LT | C99: =IF('Balance Sheet - Standardized'!C101="",0,'Balance Sheet - Standardized'!C101)/'Balance Sheet - Standardized'!C$106 -> 0 | D99: =IF('Balance Sheet - Standardized'!D101="",0,'Balance Sheet - Standardized'!D101)/'Balance Sheet - Standardized'!D$106 -> 0 | E99: =IF('Balance Sheet - Standardized'!E101="",0,'Balance Sheet - Standardized'!E101)/'Balance Sheet - Standardized'!E$106 -> 0 | F99: =IF('Balance Sheet - Standardized'!F101="",0,'Balance Sheet - Standardized'!F101)/'Balance Sheet - Standardized'!F$106 -> 0 | G99: =IF('Balance Sheet - Standardized'!G101="",0,'Balance Sheet - Standardized'!G101)/'Balance Sheet - Standardized'!G$106 -> 0 | H99: =IF('Balance Sheet - Standardized'!H101="",0,'Balance Sheet - Standardized'!H101)/'Balance Sheet - Standardized'!H$106 -> 0 | I99: =IF('Balance Sheet - Standardized'!I101="",0,'Balance Sheet - Standardized'!I101)/'Balance Sheet - Standardized'!I$106 -> 0 | J99: =IF('Balance Sheet - Standardized'!J101="",0,'Balance Sheet - Standardized'!J101)/'Balance Sheet - Standardized'!J$106 -> 0 | ... L99: =IF('Balance Sheet - Standardized'!L101="",0,'Balance Sheet - Standardized'!L101)/'Balance Sheet - Standardized'!L$106 -> 0
A100: ='Balance Sheet - Standardized'!A102 -> + Misc LT Liabilities | B100: ='Balance Sheet - Standardized'!B102 -> OTHER_NONCURRENT_LIABS_DETAILED | C100: =IF('Balance Sheet - Standardized'!C102="",0,'Balance Sheet - Standardized'!C102)/'Balance Sheet - Standardized'!C$106 -> 0.09756387 | D100: =IF('Balance Sheet - Standardized'!D102="",0,'Balance Sheet - Standardized'!D102)/'Balance Sheet - Standardized'!D$106 -> 0.083393721 | E100: =IF('Balance Sheet - Standardized'!E102="",0,'Balance Sheet - Standardized'!E102)/'Balance Sheet - Standardized'!E$106 -> 0.088495456 | F100: =IF('Balance Sheet - Standardized'!F102="",0,'Balance Sheet - Standardized'!F102)/'Balance Sheet - Standardized'!F$106 -> 0.11730467 | G100: =IF('Balance Sheet - Standardized'!G102="",0,'Balance Sheet - Standardized'!G102)/'Balance Sheet - Standardized'!G$106 -> 0.076490397 | H100: =IF('Balance Sheet - Standardized'!H102="",0,'Balance Sheet - Standardized'!H102)/'Balance Sheet - Standardized'!H$106 -> 0.067279239 | I100: =IF('Balance Sheet - Standardized'!I102="",0,'Balance Sheet - Standardized'!I102)/'Balance Sheet - Standardized'!I$106 -> 0.048081438 | J100: =IF('Balance Sheet - Standardized'!J102="",0,'Balance Sheet - Standardized'!J102)/'Balance Sheet - Standardized'!J$106 -> 0.055091394 | ... L100: =IF('Balance Sheet - Standardized'!L102="",0,'Balance Sheet - Standardized'!L102)/'Balance Sheet - Standardized'!L$106 -> 0.09022488
A101: ='Balance Sheet - Standardized'!A103 -> check
...

Sheet Income - GAAP
A1: Ticker | C1: =IF('Balance Sheet - Standardized'!C1="","",'Balance Sheet - Standardized'!C1) -> LNN | D1: ='Balance Sheet - Standardized'!D1 -> US | M1: Errors on check lines | N1: {=SUM(--ISERROR($C$13:$L$13),--ISERROR($C$18:$L$18),--ISERROR($C$20:$L$20),--ISERROR($C$29:$L$29),--ISERROR($C$31:$L$31),--ISERROR($C$36:$L$36),--ISERROR($C$41:$L$41),--ISERROR($C$43:$L$43),--ISERROR($C$49:$L$49),--ISERROR($C$51:$L$51),--ISERROR($C$55:$L$55),--ISERROR($C$59:$L$59),--ISERROR($C$63:$L$63), COUNT($C$13:$L$13) - COUNTIFS($C$13:$L$13,"<.1",$C$13:$L$13,">-.1"), COUNT($C$18:$L$18) - COUNTIFS($C$18:$L$18,"<.1", $C$18:$L$18,">-.1"), COUNT($C$20:$L$20) - COUNTIFS($C$20:$L$20,"<.1", $C$20:$L$20,">-.1"), COUNT($C$29:$L$29) - COUNTIFS($C$29:$L$29,"<.1", $C$29:$L$29,">-.1"), COUNT($C$31:$L$31) - COUNTIFS($C$31:$L$31,"<.1", $C$31:$L$31,">-.1"), COUNT($C$36:$L$36) - COUNTIFS($C$36:$L$36,"<.1", $C$36:$L$36,">-.1"), COUNT($C$41:$L$41) - COUNTIFS($C$41:$L$41,"<.1", $C$41:$L$41,">-.1"), COUNT($C$43:$L$43) - COUNTIFS($C$43:$L$43,"<.1", $C$43:$L$43,">-.1"),COUNT($C$49:$L$49) - COUNTIFS($C$49:$L$49,"<.1", $C$49:$L$49,">-.1"), COUNT($C$51:$L$51) - COUNTIFS($C$51:$L$51,"<.1", $C$51:$L$51,">-.1"), COUNT($C$55:$L$55) - COUNTIFS($C$55:$L$55,"<.1", $C$55:$L$55,">-.1"), COUNT($C$59:$L$59) - COUNTIFS($C$59:$L$59,"<.1", $C$59:$L$59,">-.1"), COUNT($C$63:$L$63) - COUNTIFS($C$63:$L$63,"<.1", $C$63:$L$63,">-.1"))} -> 0
A2: Start Year | C2: ='Balance Sheet - Standardized'!C2 -> FY 2016
A3: End Year | C3: ='Balance Sheet - Standardized'!C3 -> FY 2025
A7: In Millions of USD except Per Share | C7: ='Balance Sheet - Standardized'!C7 -> FY 2016 | D7: ='Balance Sheet - Standardized'!D7 -> FY 2017 | E7: ='Balance Sheet - Standardized'!E7 -> FY 2018 | F7: ='Balance Sheet - Standardized'!F7 -> FY 2019 | G7: ='Balance Sheet - Standardized'!G7 -> FY 2020 | H7: ='Balance Sheet - Standardized'!H7 -> FY 2021 | I7: ='Balance Sheet - Standardized'!I7 -> FY 2022 | J7: ='Balance Sheet - Standardized'!J7 -> FY 2023 | ... L7: ='Balance Sheet - Standardized'!L7 -> FY 2025
A8: 12 Months Ending | C8: ='Balance Sheet - Standardized'!C8 -> 42613 | D8: ='Balance Sheet - Standardized'!D8 -> 42978 | E8: ='Balance Sheet - Standardized'!E8 -> 43343 | F8: ='Balance Sheet - Standardized'!F8 -> 43708 | G8: ='Balance Sheet - Standardized'!G8 -> 44074 | H8: ='Balance Sheet - Standardized'!H8 -> 44439 | I8: ='Balance Sheet - Standardized'!I8 -> 44804 | J8: ='Balance Sheet - Standardized'!J8 -> 45169 | ... L8: ='Balance Sheet - Standardized'!L8 -> 45900
A9: Revenue | B9: SALES_REV_TURN | C9: 516.411 | D9: 517.985 | E9: 547.705 | F9: 444.072 | G9: 474.692 | H9: 567.646 | I9: 770.743 | J9: 674.084 | K9: 607.074 | L9: 676.368 | M9: =IF(OR(K9=0,K9=""),"",L9/K9-1) -> 0.11414424
A10: + Sales & Services Revenue | B10: IS_SALES_AND_SERVICES_REVENUES | C10: 516.411 | D10: 517.985 | E10: 547.705 | F10: 444.072 | G10: 474.692 | H10: 567.646 | I10: 770.743 | J10: 674.084 | K10: 607.074 | L10: 676.368
A11: + Financing Revenue | B11: IS_FINANCING_REVENUE
A12: + Other Revenue | B12: IS_OTHER_REVENUE
A13: check | C13: =ROUND(SUM(C10:C12)-IF(C9="",0,C9),1) -> 0 | D13: =ROUND(SUM(D10:D12)-IF(D9="",0,D9),1) -> 0 | E13: =ROUND(SUM(E10:E12)-IF(E9="",0,E9),1) -> 0 | F13: =ROUND(SUM(F10:F12)-IF(F9="",0,F9),1) -> 0 | G13: =ROUND(SUM(G10:G12)-IF(G9="",0,G9),1) -> 0 | H13: =ROUND(SUM(H10:H12)-IF(H9="",0,H9),1) -> 0 | I13: =ROUND(SUM(I10:I12)-IF(I9="",0,I9),1) -> 0 | J13: =ROUND(SUM(J10:J12)-IF(J9="",0,J9),1) -> 0 | ... L13: =ROUND(SUM(L10:L12)-IF(L9="",0,L9),1) -> 0
A14: - Cost of Revenue | B14: IS_COGS_TO_FE_AND_PP_AND_G | C14: 367.798 | D14: 372.973 | E14: 396.243 | F14: 329.464 | G14: 322.149 | H14: 417.441 | I14: 571.565 | J14: 461.069 | K14: 416.019 | L14: 465.588 | M14: =IF(OR(K14=0,K14=""),"",L14/K14-1) -> 0.11915081
A15: + Cost of Goods & Services | B15: IS_COG_AND_SERVICES_SOLD | C15: 367.798 | D15: 372.973 | E15: 396.243 | F15: 329.464 | G15: 322.149 | H15: 417.441 | I15: 571.565 | J15: 461.069 | K15: 416.019 | L15: 465.588
A16: + Depreciation & Amortization - COGS | B16: IS_DA_COST_OF_REVENUE_GAAP
A17: + Cost of Financing Revenue | B17: IS_COST_OF_FINANCING_REVENUE
A18: check | C18: =ROUND(SUM(C15:C17)-IF(C14="",0,C14),1) -> 0 | D18: =ROUND(SUM(D15:D17)-IF(D14="",0,D14),1) -> 0 | E18: =ROUND(SUM(E15:E17)-IF(E14="",0,E14),1) -> 0 | F18: =ROUND(SUM(F15:F17)-IF(F14="",0,F14),1) -> 0 | G18: =ROUND(SUM(G15:G17)-IF(G14="",0,G14),1) -> 0 | H18: =ROUND(SUM(H15:H17)-IF(H14="",0,H14),1) -> 0 | I18: =ROUND(SUM(I15:I17)-IF(I14="",0,I14),1) -> 0 | J18: =ROUND(SUM(J15:J17)-IF(J14="",0,J14),1) -> 0 | ... L18: =ROUND(SUM(L15:L17)-IF(L14="",0,L14),1) -> 0
A19: Gross Profit | B19: GROSS_PROFIT | C19: 148.613 | D19: 145.012 | E19: 151.462 | F19: 114.608 | G19: 152.543 | H19: 150.205 | I19: 199.178 | J19: 213.015 | K19: 191.055 | L19: 210.78 | M19: =IF(OR(K19=0,K19=""),"",L19/K19-1) -> 0.10324252
A20: check | C20: =ROUND(IF(C9="",0,C9)-IF(C14="",0,C14)-IF(C19="",0,C19),1) -> 0 | D20: =ROUND(IF(D9="",0,D9)-IF(D14="",0,D14)-IF(D19="",0,D19),1) -> 0 | E20: =ROUND(IF(E9="",0,E9)-IF(E14="",0,E14)-IF(E19="",0,E19),1) -> 0 | F20: =ROUND(IF(F9="",0,F9)-IF(F14="",0,F14)-IF(F19="",0,F19),1) -> 0 | G20: =ROUND(IF(G9="",0,G9)-IF(G14="",0,G14)-IF(G19="",0,G19),1) -> 0 | H20: =ROUND(IF(H9="",0,H9)-IF(H14="",0,H14)-IF(H19="",0,H19),1) -> 0 | I20: =ROUND(IF(I9="",0,I9)-IF(I14="",0,I14)-IF(I19="",0,I19),1) -> 0 | J20: =ROUND(IF(J9="",0,J9)-IF(J14="",0,J14)-IF(J19="",0,J19),1) -> 0 | ... L20: =ROUND(IF(L9="",0,L9)-IF(L14="",0,L14)-IF(L19="",0,L19),1) -> 0
A21: + Other Operating Income | B21: IS_OTHER_OPER_INC | C21: 0 | D21: 0 | E21: 0 | F21: 0 | G21: 0 | H21: 0 | I21: 0 | J21: 0 | K21: 0 | L21: 0
A22: - Operating Expenses | B22: IS_OPERATING_EXPN | C22: 114.238 | D22: 104.811 | E22: 112.899 | F22: 108.493 | G22: 98.341 | H22: 96.098 | I22: 104.535 | J22: 110.831 | K22: 114.447 | L22: 122.656 | M22: =IF(OR(K22=0,K22=""),"",L22/K22-1) -> 0.071727525
A23: + Selling, General & Admin | B23: IS_SG&A_EXPENSE | C23: 98.392 | D23: 87.664 | E23: 96.847 | F23: 94.557 | G23: 84.391 | H23: 82.739 | I23: 89.39 | J23: 92.613 | K23: 97.324 | L23: 104.726
A24: + Selling & Marketing | B24: IS_SELLING_EXPENSES | C24: 41.973 | D24: 40.705 | E24: 40.885 | F24: 30.82 | G24: 31.444 | H24: 30.816 | I24: 33.92 | J24: 36.201 | K24: 39.905 | L24: 41.74
A25: + General & Administrative | B25: IS_GENERAL_AND_ADMINISTRATIVE | C25: 56.419 | D25: 46.959 | E25: 55.962 | F25: 63.737 | G25: 52.947 | H25: 51.923 | I25: 55.47 | J25: 56.412 | K25: 57.419 | L25: 62.986
A26: + Research & Development | B26: IS_OPERATING_EXPENSES_R&D | C26: 15.846 | D26: 17.147 | E26: 16.052 | F26: 13.936 | G26: 13.95 | H26: 13.359 | I26: 15.145 | J26: 18.218 | K26: 17.123 | L26: 17.93
A27: + IS Depreciation & Amortization | B27: IS_DEPRECIATION_AND_AMORTIZATION
A28: + Other Operating Expense | B28: OTHER_OPERATING_EXPENSES_RATIO | C28: 0 | D28: 0 | E28: 0 | F28: 0 | G28: 0 | H28: 0 | I28: 0 | J28: 0 | K28: 0 | L28: 0
A29: check | C29: =ROUND(SUM(C23,C26,C27,C28)-IF(C22="",0,C22),1) -> 0 | D29: =ROUND(SUM(D23,D26,D27,D28)-IF(D22="",0,D22),1) -> 0 | E29: =ROUND(SUM(E23,E26,E27,E28)-IF(E22="",0,E22),1) -> 0 | F29: =ROUND(SUM(F23,F26,F27,F28)-IF(F22="",0,F22),1) -> 0 | G29: =ROUND(SUM(G23,G26,G27,G28)-IF(G22="",0,G22),1) -> 0 | H29: =ROUND(SUM(H23,H26,H27,H28)-IF(H22="",0,H22),1) -> 0 | I29: =ROUND(SUM(I23,I26,I27,I28)-IF(I22="",0,I22),1) -> 0 | J29: =ROUND(SUM(J23,J26,J27,J28)-IF(J22="",0,J22),1) -> 0 | ... L29: =ROUND(SUM(L23,L26,L27,L28)-IF(L22="",0,L22),1) -> 0
A30: Operating Income (Loss) | B30: IS_OPER_INC | C30: 34.375 | D30: 40.201 | E30: 38.563 | F30: 6.115 | G30: 54.202 | H30: 54.107 | I30: 94.643 | J30: 102.184 | K30: 76.608 | L30: 88.124 | M30: =IF(OR(K30=0,K30=""),"",L30/K30-1) -> 0.15032373
A31: check | C31: =ROUND(IF(C19="",0,C19)+IF(C21="",0,C21)-IF(C22="",0,C22)-IF(C30="",0,C30),1) -> 0 | D31: =ROUND(IF(D19="",0,D19)+IF(D21="",0,D21)-IF(D22="",0,D22)-IF(D30="",0,D30),1) -> 0 | E31: =ROUND(IF(E19="",0,E19)+IF(E21="",0,E21)-IF(E22="",0,E22)-IF(E30="",0,E30),1) -> 0 | F31: =ROUND(IF(F19="",0,F19)+IF(F21="",0,F21)-IF(F22="",0,F22)-IF(F30="",0,F30),1) -> 0 | G31: =ROUND(IF(G19="",0,G19)+IF(G21="",0,G21)-IF(G22="",0,G22)-IF(G30="",0,G30),1) -> 0 | H31: =ROUND(IF(H19="",0,H19)+IF(H21="",0,H21)-IF(H22="",0,H22)-IF(H30="",0,H30),1) -> 0 | I31: =ROUND(IF(I19="",0,I19)+IF(I21="",0,I21)-IF(I22="",0,I22)-IF(I30="",0,I30),1) -> 0 | J31: =ROUND(IF(J19="",0,J19)+IF(J21="",0,J21)-IF(J22="",0,J22)-IF(J30="",0,J30),1) -> 0 | ... L31: =ROUND(IF(L19="",0,L19)+IF(L21="",0,L21)-IF(L22="",0,L22)-IF(L30="",0,L30),1) -> 0
A32: - Non-Operating (Income) Loss | B32: NONOP_INCOME_LOSS | C32: 5.087 | D32: 4.486 | E32: 4.71 | F32: 4.008 | G32: 5.359 | H32: 3.721 | I32: 6.775 | J32: 1.809 | K32: -2.442 | L32: -6.459
A33: + Interest Expense, Net | B33: IS_NET_INTEREST_EXPENSE | C33: 4.106 | D33: 3.579 | E33: 3.047 | F33: 2.365 | G33: 2.803 | H33: 3.668 | I33: 3.647 | J33: 1.005 | K33: -1.955 | L33: -5.885
A34: + Interest Expense | B34: IS_INT_EXPENSE | C34: 4.751 | D34: 4.757 | E34: 4.687 | F34: 4.767 | G34: 4.759 | H34: 4.751 | I34: 4.269 | J34: 3.788 | K34: 3.234 | L34: 1.833
A35: - Interest Income | B35: IS_INT_INC | C35: 0.645 | D35: 1.178 | E35: 1.64 | F35: 2.402 | G35: 1.956 | H35: 1.083 | I35: 0.622 | J35: 2.783 | K35: 5.189 | L35: 7.718
A36: check | C36: =IF(AND(C34="",C35=""),0,ROUND(-IF(C35="",0,C35)+IF(C34="",0,C34)-IF(C33="",0,C33),1)) -> 0 | D36: =IF(AND(D34="",D35=""),0,ROUND(-IF(D35="",0,D35)+IF(D34="",0,D34)-IF(D33="",0,D33),1)) -> 0 | E36: =IF(AND(E34="",E35=""),0,ROUND(-IF(E35="",0,E35)+IF(E34="",0,E34)-IF(E33="",0,E33),1)) -> 0 | F36: =IF(AND(F34="",F35=""),0,ROUND(-IF(F35="",0,F35)+IF(F34="",0,F34)-IF(F33="",0,F33),1)) -> 0 | G36: =IF(AND(G34="",G35=""),0,ROUND(-IF(G35="",0,G35)+IF(G34="",0,G34)-IF(G33="",0,G33),1)) -> 0 | H36: =IF(AND(H34="",H35=""),0,ROUND(-IF(H35="",0,H35)+IF(H34="",0,H34)-IF(H33="",0,H33),1)) -> 0 | I36: =IF(AND(I34="",I35=""),0,ROUND(-IF(I35="",0,I35)+IF(I34="",0,I34)-IF(I33="",0,I33),1)) -> 0 | J36: =IF(AND(J34="",J35=""),0,ROUND(-IF(J35="",0,J35)+IF(J34="",0,J34)-IF(J33="",0,J33),1)) -> 0 | ... L36: =IF(AND(L34="",L35=""),0,ROUND(-IF(L35="",0,L35)+IF(L34="",0,L34)-IF(L33="",0,L33),1)) -> 0
A37: + Other Investment (Inc) Loss | B37: IS_OTHER_INVESTMENT_INCOME_LOSS
A38: + Foreign Exch (Gain) Loss | B38: IS_FOREIGN_EXCH_LOSS | C38: 0 | D38: 0 | E38: 0 | F38: 0 | G38: 0 | H38: 0 | I38: 0 | J38: 0 | K38: 0 | L38: 0
A39: + (Income) Loss from Affiliates | B39: INCOME_LOSS_FROM_AFFILIATES
A40: + Other Non-Op (Income) Loss | B40: OTHER_NONOP_INCOME_LOSS | C40: 0.981 | D40: 0.907 | E40: 1.663 | F40: 1.643 | G40: 2.556 | H40: 0.053 | I40: 3.128 | J40: 0.804 | K40: -0.487 | L40: -0.574
A41: check | C41: =ROUND(SUM(C33,C37:C40)-IF(C32="",0,C32),1) -> 0 | D41: =ROUND(SUM(D33,D37:D40)-IF(D32="",0,D32),1) -> 0 | E41: =ROUND(SUM(E33,E37:E40)-IF(E32="",0,E32),1) -> 0 | F41: =ROUND(SUM(F33,F37:F40)-IF(F32="",0,F32),1) -> 0 | G41: =ROUND(SUM(G33,G37:G40)-IF(G32="",0,G32),1) -> 0 | H41: =ROUND(SUM(H33,H37:H40)-IF(H32="",0,H32),1) -> 0 | I41: =ROUND(SUM(I33,I37:I40)-IF(I32="",0,I32),1) -> 0 | J41: =ROUND(SUM(J33,J37:J40)-IF(J32="",0,J32),1) -> 0 | ... L41: =ROUND(SUM(L33,L37:L40)-IF(L32="",0,L32),1) -> 0
A42: Pretax Income | B42: PRETAX_INC | C42: 29.288 | D42: 35.715 | E42: 33.853 | F42: 2.107 | G42: 48.843 | H42: 50.386 | I42: 87.868 | J42: 100.375 | K42: 79.05 | L42: 94.583 | M42: =IF(OR(K42=0,K42=""),"",L42/K42-1) -> 0.19649589
A43: check | C43: =ROUND(IF(C30="",0,C30)-IF(C32="",0,C32)-IF(C42="",0,C42),1) -> 0 | D43: =ROUND(IF(D30="",0,D30)-IF(D32="",0,D32)-IF(D42="",0,D42),1) -> 0 | E43: =ROUND(IF(E30="",0,E30)-IF(E32="",0,E32)-IF(E42="",0,E42),1) -> 0 | F43: =ROUND(IF(F30="",0,F30)-IF(F32="",0,F32)-IF(F42="",0,F42),1) -> 0 | G43: =ROUND(IF(G30="",0,G30)-IF(G32="",0,G32)-IF(G42="",0,G42),1) -> 0 | H43: =ROUND(IF(H30="",0,H30)-IF(H32="",0,H32)-IF(H42="",0,H42),1) -> 0 | I43: =ROUND(IF(I30="",0,I30)-IF(I32="",0,I32)-IF(I42="",0,I42),1) -> 0 | J43: =ROUND(IF(J30="",0,J30)-IF(J32="",0,J32)-IF(J42="",0,J42),1) -> 0 | ... L43: =ROUND(IF(L30="",0,L30)-IF(L32="",0,L32)-IF(L42="",0,L42),1) -> 0
A44: - Income Tax Expense (Benefit) | B44: IS_INC_TAX_EXP | C44: 9.021 | D44: 12.536 | E44: 13.576 | F44: -0.065 | G44: 10.214 | H44: 7.814 | I44: 22.399 | J44: 27.996 | K44: 12.793 | L44: 20.531
A45: + Current Income Tax | B45: IS_CURRENT_INCOME_TAX_BENEFIT | C45: 14.776 | D45: 13.439 | E45: 13.626 | F45: 5.621 | G45: 8.83 | H45: 5.903 | I45: 24.462 | J45: 27.996 | K45: 16.688 | L45: 21.964
A46: + Deferred Income Tax | B46: IS_DEFERRED_INCOME_TAX_BENEFIT | C46: -5.755 | D46: -0.903 | E46: -0.05 | F46: -5.686 | G46: 1.384 | H46: 1.911 | I46: -2.063 | K46: -3.895 | L46: -1.433
A47: + Tax Allowance/Credit | B47: IS_TAX_VALN_ALLOWNCE_CREDITS
A48: - (Income) Loss from Affiliates | B48: IS_SH_PRO_EQY_MT_INV_NET_OF_TAX
A49: check | C49: =IF(AND(C45="",C46="",C47=""),0,ROUND(SUM(C45:C47)-IF(C44="",0,C44),1)) -> 0 | D49: =IF(AND(D45="",D46="",D47=""),0,ROUND(SUM(D45:D47)-IF(D44="",0,D44),1)) -> 0 | E49: =IF(AND(E45="",E46="",E47=""),0,ROUND(SUM(E45:E47)-IF(E44="",0,E44),1)) -> 0 | F49: =IF(AND(F45="",F46="",F47=""),0,ROUND(SUM(F45:F47)-IF(F44="",0,F44),1)) -> 0 | G49: =IF(AND(G45="",G46="",G47=""),0,ROUND(SUM(G45:G47)-IF(G44="",0,G44),1)) -> 0 | H49: =IF(AND(H45="",H46="",H47=""),0,ROUND(SUM(H45:H47)-IF(H44="",0,H44),1)) -> 0 | I49: =IF(AND(I45="",I46="",I47=""),0,ROUND(SUM(I45:I47)-IF(I44="",0,I44),1)) -> 0 | J49: =IF(AND(J45="",J46="",J47=""),0,ROUND(SUM(J45:J47)-IF(J44="",0,J44),1)) -> 0 | ... L49: =IF(AND(L45="",L46="",L47=""),0,ROUND(SUM(L45:L47)-IF(L44="",0,L44),1)) -> 0
A50: Income (Loss) from Cont Ops | B50: IS_INC_BEF_XO_ITEM | C50: 20.267 | D50: 23.179 | E50: 20.277 | F50: 2.172 | G50: 38.629 | H50: 42.572 | I50: 65.469 | J50: 72.379 | K50: 66.257 | L50: 74.052
A51: check | C51: =ROUND(IF(C42="",0,C42)-IF(C44="",0,C44)-IF(C48="",0,C48)-IF(C50="",0,C50),1) -> 0 | D51: =ROUND(IF(D42="",0,D42)-IF(D44="",0,D44)-IF(D48="",0,D48)-IF(D50="",0,D50),1) -> 0 | E51: =ROUND(IF(E42="",0,E42)-IF(E44="",0,E44)-IF(E48="",0,E48)-IF(E50="",0,E50),1) -> 0 | F51: =ROUND(IF(F42="",0,F42)-IF(F44="",0,F44)-IF(F48="",0,F48)-IF(F50="",0,F50),1) -> 0 | G51: =ROUND(IF(G42="",0,G42)-IF(G44="",0,G44)-IF(G48="",0,G48)-IF(G50="",0,G50),1) -> 0 | H51: =ROUND(IF(H42="",0,H42)-IF(H44="",0,H44)-IF(H48="",0,H48)-IF(H50="",0,H50),1) -> 0 | I51: =ROUND(IF(I42="",0,I42)-IF(I44="",0,I44)-IF(I48="",0,I48)-IF(I50="",0,I50),1) -> 0 | J51: =ROUND(IF(J42="",0,J42)-IF(J44="",0,J44)-IF(J48="",0,J48)-IF(J50="",0,J50),1) -> 0 | ... L51: =ROUND(IF(L42="",0,L42)-IF(L44="",0,L44)-IF(L48="",0,L48)-IF(L50="",0,L50),1) -> 0
A52: - Net Extraordinary Losses (Gains) | B52: XO_GL_NET_OF_TAX | C52: 0 | D52: 0 | E52: 0 | F52: 0 | G52: 0 | H52: 0 | I52: 0 | J52: 0 | K52: 0 | L52: 0
A53: + Discontinued Operations | B53: IS_DISCONTINUED_OPERATIONS | C53: 0 | D53: 0 | E53: 0 | F53: 0 | G53: 0 | H53: 0 | I53: 0 | J53: 0 | K53: 0 | L53: 0
A54: + XO & Accounting Changes | B54: IS_EXTRAORD_ITEMS_&_ACCTG_CHNG | C54: 0 | D54: 0 | E54: 0 | F54: 0 | G54: 0 | H54: 0 | I54: 0 | J54: 0 | K54: 0 | L54: 0
A55: check | C55: =ROUND(SUM(C53:C54)-IF(C52="",0,C52),1) -> 0 | D55: =ROUND(SUM(D53:D54)-IF(D52="",0,D52),1) -> 0 | E55: =ROUND(SUM(E53:E54)-IF(E52="",0,E52),1) -> 0 | F55: =ROUND(SUM(F53:F54)-IF(F52="",0,F52),1) -> 0 | G55: =ROUND(SUM(G53:G54)-IF(G52="",0,G52),1) -> 0 | H55: =ROUND(SUM(H53:H54)-IF(H52="",0,H52),1) -> 0 | I55: =ROUND(SUM(I53:I54)-IF(I52="",0,I52),1) -> 0 | J55: =ROUND(SUM(J53:J54)-IF(J52="",0,J52),1) -> 0 | ... L55: =ROUND(SUM(L53:L54)-IF(L52="",0,L52),1) -> 0
A56: Income (Loss) Incl. MI | B56: NI_INCLUDING_MINORITY_INT_RATIO | C56: 20.267 | D56: 23.179 | E56: 20.277 | F56: 2.172 | G56: 38.629 | H56: 42.572 | I56: 65.469 | J56: 72.379 | K56: 66.257 | L56: 74.052
A57: - Minority Interest | B57: MIN_NONCONTROL_INTEREST_CREDITS | C57: 0 | D57: 0 | E57: 0 | F57: 0 | G57: 0 | H57: 0 | I57: 0 | J57: 0 | K57: 0 | L57: 0
A58: Net Income, GAAP | B58: NET_INCOME | C58: 20.267 | D58: 23.179 | E58: 20.277 | F58: 2.172 | G58: 38.629 | H58: 42.572 | I58: 65.469 | J58: 72.379 | K58: 66.257 | L58: 74.052 | M58: =IF(OR(K58=0,K58=""),"",L58/K58-1) -> 0.11764795
A59: check | C59: =ROUND(IF(C50="",0,C50)-IF(C52="",0,C52)-IF(C57="",0,C57)-IF(C58="",0,C58),1) -> 0 | D59: =ROUND(IF(D50="",0,D50)-IF(D52="",0,D52)-IF(D57="",0,D57)-IF(D58="",0,D58),1) -> 0 | E59: =ROUND(IF(E50="",0,E50)-IF(E52="",0,E52)-IF(E57="",0,E57)-IF(E58="",0,E58),1) -> 0 | F59: =ROUND(IF(F50="",0,F50)-IF(F52="",0,F52)-IF(F57="",0,F57)-IF(F58="",0,F58),1) -> 0 | G59: =ROUND(IF(G50="",0,G50)-IF(G52="",0,G52)-IF(G57="",0,G57)-IF(G58="",0,G58),1) -> 0 | H59: =ROUND(IF(H50="",0,H50)-IF(H52="",0,H52)-IF(H57="",0,H57)-IF(H58="",0,H58),1) -> 0 | I59: =ROUND(IF(I50="",0,I50)-IF(I52="",0,I52)-IF(I57="",0,I57)-IF(I58="",0,I58),1) -> 0 | J59: =ROUND(IF(J50="",0,J50)-IF(J52="",0,J52)-IF(J57="",0,J57)-IF(J58="",0,J58),1) -> 0 | ... L59: =ROUND(IF(L50="",0,L50)-IF(L52="",0,L52)-IF(L57="",0,L57)-IF(L58="",0,L58),1) -> 0
A60: - Preferred Dividends | B60: IS_TOT_CASH_PFD_DVD | C60: 0 | D60: 0 | E60: 0 | F60: 0 | G60: 0 | H60: 0 | I60: 0 | J60: 0 | K60: 0 | L60: 0
A61: - Other Adjustments | B61: OTHER_ADJUSTMENTS | C61: 0 | D61: 0 | E61: 0 | F61: 0 | G61: 0 | H61: 0 | I61: 0 | J61: 0 | K61: 0 | L61: 0
A62: Net Income Avail to Common, GAAP | B62: EARN_FOR_COMMON | C62: 20.267 | D62: 23.179 | E62: 20.277 | F62: 2.172 | G62: 38.629 | H62: 42.572 | I62: 65.469 | J62: 72.379 | K62: 66.257 | L62: 74.052 | M62: =IF(OR(K62=0,K62=""),"",L62/K62-1) -> 0.11764795
A63: check | C63: =ROUND(IF(C58="",0,C58)-IF(C60="",0,C60)-IF(C61="",0,C61)-IF(C62="",0,C62),1) -> 0 | D63: =ROUND(IF(D58="",0,D58)-IF(D60="",0,D60)-IF(D61="",0,D61)-IF(D62="",0,D62),1) -> 0 | E63: =ROUND(IF(E58="",0,E58)-IF(E60="",0,E60)-IF(E61="",0,E61)-IF(E62="",0,E62),1) -> 0 | F63: =ROUND(IF(F58="",0,F58)-IF(F60="",0,F60)-IF(F61="",0,F61)-IF(F62="",0,F62),1) -> 0 | G63: =ROUND(IF(G58="",0,G58)-IF(G60="",0,G60)-IF(G61="",0,G61)-IF(G62="",0,G62),1) -> 0 | H63: =ROUND(IF(H58="",0,H58)-IF(H60="",0,H60)-IF(H61="",0,H61)-IF(H62="",0,H62),1) -> 0 | I63: =ROUND(IF(I58="",0,I58)-IF(I60="",0,I60)-IF(I61="",0,I61)-IF(I62="",0,I62),1) -> 0 | J63: =ROUND(IF(J58="",0,J58)-IF(J60="",0,J60)-IF(J61="",0,J61)-IF(J62="",0,J62),1) -> 0 | ... L63: =ROUND(IF(L58="",0,L58)-IF(L60="",0,L60)-IF(L61="",0,L61)-IF(L62="",0,L62),1) -> 0
A65: Basic Weighted Avg Shares | B65: IS_AVG_NUM_SH_FOR_EPS | C65: 10.906 | D65: 10.666 | E65: 10.741 | F65: 10.781 | G65: 10.823 | H65: 10.886 | I65: 10.965 | J65: 11.003 | K65: 10.976 | L65: 10.859
A66: Basic EPS, GAAP | B66: IS_EPS | C66: 1.86 | D66: 2.17 | E66: 1.89 | F66: 0.2 | G66: 3.57 | H66: 3.91 | I66: 5.97 | J66: 6.58 | K66: 6.04 | L66: 6.82
A67: Basic EPS from Cont Ops | B67: IS_EARN_BEF_XO_ITEMS_PER_SH | C67: 1.86 | D67: 2.17 | E67: 1.89 | F67: 0.2 | G67: 3.57 | H67: 3.91 | I67: 5.97 | J67: 6.58 | K67: 6.04 | L67: 6.82
A68: Basic EPS from Cont Ops, Adjusted | B68: IS_BASIC_EPS_CONT_OPS | C68: 2.6377 | D68: 2.17 | E68: 2.4999 | F68: 1.2122 | G68: 3.4846 | H68: 3.8318 | I68: 5.97 | J68: 6.58 | K68: 6.04 | L68: 6.82
A70: Diluted Weighted Avg Shares | B70: IS_SH_FOR_DILUTED_EPS | C70: 10.93 | D70: 10.694 | E70: 10.772 | F70: 10.81 | G70: 10.861 | H70: 10.985 | I70: 11.031 | J70: 11.062 | K70: 11.017 | L70: 10.918
A71: Diluted EPS, GAAP | B71: IS_DILUTED_EPS | C71: 1.85 | D71: 2.17 | E71: 1.88 | F71: 0.2 | G71: 3.56 | H71: 3.88 | I71: 5.94 | J71: 6.54 | K71: 6.01 | L71: 6.78 | M71: =IF(OR(K71=0,K71=""),"",L71/K71-1) -> 0.1281198
A72: Diluted EPS from Cont Ops | B72: IS_DIL_EPS_BEF_XO | C72: 1.85 | D72: 2.17 | E72: 1.88 | F72: 0.2 | G72: 3.56 | H72: 3.88 | I72: 5.94 | J72: 6.54 | K72: 6.01 | L72: 6.78
A73: Diluted EPS from Cont Ops, Adjusted | B73: IS_DIL_EPS_CONT_OPS | C73: 2.6277 | D73: 2.17 | E73: 2.4903 | F73: 1.208 | G73: 3.4758 | H73: 3.8018 | I73: 5.94 | J73: 6.54 | K73: 6.01 | L73: 6.78
A75: Reference Items
A76: EBITDA | B76: EBITDA | C76: 51.256 | D76: 56.879 | E76: 55.077 | F76: 20.133 | G76: 79.597 | H76: 78.725 | I76: 120.394 | J76: 125.58 | K76: 102.194 | L76: 113.84
A77: EBITA | B77: EBITA | C77: 39.056 | D77: 44.679 | E77: 42.577 | F77: 9.033 | G77: 67.997 | H77: 66.025 | I77: 106.894 | J77: 111.68 | K77: 79.508 | L77: 90.324
A78: EBIT | B78: EBIT | C78: 34.375 | D78: 40.201 | E78: 38.563 | F78: 6.115 | G78: 54.202 | H78: 54.107 | I78: 94.643 | J78: 102.184 | K78: 76.608 | L78: 88.124
A79: Gross Margin | B79: GROSS_MARGIN | C79: 28.778 | D79: 27.9954 | E79: 27.6539 | F79: 25.8084 | G79: 32.1352 | H79: 26.461 | I79: 25.8423 | J79: 31.6007 | K79: 31.4715 | L79: 31.1635
A80: Operating Margin | B80: OPER_MARGIN | C80: 6.6565 | D80: 7.761 | E80: 7.0408 | F80: 1.377 | G80: 11.4184 | H80: 9.5318 | I80: 12.2794 | J80: 15.1589 | K80: 12.6192 | L80: 13.029
A81: Profit Margin | B81: PROF_MARGIN | C81: 3.9246 | D81: 4.4748 | E81: 3.7022 | F81: 0.4891 | G81: 8.1377 | H81: 7.4997 | I81: 8.4943 | J81: 10.7374 | K81: 10.9142 | L81: 10.9485
A82: Dividends per Share | B82: EQY_DPS | C82: 1.13 | D82: 1.17 | E82: 1.21 | F82: 1.24 | G82: 1.26 | H82: 1.3 | I82: 1.33 | J82: 1.37 | K82: 1.41 | L82: 1.45
A83: Depreciation Expense | B83: IS_DEPR_EXP | C83: 12.2 | D83: 12.2 | E83: 12.5 | F83: 11.1 | G83: 11.6 | H83: 12.7 | I83: 13.5 | J83: 13.9
A84: Rental Expense | B84: BS_CURR_RENTAL_EXPENSE | C84: 5 | D84: 5.1 | E84: 5 | F84: 5.4 | G84: 6.423 | H84: 5.949 | I84: 6.125 | J84: 4.65 | K84: 4.953 | L84: 5.394
M86: ="FY "&VALUE(RIGHT(L7,4))+1 -> FY 2026
A87: 10-k Total Shares Buybacks (Millions) | B87: BS_TOTAL_#_OF_SHARES_REPURCHASED | C87: 0.6888 | D87: 0 | E87: 0 | F87: 0 | G87: 0 | H87: 0 | I87: 0 | J87: 0 | K87: 0.0407 | L87: 0.0857
A88: $ Paid for Shares (Millions) | B88: BS_TOT_VAL_OF_SHARES_REPURCHASED | C88: 48.3 | D88: 0 | E88: 0 | F88: 0 | G88: 0 | H88: 0 | I88: 0 | J88: 0 | K88: 4.55 | L88: 11.42 | N88: =SUM(C88:L88) -> 64.27
A89: Total Shares Buybacks with Adjustment | C89: =IF(C87="","",C87*PRODUCT(C92:$M$92)) -> 0.6888 | D89: =IF(D87="","",D87*PRODUCT(D92:$M$92)) -> 0 | E89: =IF(E87="","",E87*PRODUCT(E92:$M$92)) -> 0 | F89: =IF(F87="","",F87*PRODUCT(F92:$M$92)) -> 0 | G89: =IF(G87="","",G87*PRODUCT(G92:$M$92)) -> 0 | H89: =IF(H87="","",H87*PRODUCT(H92:$M$92)) -> 0 | I89: =IF(I87="","",I87*PRODUCT(I92:$M$92)) -> 0 | J89: =IF(J87="","",J87*PRODUCT(J92:$M$92)) -> 0 | ... L89: =IF(L87="","",L87*PRODUCT(L92:$M$92)) -> 0.0857 | N89: =SUM(C89:L89) -> 0.8152
A90: Paid per Share | C90: =IF(OR(C88="", C89=""),"",C88/C89) -> 70.121951 | D90: =IF(OR(D88="", D89=""),"",D88/D89) -> #DIV/0! | E90: =IF(OR(E88="", E89=""),"",E88/E89) -> #DIV/0! | F90: =IF(OR(F88="", F89=""),"",F88/F89) -> #DIV/0! | G90: =IF(OR(G88="", G89=""),"",G88/G89) -> #DIV/0! | H90: =IF(OR(H88="", H89=""),"",H88/H89) -> #DIV/0! | I90: =IF(OR(I88="", I89=""),"",I88/I89) -> #DIV/0! | J90: =IF(OR(J88="", J89=""),"",J88/J89) -> #DIV/0! | ... L90: =IF(OR(L88="", L89=""),"",L88/L89) -> 133.25554 | N90: =N88/N89 -> 78.839549
A91: Purchase PE | C91: =IF(C90="","",C90/C71) -> 37.903757 | D91: =IF(D90="","",D90/D71) -> #DIV/0! | E91: =IF(E90="","",E90/E71) -> #DIV/0! | F91: =IF(F90="","",F90/F71) -> #DIV/0! | G91: =IF(G90="","",G90/G71) -> #DIV/0! | H91: =IF(H90="","",H90/H71) -> #DIV/0! | I91: =IF(I90="","",I90/I71) -> #DIV/0! | J91: =IF(J90="","",J90/J71) -> #DIV/0! | ... L91: =IF(L90="","",L90/L71) -> 19.65421
A92: Split Ratio | C92: =VLOOKUP(VALUE(RIGHT(C7,4)), SplitsByYear, 3, FALSE) -> 1 | D92: =VLOOKUP(VALUE(RIGHT(D7,4)), SplitsByYear, 3, FALSE) -> 1 | E92: =VLOOKUP(VALUE(RIGHT(E7,4)), SplitsByYear, 3, FALSE) -> 1 | F92: =VLOOKUP(VALUE(RIGHT(F7,4)), SplitsByYear, 3, FALSE) -> 1 | G92: =VLOOKUP(VALUE(RIGHT(G7,4)), SplitsByYear, 3, FALSE) -> 1 | H92: =VLOOKUP(VALUE(RIGHT(H7,4)), SplitsByYear, 3, FALSE) -> 1 | I92: =VLOOKUP(VALUE(RIGHT(I7,4)), SplitsByYear, 3, FALSE) -> 1 | J92: =VLOOKUP(VALUE(RIGHT(J7,4)), SplitsByYear, 3, FALSE) -> 1 | ... L92: =VLOOKUP(VALUE(RIGHT(L7,4)), SplitsByYear, 3, FALSE) -> 1 | M92: =VLOOKUP(VALUE(RIGHT(L7,4))+1, SplitsByYear, 3, FALSE) -> 1
A93: Closing Price (Sanity check with Buyback Price) | C93: 71.96 | D93: 86.57 | E93: 95.77 | F93: 88.26 | G93: 99.93 | H93: 164.75 | I93: 160.36 | J93: 124.1 | K93: 124.05 | L93: 137.23
A95: Extra Data Pulled from Bloomberg
A96: ="Retained Earnings FY "&RIGHT(C7,4)-1 -> Retained Earnings FY 2015 | B96: BS_PURE_RETAINED_EARNINGS | C96: 458.9
A97: ="EPS FY "&RIGHT($C$7,4)-1 -> EPS FY 2015 | B97: IS_DILUTED_EPS | C97: 2.22
A98: ="EPS FY "&RIGHT($C$7,4)-2 -> EPS FY 2014 | B98: IS_DILUTED_EPS | C98: 4
A99: ="EPS FY "&RIGHT($C$7,4)-3 -> EPS FY 2013 | B99: IS_DILUTED_EPS | C99: 5.47
A100: ="EPS FY "&RIGHT($C$7,4)-4 -> EPS FY 2012 | B100: IS_DILUTED_EPS | C100: 3.38
A101: ="EPS FY "&RIGHT($C$7,4)-5 -> EPS FY 2011 | B101: IS_DILUTED_EPS | C101: 2.9
A102: ="EPS FY "&RIGHT($C$7,4)-6 -> EPS FY 2010 | B102: IS_DILUTED_EPS | C102: 1.98
A103: ="EPS FY "&RIGHT($C$7,4)-7 -> EPS FY 2009 | B103: IS_DILUTED_EPS | C103: 1.11
A104: ="EPS FY "&RIGHT($C$7,4)-8 -> EPS FY 2008 | B104: IS_DILUTED_EPS | C104: 3.2
A105: ="EPS FY "&RIGHT($C$7,4)-9 -> EPS FY 2007 | B105: IS_DILUTED_EPS | C105: 1.31
A106: Current 10 Year Treasury Rate | C106: 4.6762

Sheet IS%
A1: ='Income - GAAP'!A1 -> Ticker | C1: =IF('Balance Sheet - Standardized'!C1="","",'Balance Sheet - Standardized'!C1) -> LNN
A2: ='Income - GAAP'!A2 -> Start Year | C2: ='Income - GAAP'!C2 -> FY 2016
A3: ='Income - GAAP'!A3 -> End Year | C3: ='Income - GAAP'!C3 -> FY 2025
A7: ='Income - GAAP'!A7 -> In Millions of USD except Per Share | C7: ='Income - GAAP'!C7 -> FY 2016 | D7: ='Income - GAAP'!D7 -> FY 2017 | E7: ='Income - GAAP'!E7 -> FY 2018 | F7: ='Income - GAAP'!F7 -> FY 2019 | G7: ='Income - GAAP'!G7 -> FY 2020 | H7: ='Income - GAAP'!H7 -> FY 2021 | I7: ='Income - GAAP'!I7 -> FY 2022 | J7: ='Income - GAAP'!J7 -> FY 2023 | ... L7: ='Income - GAAP'!L7 -> FY 2025
A8: ='Income - GAAP'!A8 -> 12 Months Ending | C8: ='Income - GAAP'!C8 -> 42613 | D8: ='Income - GAAP'!D8 -> 42978 | E8: ='Income - GAAP'!E8 -> 43343 | F8: ='Income - GAAP'!F8 -> 43708 | G8: ='Income - GAAP'!G8 -> 44074 | H8: ='Income - GAAP'!H8 -> 44439 | I8: ='Income - GAAP'!I8 -> 44804 | J8: ='Income - GAAP'!J8 -> 45169 | ... L8: ='Income - GAAP'!L8 -> 45900
A9: ='Income - GAAP'!A9 -> Revenue | B9: ='Income - GAAP'!B9 -> SALES_REV_TURN | C9: =IF('Income - GAAP'!C9="",0,'Income - GAAP'!C9)/'Income - GAAP'!C$9 -> 1 | D9: =IF('Income - GAAP'!D9="",0,'Income - GAAP'!D9)/'Income - GAAP'!D$9 -> 1 | E9: =IF('Income - GAAP'!E9="",0,'Income - GAAP'!E9)/'Income - GAAP'!E$9 -> 1 | F9: =IF('Income - GAAP'!F9="",0,'Income - GAAP'!F9)/'Income - GAAP'!F$9 -> 1 | G9: =IF('Income - GAAP'!G9="",0,'Income - GAAP'!G9)/'Income - GAAP'!G$9 -> 1 | H9: =IF('Income - GAAP'!H9="",0,'Income - GAAP'!H9)/'Income - GAAP'!H$9 -> 1 | I9: =IF('Income - GAAP'!I9="",0,'Income - GAAP'!I9)/'Income - GAAP'!I$9 -> 1 | J9: =IF('Income - GAAP'!J9="",0,'Income - GAAP'!J9)/'Income - GAAP'!J$9 -> 1 | ... L9: =IF('Income - GAAP'!L9="",0,'Income - GAAP'!L9)/'Income - GAAP'!L$9 -> 1
A10: ='Income - GAAP'!A10 -> + Sales & Services Revenue | B10: ='Income - GAAP'!B10 -> IS_SALES_AND_SERVICES_REVENUES | C10: =IF('Income - GAAP'!C10="",0,'Income - GAAP'!C10)/'Income - GAAP'!C$9 -> 1 | D10: =IF('Income - GAAP'!D10="",0,'Income - GAAP'!D10)/'Income - GAAP'!D$9 -> 1 | E10: =IF('Income - GAAP'!E10="",0,'Income - GAAP'!E10)/'Income - GAAP'!E$9 -> 1 | F10: =IF('Income - GAAP'!F10="",0,'Income - GAAP'!F10)/'Income - GAAP'!F$9 -> 1 | G10: =IF('Income - GAAP'!G10="",0,'Income - GAAP'!G10)/'Income - GAAP'!G$9 -> 1 | H10: =IF('Income - GAAP'!H10="",0,'Income - GAAP'!H10)/'Income - GAAP'!H$9 -> 1 | I10: =IF('Income - GAAP'!I10="",0,'Income - GAAP'!I10)/'Income - GAAP'!I$9 -> 1 | J10: =IF('Income - GAAP'!J10="",0,'Income - GAAP'!J10)/'Income - GAAP'!J$9 -> 1 | ... L10: =IF('Income - GAAP'!L10="",0,'Income - GAAP'!L10)/'Income - GAAP'!L$9 -> 1
A11: ='Income - GAAP'!A11 -> + Financing Revenue | B11: ='Income - GAAP'!B11 -> IS_FINANCING_REVENUE | C11: =IF('Income - GAAP'!C11="",0,'Income - GAAP'!C11)/'Income - GAAP'!C$9 -> 0 | D11: =IF('Income - GAAP'!D11="",0,'Income - GAAP'!D11)/'Income - GAAP'!D$9 -> 0 | E11: =IF('Income - GAAP'!E11="",0,'Income - GAAP'!E11)/'Income - GAAP'!E$9 -> 0 | F11: =IF('Income - GAAP'!F11="",0,'Income - GAAP'!F11)/'Income - GAAP'!F$9 -> 0 | G11: =IF('Income - GAAP'!G11="",0,'Income - GAAP'!G11)/'Income - GAAP'!G$9 -> 0 | H11: =IF('Income - GAAP'!H11="",0,'Income - GAAP'!H11)/'Income - GAAP'!H$9 -> 0 | I11: =IF('Income - GAAP'!I11="",0,'Income - GAAP'!I11)/'Income - GAAP'!I$9 -> 0 | J11: =IF('Income - GAAP'!J11="",0,'Income - GAAP'!J11)/'Income - GAAP'!J$9 -> 0 | ... L11: =IF('Income - GAAP'!L11="",0,'Income - GAAP'!L11)/'Income - GAAP'!L$9 -> 0
A12: ='Income - GAAP'!A12 -> + Other Revenue | B12: ='Income - GAAP'!B12 -> IS_OTHER_REVENUE | C12: =IF('Income - GAAP'!C12="",0,'Income - GAAP'!C12)/'Income - GAAP'!C$9 -> 0 | D12: =IF('Income - GAAP'!D12="",0,'Income - GAAP'!D12)/'Income - GAAP'!D$9 -> 0 | E12: =IF('Income - GAAP'!E12="",0,'Income - GAAP'!E12)/'Income - GAAP'!E$9 -> 0 | F12: =IF('Income - GAAP'!F12="",0,'Income - GAAP'!F12)/'Income - GAAP'!F$9 -> 0 | G12: =IF('Income - GAAP'!G12="",0,'Income - GAAP'!G12)/'Income - GAAP'!G$9 -> 0 | H12: =IF('Income - GAAP'!H12="",0,'Income - GAAP'!H12)/'Income - GAAP'!H$9 -> 0 | I12: =IF('Income - GAAP'!I12="",0,'Income - GAAP'!I12)/'Income - GAAP'!I$9 -> 0 | J12: =IF('Income - GAAP'!J12="",0,'Income - GAAP'!J12)/'Income - GAAP'!J$9 -> 0 | ... L12: =IF('Income - GAAP'!L12="",0,'Income - GAAP'!L12)/'Income - GAAP'!L$9 -> 0
A13: ='Income - GAAP'!A13 -> check
A14: ='Income - GAAP'!A14 -> - Cost of Revenue | B14: ='Income - GAAP'!B14 -> IS_COGS_TO_FE_AND_PP_AND_G | C14: =IF('Income - GAAP'!C14="",0,'Income - GAAP'!C14)/'Income - GAAP'!C$9 -> 0.71221953 | D14: =IF('Income - GAAP'!D14="",0,'Income - GAAP'!D14)/'Income - GAAP'!D$9 -> 0.72004595 | E14: =IF('Income - GAAP'!E14="",0,'Income - GAAP'!E14)/'Income - GAAP'!E$9 -> 0.72346062 | F14: =IF('Income - GAAP'!F14="",0,'Income - GAAP'!F14)/'Income - GAAP'!F$9 -> 0.74191573 | G14: =IF('Income - GAAP'!G14="",0,'Income - GAAP'!G14)/'Income - GAAP'!G$9 -> 0.67864847 | H14: =IF('Income - GAAP'!H14="",0,'Income - GAAP'!H14)/'Income - GAAP'!H$9 -> 0.73538966 | I14: =IF('Income - GAAP'!I14="",0,'Income - GAAP'!I14)/'Income - GAAP'!I$9 -> 0.74157663 | J14: =IF('Income - GAAP'!J14="",0,'Income - GAAP'!J14)/'Income - GAAP'!J$9 -> 0.68399339 | ... L14: =IF('Income - GAAP'!L14="",0,'Income - GAAP'!L14)/'Income - GAAP'!L$9 -> 0.68836491
A15: ='Income - GAAP'!A15 -> + Cost of Goods & Services | B15: ='Income - GAAP'!B15 -> IS_COG_AND_SERVICES_SOLD | C15: =IF('Income - GAAP'!C15="",0,'Income - GAAP'!C15)/'Income - GAAP'!C$9 -> 0.71221953 | D15: =IF('Income - GAAP'!D15="",0,'Income - GAAP'!D15)/'Income - GAAP'!D$9 -> 0.72004595 | E15: =IF('Income - GAAP'!E15="",0,'Income - GAAP'!E15)/'Income - GAAP'!E$9 -> 0.72346062 | F15: =IF('Income - GAAP'!F15="",0,'Income - GAAP'!F15)/'Income - GAAP'!F$9 -> 0.74191573 | G15: =IF('Income - GAAP'!G15="",0,'Income - GAAP'!G15)/'Income - GAAP'!G$9 -> 0.67864847 | H15: =IF('Income - GAAP'!H15="",0,'Income - GAAP'!H15)/'Income - GAAP'!H$9 -> 0.73538966 | I15: =IF('Income - GAAP'!I15="",0,'Income - GAAP'!I15)/'Income - GAAP'!I$9 -> 0.74157663 | J15: =IF('Income - GAAP'!J15="",0,'Income - GAAP'!J15)/'Income - GAAP'!J$9 -> 0.68399339 | ... L15: =IF('Income - GAAP'!L15="",0,'Income - GAAP'!L15)/'Income - GAAP'!L$9 -> 0.68836491
A16: ='Income - GAAP'!A16 -> + Depreciation & Amortization - COGS | B16: ='Income - GAAP'!B16 -> IS_DA_COST_OF_REVENUE_GAAP | C16: =IF('Income - GAAP'!C16="",0,'Income - GAAP'!C16)/'Income - GAAP'!C$9 -> 0 | D16: =IF('Income - GAAP'!D16="",0,'Income - GAAP'!D16)/'Income - GAAP'!D$9 -> 0 | E16: =IF('Income - GAAP'!E16="",0,'Income - GAAP'!E16)/'Income - GAAP'!E$9 -> 0 | F16: =IF('Income - GAAP'!F16="",0,'Income - GAAP'!F16)/'Income - GAAP'!F$9 -> 0 | G16: =IF('Income - GAAP'!G16="",0,'Income - GAAP'!G16)/'Income - GAAP'!G$9 -> 0 | H16: =IF('Income - GAAP'!H16="",0,'Income - GAAP'!H16)/'Income - GAAP'!H$9 -> 0 | I16: =IF('Income - GAAP'!I16="",0,'Income - GAAP'!I16)/'Income - GAAP'!I$9 -> 0 | J16: =IF('Income - GAAP'!J16="",0,'Income - GAAP'!J16)/'Income - GAAP'!J$9 -> 0 | ... L16: =IF('Income - GAAP'!L16="",0,'Income - GAAP'!L16)/'Income - GAAP'!L$9 -> 0
A17: ='Income - GAAP'!A17 -> + Cost of Financing Revenue | B17: ='Income - GAAP'!B17 -> IS_COST_OF_FINANCING_REVENUE | C17: =IF('Income - GAAP'!C17="",0,'Income - GAAP'!C17)/'Income - GAAP'!C$9 -> 0 | D17: =IF('Income - GAAP'!D17="",0,'Income - GAAP'!D17)/'Income - GAAP'!D$9 -> 0 | E17: =IF('Income - GAAP'!E17="",0,'Income - GAAP'!E17)/'Income - GAAP'!E$9 -> 0 | F17: =IF('Income - GAAP'!F17="",0,'Income - GAAP'!F17)/'Income - GAAP'!F$9 -> 0 | G17: =IF('Income - GAAP'!G17="",0,'Income - GAAP'!G17)/'Income - GAAP'!G$9 -> 0 | H17: =IF('Income - GAAP'!H17="",0,'Income - GAAP'!H17)/'Income - GAAP'!H$9 -> 0 | I17: =IF('Income - GAAP'!I17="",0,'Income - GAAP'!I17)/'Income - GAAP'!I$9 -> 0 | J17: =IF('Income - GAAP'!J17="",0,'Income - GAAP'!J17)/'Income - GAAP'!J$9 -> 0 | ... L17: =IF('Income - GAAP'!L17="",0,'Income - GAAP'!L17)/'Income - GAAP'!L$9 -> 0
A18: ='Income - GAAP'!A18 -> check
A19: ='Income - GAAP'!A19 -> Gross Profit | B19: ='Income - GAAP'!B19 -> GROSS_PROFIT | C19: =IF('Income - GAAP'!C19="",0,'Income - GAAP'!C19)/'Income - GAAP'!C$9 -> 0.28778047 | D19: =IF('Income - GAAP'!D19="",0,'Income - GAAP'!D19)/'Income - GAAP'!D$9 -> 0.27995405 | E19: =IF('Income - GAAP'!E19="",0,'Income - GAAP'!E19)/'Income - GAAP'!E$9 -> 0.27653938 | F19: =IF('Income - GAAP'!F19="",0,'Income - GAAP'!F19)/'Income - GAAP'!F$9 -> 0.25808427 | G19: =IF('Income - GAAP'!G19="",0,'Income - GAAP'!G19)/'Income - GAAP'!G$9 -> 0.32135153 | H19: =IF('Income - GAAP'!H19="",0,'Income - GAAP'!H19)/'Income - GAAP'!H$9 -> 0.26461034 | I19: =IF('Income - GAAP'!I19="",0,'Income - GAAP'!I19)/'Income - GAAP'!I$9 -> 0.25842337 | J19: =IF('Income - GAAP'!J19="",0,'Income - GAAP'!J19)/'Income - GAAP'!J$9 -> 0.31600661 | ... L19: =IF('Income - GAAP'!L19="",0,'Income - GAAP'!L19)/'Income - GAAP'!L$9 -> 0.31163509
A20: ='Income - GAAP'!A20 -> check
A21: ='Income - GAAP'!A21 -> + Other Operating Income | B21: ='Income - GAAP'!B21 -> IS_OTHER_OPER_INC | C21: =IF('Income - GAAP'!C21="",0,'Income - GAAP'!C21)/'Income - GAAP'!C$9 -> 0 | D21: =IF('Income - GAAP'!D21="",0,'Income - GAAP'!D21)/'Income - GAAP'!D$9 -> 0 | E21: =IF('Income - GAAP'!E21="",0,'Income - GAAP'!E21)/'Income - GAAP'!E$9 -> 0 | F21: =IF('Income - GAAP'!F21="",0,'Income - GAAP'!F21)/'Income - GAAP'!F$9 -> 0 | G21: =IF('Income - GAAP'!G21="",0,'Income - GAAP'!G21)/'Income - GAAP'!G$9 -> 0 | H21: =IF('Income - GAAP'!H21="",0,'Income - GAAP'!H21)/'Income - GAAP'!H$9 -> 0 | I21: =IF('Income - GAAP'!I21="",0,'Income - GAAP'!I21)/'Income - GAAP'!I$9 -> 0 | J21: =IF('Income - GAAP'!J21="",0,'Income - GAAP'!J21)/'Income - GAAP'!J$9 -> 0 | ... L21: =IF('Income - GAAP'!L21="",0,'Income - GAAP'!L21)/'Income - GAAP'!L$9 -> 0
A22: ='Income - GAAP'!A22 -> - Operating Expenses | B22: ='Income - GAAP'!B22 -> IS_OPERATING_EXPN | C22: =IF('Income - GAAP'!C22="",0,'Income - GAAP'!C22)/'Income - GAAP'!C$9 -> 0.22121527 | D22: =IF('Income - GAAP'!D22="",0,'Income - GAAP'!D22)/'Income - GAAP'!D$9 -> 0.2023437 | E22: =IF('Income - GAAP'!E22="",0,'Income - GAAP'!E22)/'Income - GAAP'!E$9 -> 0.20613104 | F22: =IF('Income - GAAP'!F22="",0,'Income - GAAP'!F22)/'Income - GAAP'!F$9 -> 0.24431399 | G22: =IF('Income - GAAP'!G22="",0,'Income - GAAP'!G22)/'Income - GAAP'!G$9 -> 0.20716802 | H22: =IF('Income - GAAP'!H22="",0,'Income - GAAP'!H22)/'Income - GAAP'!H$9 -> 0.16929213 | I22: =IF('Income - GAAP'!I22="",0,'Income - GAAP'!I22)/'Income - GAAP'!I$9 -> 0.13562887 | J22: =IF('Income - GAAP'!J22="",0,'Income - GAAP'!J22)/'Income - GAAP'!J$9 -> 0.16441719 | ... L22: =IF('Income - GAAP'!L22="",0,'Income - GAAP'!L22)/'Income - GAAP'!L$9 -> 0.18134507
A23: ='Income - GAAP'!A23 -> + Selling, General & Admin | B23: ='Income - GAAP'!B23 -> IS_SG&A_EXPENSE | C23: =IF('Income - GAAP'!C23="",0,'Income - GAAP'!C23)/'Income - GAAP'!C$9 -> 0.19053041 | D23: =IF('Income - GAAP'!D23="",0,'Income - GAAP'!D23)/'Income - GAAP'!D$9 -> 0.16924042 | E23: =IF('Income - GAAP'!E23="",0,'Income - GAAP'!E23)/'Income - GAAP'!E$9 -> 0.17682329 | F23: =IF('Income - GAAP'!F23="",0,'Income - GAAP'!F23)/'Income - GAAP'!F$9 -> 0.21293169 | G23: =IF('Income - GAAP'!G23="",0,'Income - GAAP'!G23)/'Income - GAAP'!G$9 -> 0.17778054 | H23: =IF('Income - GAAP'!H23="",0,'Income - GAAP'!H23)/'Income - GAAP'!H$9 -> 0.1457581 | I23: =IF('Income - GAAP'!I23="",0,'Income - GAAP'!I23)/'Income - GAAP'!I$9 -> 0.115979 | J23: =IF('Income - GAAP'!J23="",0,'Income - GAAP'!J23)/'Income - GAAP'!J$9 -> 0.13739089 | ... L23: =IF('Income - GAAP'!L23="",0,'Income - GAAP'!L23)/'Income - GAAP'!L$9 -> 0.15483583
A24: ='Income - GAAP'!A24 -> + Selling & Marketing | B24: ='Income - GAAP'!B24 -> IS_SELLING_EXPENSES | C24: =IF('Income - GAAP'!C24="",0,'Income - GAAP'!C24)/'Income - GAAP'!C$9 -> 0.081278284 | D24: =IF('Income - GAAP'!D24="",0,'Income - GAAP'!D24)/'Income - GAAP'!D$9 -> 0.078583357 | E24: =IF('Income - GAAP'!E24="",0,'Income - GAAP'!E24)/'Income - GAAP'!E$9 -> 0.074647849 | F24: =IF('Income - GAAP'!F24="",0,'Income - GAAP'!F24)/'Income - GAAP'!F$9 -> 0.06940316 | G24: =IF('Income - GAAP'!G24="",0,'Income - GAAP'!G24)/'Income - GAAP'!G$9 -> 0.066240847 | H24: =IF('Income - GAAP'!H24="",0,'Income - GAAP'!H24)/'Income - GAAP'!H$9 -> 0.054287355 | I24: =IF('Income - GAAP'!I24="",0,'Income - GAAP'!I24)/'Income - GAAP'!I$9 -> 0.044009482 | J24: =IF('Income - GAAP'!J24="",0,'Income - GAAP'!J24)/'Income - GAAP'!J$9 -> 0.053703989 | ... L24: =IF('Income - GAAP'!L24="",0,'Income - GAAP'!L24)/'Income - GAAP'!L$9 -> 0.061711967
A25: ='Income - GAAP'!A25 -> + General & Administrative | B25: ='Income - GAAP'!B25 -> IS_GENERAL_AND_ADMINISTRATIVE | C25: =IF('Income - GAAP'!C25="",0,'Income - GAAP'!C25)/'Income - GAAP'!C$9 -> 0.10925213 | D25: =IF('Income - GAAP'!D25="",0,'Income - GAAP'!D25)/'Income - GAAP'!D$9 -> 0.090657065 | E25: =IF('Income - GAAP'!E25="",0,'Income - GAAP'!E25)/'Income - GAAP'!E$9 -> 0.10217544 | F25: =IF('Income - GAAP'!F25="",0,'Income - GAAP'!F25)/'Income - GAAP'!F$9 -> 0.14352853 | G25: =IF('Income - GAAP'!G25="",0,'Income - GAAP'!G25)/'Income - GAAP'!G$9 -> 0.11153969 | H25: =IF('Income - GAAP'!H25="",0,'Income - GAAP'!H25)/'Income - GAAP'!H$9 -> 0.091470741 | I25: =IF('Income - GAAP'!I25="",0,'Income - GAAP'!I25)/'Income - GAAP'!I$9 -> 0.071969515 | J25: =IF('Income - GAAP'!J25="",0,'Income - GAAP'!J25)/'Income - GAAP'!J$9 -> 0.0836869 | ... L25: =IF('Income - GAAP'!L25="",0,'Income - GAAP'!L25)/'Income - GAAP'!L$9 -> 0.093123862
A26: ='Income - GAAP'!A26 -> + Research & Development | B26: ='Income - GAAP'!B26 -> IS_OPERATING_EXPENSES_R&D | C26: =IF('Income - GAAP'!C26="",0,'Income - GAAP'!C26)/'Income - GAAP'!C$9 -> 0.030684861 | D26: =IF('Income - GAAP'!D26="",0,'Income - GAAP'!D26)/'Income - GAAP'!D$9 -> 0.033103275 | E26: =IF('Income - GAAP'!E26="",0,'Income - GAAP'!E26)/'Income - GAAP'!E$9 -> 0.029307748 | F26: =IF('Income - GAAP'!F26="",0,'Income - GAAP'!F26)/'Income - GAAP'!F$9 -> 0.031382298 | G26: =IF('Income - GAAP'!G26="",0,'Income - GAAP'!G26)/'Income - GAAP'!G$9 -> 0.029387477 | H26: =IF('Income - GAAP'!H26="",0,'Income - GAAP'!H26)/'Income - GAAP'!H$9 -> 0.023534034 | I26: =IF('Income - GAAP'!I26="",0,'Income - GAAP'!I26)/'Income - GAAP'!I$9 -> 0.01964987 | J26: =IF('Income - GAAP'!J26="",0,'Income - GAAP'!J26)/'Income - GAAP'!J$9 -> 0.027026305 | ... L26: =IF('Income - GAAP'!L26="",0,'Income - GAAP'!L26)/'Income - GAAP'!L$9 -> 0.026509238
A27: ='Income - GAAP'!A27 -> + IS Depreciation & Amortization | B27: ='Income - GAAP'!B27 -> IS_DEPRECIATION_AND_AMORTIZATION | C27: =IF('Income - GAAP'!C27="",0,'Income - GAAP'!C27)/'Income - GAAP'!C$9 -> 0 | D27: =IF('Income - GAAP'!D27="",0,'Income - GAAP'!D27)/'Income - GAAP'!D$9 -> 0 | E27: =IF('Income - GAAP'!E27="",0,'Income - GAAP'!E27)/'Income - GAAP'!E$9 -> 0 | F27: =IF('Income - GAAP'!F27="",0,'Income - GAAP'!F27)/'Income - GAAP'!F$9 -> 0 | G27: =IF('Income - GAAP'!G27="",0,'Income - GAAP'!G27)/'Income - GAAP'!G$9 -> 0 | H27: =IF('Income - GAAP'!H27="",0,'Income - GAAP'!H27)/'Income - GAAP'!H$9 -> 0 | I27: =IF('Income - GAAP'!I27="",0,'Income - GAAP'!I27)/'Income - GAAP'!I$9 -> 0 | J27: =IF('Income - GAAP'!J27="",0,'Income - GAAP'!J27)/'Income - GAAP'!J$9 -> 0 | ... L27: =IF('Income - GAAP'!L27="",0,'Income - GAAP'!L27)/'Income - GAAP'!L$9 -> 0
A28: ='Income - GAAP'!A28 -> + Other Operating Expense | B28: ='Income - GAAP'!B28 -> OTHER_OPERATING_EXPENSES_RATIO | C28: =IF('Income - GAAP'!C28="",0,'Income - GAAP'!C28)/'Income - GAAP'!C$9 -> 0 | D28: =IF('Income - GAAP'!D28="",0,'Income - GAAP'!D28)/'Income - GAAP'!D$9 -> 0 | E28: =IF('Income - GAAP'!E28="",0,'Income - GAAP'!E28)/'Income - GAAP'!E$9 -> 0 | F28: =IF('Income - GAAP'!F28="",0,'Income - GAAP'!F28)/'Income - GAAP'!F$9 -> 0 | G28: =IF('Income - GAAP'!G28="",0,'Income - GAAP'!G28)/'Income - GAAP'!G$9 -> 0 | H28: =IF('Income - GAAP'!H28="",0,'Income - GAAP'!H28)/'Income - GAAP'!H$9 -> 0 | I28: =IF('Income - GAAP'!I28="",0,'Income - GAAP'!I28)/'Income - GAAP'!I$9 -> 0 | J28: =IF('Income - GAAP'!J28="",0,'Income - GAAP'!J28)/'Income - GAAP'!J$9 -> 0 | ... L28: =IF('Income - GAAP'!L28="",0,'Income - GAAP'!L28)/'Income - GAAP'!L$9 -> 0
A29: ='Income - GAAP'!A29 -> check
A30: ='Income - GAAP'!A30 -> Operating Income (Loss) | B30: ='Income - GAAP'!B30 -> IS_OPER_INC | C30: =IF('Income - GAAP'!C30="",0,'Income - GAAP'!C30)/'Income - GAAP'!C$9 -> 0.066565197 | D30: =IF('Income - GAAP'!D30="",0,'Income - GAAP'!D30)/'Income - GAAP'!D$9 -> 0.077610356 | E30: =IF('Income - GAAP'!E30="",0,'Income - GAAP'!E30)/'Income - GAAP'!E$9 -> 0.07040834 | F30: =IF('Income - GAAP'!F30="",0,'Income - GAAP'!F30)/'Income - GAAP'!F$9 -> 0.01377029 | G30: =IF('Income - GAAP'!G30="",0,'Income - GAAP'!G30)/'Income - GAAP'!G$9 -> 0.11418351 | H30: =IF('Income - GAAP'!H30="",0,'Income - GAAP'!H30)/'Income - GAAP'!H$9 -> 0.095318209 | I30: =IF('Income - GAAP'!I30="",0,'Income - GAAP'!I30)/'Income - GAAP'!I$9 -> 0.1227945 | J30: =IF('Income - GAAP'!J30="",0,'Income - GAAP'!J30)/'Income - GAAP'!J$9 -> 0.15158942 | ... L30: =IF('Income - GAAP'!L30="",0,'Income - GAAP'!L30)/'Income - GAAP'!L$9 -> 0.13029002
A31: ='Income - GAAP'!A31 -> check
A32: ='Income - GAAP'!A32 -> - Non-Operating (Income) Loss | B32: ='Income - GAAP'!B32 -> NONOP_INCOME_LOSS | C32: =IF('Income - GAAP'!C32="",0,'Income - GAAP'!C32)/'Income - GAAP'!C$9 -> 0.0098506809 | D32: =IF('Income - GAAP'!D32="",0,'Income - GAAP'!D32)/'Income - GAAP'!D$9 -> 0.0086604824 | E32: =IF('Income - GAAP'!E32="",0,'Income - GAAP'!E32)/'Income - GAAP'!E$9 -> 0.0085995198 | F32: =IF('Income - GAAP'!F32="",0,'Income - GAAP'!F32)/'Income - GAAP'!F$9 -> 0.0090255634 | G32: =IF('Income - GAAP'!G32="",0,'Income - GAAP'!G32)/'Income - GAAP'!G$9 -> 0.011289426 | H32: =IF('Income - GAAP'!H32="",0,'Income - GAAP'!H32)/'Income - GAAP'!H$9 -> 0.0065551418 | I32: =IF('Income - GAAP'!I32="",0,'Income - GAAP'!I32)/'Income - GAAP'!I$9 -> 0.0087902193 | J32: =IF('Income - GAAP'!J32="",0,'Income - GAAP'!J32)/'Income - GAAP'!J$9 -> 0.0026836418 | ... L32: =IF('Income - GAAP'!L32="",0,'Income - GAAP'!L32)/'Income - GAAP'!L$9 -> -0.0095495352
A33: ='Income - GAAP'!A33 -> + Interest Expense, Net | B33: ='Income - GAAP'!B33 -> IS_NET_INTEREST_EXPENSE | C33: =IF('Income - GAAP'!C33="",0,'Income - GAAP'!C33)/'Income - GAAP'!C$9 -> 0.0079510313 | D33: =IF('Income - GAAP'!D33="",0,'Income - GAAP'!D33)/'Income - GAAP'!D$9 -> 0.0069094665 | E33: =IF('Income - GAAP'!E33="",0,'Income - GAAP'!E33)/'Income - GAAP'!E$9 -> 0.0055632138 | F33: =IF('Income - GAAP'!F33="",0,'Income - GAAP'!F33)/'Income - GAAP'!F$9 -> 0.0053257129 | G33: =IF('Income - GAAP'!G33="",0,'Income - GAAP'!G33)/'Income - GAAP'!G$9 -> 0.0059048815 | H33: =IF('Income - GAAP'!H33="",0,'Income - GAAP'!H33)/'Income - GAAP'!H$9 -> 0.0064617737 | I33: =IF('Income - GAAP'!I33="",0,'Income - GAAP'!I33)/'Income - GAAP'!I$9 -> 0.0047317978 | J33: =IF('Income - GAAP'!J33="",0,'Income - GAAP'!J33)/'Income - GAAP'!J$9 -> 0.0014909121 | ... L33: =IF('Income - GAAP'!L33="",0,'Income - GAAP'!L33)/'Income - GAAP'!L$9 -> -0.0087008847
A34: ='Income - GAAP'!A34 -> + Interest Expense | B34: ='Income - GAAP'!B34 -> IS_INT_EXPENSE | C34: =IF('Income - GAAP'!C34="",0,'Income - GAAP'!C34)/'Income - GAAP'!C$9 -> 0.0092000364 | D34: =IF('Income - GAAP'!D34="",0,'Income - GAAP'!D34)/'Income - GAAP'!D$9 -> 0.0091836636 | E34: =IF('Income - GAAP'!E34="",0,'Income - GAAP'!E34)/'Income - GAAP'!E$9 -> 0.0085575264 | F34: =IF('Income - GAAP'!F34="",0,'Income - GAAP'!F34)/'Income - GAAP'!F$9 -> 0.010734746 | G34: =IF('Income - GAAP'!G34="",0,'Income - GAAP'!G34)/'Income - GAAP'!G$9 -> 0.010025448 | H34: =IF('Income - GAAP'!H34="",0,'Income - GAAP'!H34)/'Income - GAAP'!H$9 -> 0.0083696529 | I34: =IF('Income - GAAP'!I34="",0,'Income - GAAP'!I34)/'Income - GAAP'!I$9 -> 0.0055388113 | J34: =IF('Income - GAAP'!J34="",0,'Income - GAAP'!J34)/'Income - GAAP'!J$9 -> 0.0056194777 | ... L34: =IF('Income - GAAP'!L34="",0,'Income - GAAP'!L34)/'Income - GAAP'!L$9 -> 0.0027100632
A35: ='Income - GAAP'!A35 -> - Interest Income | B35: ='Income - GAAP'!B35 -> IS_INT_INC | C35: =IF('Income - GAAP'!C35="",0,'Income - GAAP'!C35)/'Income - GAAP'!C$9 -> 0.0012490052 | D35: =IF('Income - GAAP'!D35="",0,'Income - GAAP'!D35)/'Income - GAAP'!D$9 -> 0.0022741971 | E35: =IF('Income - GAAP'!E35="",0,'Income - GAAP'!E35)/'Income - GAAP'!E$9 -> 0.0029943126 | F35: =IF('Income - GAAP'!F35="",0,'Income - GAAP'!F35)/'Income - GAAP'!F$9 -> 0.0054090328 | G35: =IF('Income - GAAP'!G35="",0,'Income - GAAP'!G35)/'Income - GAAP'!G$9 -> 0.0041205666 | H35: =IF('Income - GAAP'!H35="",0,'Income - GAAP'!H35)/'Income - GAAP'!H$9 -> 0.0019078792 | I35: =IF('Income - GAAP'!I35="",0,'Income - GAAP'!I35)/'Income - GAAP'!I$9 -> 0.00080701349 | J35: =IF('Income - GAAP'!J35="",0,'Income - GAAP'!J35)/'Income - GAAP'!J$9 -> 0.0041285656 | ... L35: =IF('Income - GAAP'!L35="",0,'Income - GAAP'!L35)/'Income - GAAP'!L$9 -> 0.011410948
A36: ='Income - GAAP'!A36 -> check
A37: ='Income - GAAP'!A37 -> + Other Investment (Inc) Loss | B37: ='Income - GAAP'!B37 -> IS_OTHER_INVESTMENT_INCOME_LOSS | C37: =IF('Income - GAAP'!C37="",0,'Income - GAAP'!C37)/'Income - GAAP'!C$9 -> 0 | D37: =IF('Income - GAAP'!D37="",0,'Income - GAAP'!D37)/'Income - GAAP'!D$9 -> 0 | E37: =IF('Income - GAAP'!E37="",0,'Income - GAAP'!E37)/'Income - GAAP'!E$9 -> 0 | F37: =IF('Income - GAAP'!F37="",0,'Income - GAAP'!F37)/'Income - GAAP'!F$9 -> 0 | G37: =IF('Income - GAAP'!G37="",0,'Income - GAAP'!G37)/'Income - GAAP'!G$9 -> 0 | H37: =IF('Income - GAAP'!H37="",0,'Income - GAAP'!H37)/'Income - GAAP'!H$9 -> 0 | I37: =IF('Income - GAAP'!I37="",0,'Income - GAAP'!I37)/'Income - GAAP'!I$9 -> 0 | J37: =IF('Income - GAAP'!J37="",0,'Income - GAAP'!J37)/'Income - GAAP'!J$9 -> 0 | ... L37: =IF('Income - GAAP'!L37="",0,'Income - GAAP'!L37)/'Income - GAAP'!L$9 -> 0
A38: ='Income - GAAP'!A38 -> + Foreign Exch (Gain) Loss | B38: ='Income - GAAP'!B38 -> IS_FOREIGN_EXCH_LOSS | C38: =IF('Income - GAAP'!C38="",0,'Income - GAAP'!C38)/'Income - GAAP'!C$9 -> 0 | D38: =IF('Income - GAAP'!D38="",0,'Income - GAAP'!D38)/'Income - GAAP'!D$9 -> 0 | E38: =IF('Income - GAAP'!E38="",0,'Income - GAAP'!E38)/'Income - GAAP'!E$9 -> 0 | F38: =IF('Income - GAAP'!F38="",0,'Income - GAAP'!F38)/'Income - GAAP'!F$9 -> 0 | G38: =IF('Income - GAAP'!G38="",0,'Income - GAAP'!G38)/'Income - GAAP'!G$9 -> 0 | H38: =IF('Income - GAAP'!H38="",0,'Income - GAAP'!H38)/'Income - GAAP'!H$9 -> 0 | I38: =IF('Income - GAAP'!I38="",0,'Income - GAAP'!I38)/'Income - GAAP'!I$9 -> 0 | J38: =IF('Income - GAAP'!J38="",0,'Income - GAAP'!J38)/'Income - GAAP'!J$9 -> 0 | ... L38: =IF('Income - GAAP'!L38="",0,'Income - GAAP'!L38)/'Income - GAAP'!L$9 -> 0
A39: ='Income - GAAP'!A39 -> + (Income) Loss from Affiliates | B39: ='Income - GAAP'!B39 -> INCOME_LOSS_FROM_AFFILIATES | C39: =IF('Income - GAAP'!C39="",0,'Income - GAAP'!C39)/'Income - GAAP'!C$9 -> 0 | D39: =IF('Income - GAAP'!D39="",0,'Income - GAAP'!D39)/'Income - GAAP'!D$9 -> 0 | E39: =IF('Income - GAAP'!E39="",0,'Income - GAAP'!E39)/'Income - GAAP'!E$9 -> 0 | F39: =IF('Income - GAAP'!F39="",0,'Income - GAAP'!F39)/'Income - GAAP'!F$9 -> 0 | G39: =IF('Income - GAAP'!G39="",0,'Income - GAAP'!G39)/'Income - GAAP'!G$9 -> 0 | H39: =IF('Income - GAAP'!H39="",0,'Income - GAAP'!H39)/'Income - GAAP'!H$9 -> 0 | I39: =IF('Income - GAAP'!I39="",0,'Income - GAAP'!I39)/'Income - GAAP'!I$9 -> 0 | J39: =IF('Income - GAAP'!J39="",0,'Income - GAAP'!J39)/'Income - GAAP'!J$9 -> 0 | ... L39: =IF('Income - GAAP'!L39="",0,'Income - GAAP'!L39)/'Income - GAAP'!L$9 -> 0
A40: ='Income - GAAP'!A40 -> + Other Non-Op (Income) Loss | B40: ='Income - GAAP'!B40 -> OTHER_NONOP_INCOME_LOSS | C40: =IF('Income - GAAP'!C40="",0,'Income - GAAP'!C40)/'Income - GAAP'!C$9 -> 0.0018996497 | D40: =IF('Income - GAAP'!D40="",0,'Income - GAAP'!D40)/'Income - GAAP'!D$9 -> 0.001751016 | E40: =IF('Income - GAAP'!E40="",0,'Income - GAAP'!E40)/'Income - GAAP'!E$9 -> 0.003036306 | F40: =IF('Income - GAAP'!F40="",0,'Income - GAAP'!F40)/'Income - GAAP'!F$9 -> 0.0036998505 | G40: =IF('Income - GAAP'!G40="",0,'Income - GAAP'!G40)/'Income - GAAP'!G$9 -> 0.0053845441 | H40: =IF('Income - GAAP'!H40="",0,'Income - GAAP'!H40)/'Income - GAAP'!H$9 -> 9.336805e-05 | I40: =IF('Income - GAAP'!I40="",0,'Income - GAAP'!I40)/'Income - GAAP'!I$9 -> 0.0040584215 | J40: =IF('Income - GAAP'!J40="",0,'Income - GAAP'!J40)/'Income - GAAP'!J$9 -> 0.0011927297 | ... L40: =IF('Income - GAAP'!L40="",0,'Income - GAAP'!L40)/'Income - GAAP'!L$9 -> -0.00084865044
A41: ='Income - GAAP'!A41 -> check
A42: ='Income - GAAP'!A42 -> Pretax Income | B42: ='Income - GAAP'!B42 -> PRETAX_INC | C42: =IF('Income - GAAP'!C42="",0,'Income - GAAP'!C42)/'Income - GAAP'!C$9 -> 0.056714516 | D42: =IF('Income - GAAP'!D42="",0,'Income - GAAP'!D42)/'Income - GAAP'!D$9 -> 0.068949873 | E42: =IF('Income - GAAP'!E42="",0,'Income - GAAP'!E42)/'Income - GAAP'!E$9 -> 0.06180882 | F42: =IF('Income - GAAP'!F42="",0,'Income - GAAP'!F42)/'Income - GAAP'!F$9 -> 0.0047447261 | G42: =IF('Income - GAAP'!G42="",0,'Income - GAAP'!G42)/'Income - GAAP'!G$9 -> 0.10289409 | H42: =IF('Income - GAAP'!H42="",0,'Income - GAAP'!H42)/'Income - GAAP'!H$9 -> 0.088763067 | I42: =IF('Income - GAAP'!I42="",0,'Income - GAAP'!I42)/'Income - GAAP'!I$9 -> 0.11400428 | J42: =IF('Income - GAAP'!J42="",0,'Income - GAAP'!J42)/'Income - GAAP'!J$9 -> 0.14890577 | ... L42: =IF('Income - GAAP'!L42="",0,'Income - GAAP'!L42)/'Income - GAAP'!L$9 -> 0.13983955
A43: ='Income - GAAP'!A43 -> check
A44: ='Income - GAAP'!A44 -> - Income Tax Expense (Benefit) | B44: ='Income - GAAP'!B44 -> IS_INC_TAX_EXP | C44: =IF('Income - GAAP'!C44="",0,'Income - GAAP'!C44)/'Income - GAAP'!C$9 -> 0.017468644 | D44: =IF('Income - GAAP'!D44="",0,'Income - GAAP'!D44)/'Income - GAAP'!D$9 -> 0.024201473 | E44: =IF('Income - GAAP'!E44="",0,'Income - GAAP'!E44)/'Income - GAAP'!E$9 -> 0.024787066 | F44: =IF('Income - GAAP'!F44="",0,'Income - GAAP'!F44)/'Income - GAAP'!F$9 -> -0.00014637266 | G44: =IF('Income - GAAP'!G44="",0,'Income - GAAP'!G44)/'Income - GAAP'!G$9 -> 0.02151711 | H44: =IF('Income - GAAP'!H44="",0,'Income - GAAP'!H44)/'Income - GAAP'!H$9 -> 0.013765622 | I44: =IF('Income - GAAP'!I44="",0,'Income - GAAP'!I44)/'Income - GAAP'!I$9 -> 0.029061568 | J44: =IF('Income - GAAP'!J44="",0,'Income - GAAP'!J44)/'Income - GAAP'!J$9 -> 0.041531916 | ... L44: =IF('Income - GAAP'!L44="",0,'Income - GAAP'!L44)/'Income - GAAP'!L$9 -> 0.030354777
A45: ='Income - GAAP'!A45 -> + Current Income Tax | B45: ='Income - GAAP'!B45 -> IS_CURRENT_INCOME_TAX_BENEFIT | C45: =IF('Income - GAAP'!C45="",0,'Income - GAAP'!C45)/'Income - GAAP'!C$9 -> 0.028612868 | D45: =IF('Income - GAAP'!D45="",0,'Income - GAAP'!D45)/'Income - GAAP'!D$9 -> 0.025944767 | E45: =IF('Income - GAAP'!E45="",0,'Income - GAAP'!E45)/'Income - GAAP'!E$9 -> 0.024878356 | F45: =IF('Income - GAAP'!F45="",0,'Income - GAAP'!F45)/'Income - GAAP'!F$9 -> 0.012657857 | G45: =IF('Income - GAAP'!G45="",0,'Income - GAAP'!G45)/'Income - GAAP'!G$9 -> 0.018601535 | H45: =IF('Income - GAAP'!H45="",0,'Income - GAAP'!H45)/'Income - GAAP'!H$9 -> 0.010399087 | I45: =IF('Income - GAAP'!I45="",0,'Income - GAAP'!I45)/'Income - GAAP'!I$9 -> 0.031738206 | J45: =IF('Income - GAAP'!J45="",0,'Income - GAAP'!J45)/'Income - GAAP'!J$9 -> 0.041531916 | ... L45: =IF('Income - GAAP'!L45="",0,'Income - GAAP'!L45)/'Income - GAAP'!L$9 -> 0.032473446
A46: ='Income - GAAP'!A46 -> + Deferred Income Tax | B46: ='Income - GAAP'!B46 -> IS_DEFERRED_INCOME_TAX_BENEFIT | C46: =IF('Income - GAAP'!C46="",0,'Income - GAAP'!C46)/'Income - GAAP'!C$9 -> -0.011144224 | D46: =IF('Income - GAAP'!D46="",0,'Income - GAAP'!D46)/'Income - GAAP'!D$9 -> -0.0017432937 | E46: =IF('Income - GAAP'!E46="",0,'Income - GAAP'!E46)/'Income - GAAP'!E$9 -> -9.1290019e-05 | F46: =IF('Income - GAAP'!F46="",0,'Income - GAAP'!F46)/'Income - GAAP'!F$9 -> -0.01280423 | G46: =IF('Income - GAAP'!G46="",0,'Income - GAAP'!G46)/'Income - GAAP'!G$9 -> 0.0029155747 | H46: =IF('Income - GAAP'!H46="",0,'Income - GAAP'!H46)/'Income - GAAP'!H$9 -> 0.0033665348 | I46: =IF('Income - GAAP'!I46="",0,'Income - GAAP'!I46)/'Income - GAAP'!I$9 -> -0.002676638 | J46: =IF('Income - GAAP'!J46="",0,'Income - GAAP'!J46)/'Income - GAAP'!J$9 -> 0 | ... L46: =IF('Income - GAAP'!L46="",0,'Income - GAAP'!L46)/'Income - GAAP'!L$9 -> -0.0021186691
A47: ='Income - GAAP'!A47 -> + Tax Allowance/Credit | B47: ='Income - GAAP'!B47 -> IS_TAX_VALN_ALLOWNCE_CREDITS | C47: =IF('Income - GAAP'!C47="",0,'Income - GAAP'!C47)/'Income - GAAP'!C$9 -> 0 | D47: =IF('Income - GAAP'!D47="",0,'Income - GAAP'!D47)/'Income - GAAP'!D$9 -> 0 | E47: =IF('Income - GAAP'!E47="",0,'Income - GAAP'!E47)/'Income - GAAP'!E$9 -> 0 | F47: =IF('Income - GAAP'!F47="",0,'Income - GAAP'!F47)/'Income - GAAP'!F$9 -> 0 | G47: =IF('Income - GAAP'!G47="",0,'Income - GAAP'!G47)/'Income - GAAP'!G$9 -> 0 | H47: =IF('Income - GAAP'!H47="",0,'Income - GAAP'!H47)/'Income - GAAP'!H$9 -> 0 | I47: =IF('Income - GAAP'!I47="",0,'Income - GAAP'!I47)/'Income - GAAP'!I$9 -> 0 | J47: =IF('Income - GAAP'!J47="",0,'Income - GAAP'!J47)/'Income - GAAP'!J$9 -> 0 | ... L47: =IF('Income - GAAP'!L47="",0,'Income - GAAP'!L47)/'Income - GAAP'!L$9 -> 0
A48: ='Income - GAAP'!A48 -> - (Income) Loss from Affiliates | B48: ='Income - GAAP'!B48 -> IS_SH_PRO_EQY_MT_INV_NET_OF_TAX | C48: =IF('Income - GAAP'!C48="",0,'Income - GAAP'!C48)/'Income - GAAP'!C$9 -> 0 | D48: =IF('Income - GAAP'!D48="",0,'Income - GAAP'!D48)/'Income - GAAP'!D$9 -> 0 | E48: =IF('Income - GAAP'!E48="",0,'Income - GAAP'!E48)/'Income - GAAP'!E$9 -> 0 | F48: =IF('Income - GAAP'!F48="",0,'Income - GAAP'!F48)/'Income - GAAP'!F$9 -> 0 | G48: =IF('Income - GAAP'!G48="",0,'Income - GAAP'!G48)/'Income - GAAP'!G$9 -> 0 | H48: =IF('Income - GAAP'!H48="",0,'Income - GAAP'!H48)/'Income - GAAP'!H$9 -> 0 | I48: =IF('Income - GAAP'!I48="",0,'Income - GAAP'!I48)/'Income - GAAP'!I$9 -> 0 | J48: =IF('Income - GAAP'!J48="",0,'Income - GAAP'!J48)/'Income - GAAP'!J$9 -> 0 | ... L48: =IF('Income - GAAP'!L48="",0,'Income - GAAP'!L48)/'Income - GAAP'!L$9 -> 0
A50: ='Income - GAAP'!A50 -> Income (Loss) from Cont Ops | B50: ='Income - GAAP'!B50 -> IS_INC_BEF_XO_ITEM | C50: =IF('Income - GAAP'!C50="",0,'Income - GAAP'!C50)/'Income - GAAP'!C$9 -> 0.039245872 | D50: =IF('Income - GAAP'!D50="",0,'Income - GAAP'!D50)/'Income - GAAP'!D$9 -> 0.0447484 | E50: =IF('Income - GAAP'!E50="",0,'Income - GAAP'!E50)/'Income - GAAP'!E$9 -> 0.037021754 | F50: =IF('Income - GAAP'!F50="",0,'Income - GAAP'!F50)/'Income - GAAP'!F$9 -> 0.0048910987 | G50: =IF('Income - GAAP'!G50="",0,'Income - GAAP'!G50)/'Income - GAAP'!G$9 -> 0.081376977 | H50: =IF('Income - GAAP'!H50="",0,'Income - GAAP'!H50)/'Income - GAAP'!H$9 -> 0.074997446 | I50: =IF('Income - GAAP'!I50="",0,'Income - GAAP'!I50)/'Income - GAAP'!I$9 -> 0.084942711 | J50: =IF('Income - GAAP'!J50="",0,'Income - GAAP'!J50)/'Income - GAAP'!J$9 -> 0.10737386 | ... L50: =IF('Income - GAAP'!L50="",0,'Income - GAAP'!L50)/'Income - GAAP'!L$9 -> 0.10948478
A51: ='Income - GAAP'!A51 -> check
A52: ='Income - GAAP'!A52 -> - Net Extraordinary Losses (Gains) | B52: ='Income - GAAP'!B52 -> XO_GL_NET_OF_TAX | C52: =IF('Income - GAAP'!C52="",0,'Income - GAAP'!C52)/'Income - GAAP'!C$9 -> 0 | D52: =IF('Income - GAAP'!D52="",0,'Income - GAAP'!D52)/'Income - GAAP'!D$9 -> 0 | E52: =IF('Income - GAAP'!E52="",0,'Income - GAAP'!E52)/'Income - GAAP'!E$9 -> 0 | F52: =IF('Income - GAAP'!F52="",0,'Income - GAAP'!F52)/'Income - GAAP'!F$9 -> 0 | G52: =IF('Income - GAAP'!G52="",0,'Income - GAAP'!G52)/'Income - GAAP'!G$9 -> 0 | H52: =IF('Income - GAAP'!H52="",0,'Income - GAAP'!H52)/'Income - GAAP'!H$9 -> 0 | I52: =IF('Income - GAAP'!I52="",0,'Income - GAAP'!I52)/'Income - GAAP'!I$9 -> 0 | J52: =IF('Income - GAAP'!J52="",0,'Income - GAAP'!J52)/'Income - GAAP'!J$9 -> 0 | ... L52: =IF('Income - GAAP'!L52="",0,'Income - GAAP'!L52)/'Income - GAAP'!L$9 -> 0
A53: ='Income - GAAP'!A53 -> + Discontinued Operations | B53: ='Income - GAAP'!B53 -> IS_DISCONTINUED_OPERATIONS | C53: =IF('Income - GAAP'!C53="",0,'Income - GAAP'!C53)/'Income - GAAP'!C$9 -> 0 | D53: =IF('Income - GAAP'!D53="",0,'Income - GAAP'!D53)/'Income - GAAP'!D$9 -> 0 | E53: =IF('Income - GAAP'!E53="",0,'Income - GAAP'!E53)/'Income - GAAP'!E$9 -> 0 | F53: =IF('Income - GAAP'!F53="",0,'Income - GAAP'!F53)/'Income - GAAP'!F$9 -> 0 | G53: =IF('Income - GAAP'!G53="",0,'Income - GAAP'!G53)/'Income - GAAP'!G$9 -> 0 | H53: =IF('Income - GAAP'!H53="",0,'Income - GAAP'!H53)/'Income - GAAP'!H$9 -> 0 | I53: =IF('Income - GAAP'!I53="",0,'Income - GAAP'!I53)/'Income - GAAP'!I$9 -> 0 | J53: =IF('Income - GAAP'!J53="",0,'Income - GAAP'!J53)/'Income - GAAP'!J$9 -> 0 | ... L53: =IF('Income - GAAP'!L53="",0,'Income - GAAP'!L53)/'Income - GAAP'!L$9 -> 0
A54: ='Income - GAAP'!A54 -> + XO & Accounting Changes | B54: ='Income - GAAP'!B54 -> IS_EXTRAORD_ITEMS_&_ACCTG_CHNG | C54: =IF('Income - GAAP'!C54="",0,'Income - GAAP'!C54)/'Income - GAAP'!C$9 -> 0 | D54: =IF('Income - GAAP'!D54="",0,'Income - GAAP'!D54)/'Income - GAAP'!D$9 -> 0 | E54: =IF('Income - GAAP'!E54="",0,'Income - GAAP'!E54)/'Income - GAAP'!E$9 -> 0 | F54: =IF('Income - GAAP'!F54="",0,'Income - GAAP'!F54)/'Income - GAAP'!F$9 -> 0 | G54: =IF('Income - GAAP'!G54="",0,'Income - GAAP'!G54)/'Income - GAAP'!G$9 -> 0 | H54: =IF('Income - GAAP'!H54="",0,'Income - GAAP'!H54)/'Income - GAAP'!H$9 -> 0 | I54: =IF('Income - GAAP'!I54="",0,'Income - GAAP'!I54)/'Income - GAAP'!I$9 -> 0 | J54: =IF('Income - GAAP'!J54="",0,'Income - GAAP'!J54)/'Income - GAAP'!J$9 -> 0 | ... L54: =IF('Income - GAAP'!L54="",0,'Income - GAAP'!L54)/'Income - GAAP'!L$9 -> 0
A55: ='Income - GAAP'!A55 -> check
A56: ='Income - GAAP'!A56 -> Income (Loss) Incl. MI | B56: ='Income - GAAP'!B56 -> NI_INCLUDING_MINORITY_INT_RATIO | C56: =IF('Income - GAAP'!C56="",0,'Income - GAAP'!C56)/'Income - GAAP'!C$9 -> 0.039245872 | D56: =IF('Income - GAAP'!D56="",0,'Income - GAAP'!D56)/'Income - GAAP'!D$9 -> 0.0447484 | E56: =IF('Income - GAAP'!E56="",0,'Income - GAAP'!E56)/'Income - GAAP'!E$9 -> 0.037021754 | F56: =IF('Income - GAAP'!F56="",0,'Income - GAAP'!F56)/'Income - GAAP'!F$9 -> 0.0048910987 | G56: =IF('Income - GAAP'!G56="",0,'Income - GAAP'!G56)/'Income - GAAP'!G$9 -> 0.081376977 | H56: =IF('Income - GAAP'!H56="",0,'Income - GAAP'!H56)/'Income - GAAP'!H$9 -> 0.074997446 | I56: =IF('Income - GAAP'!I56="",0,'Income - GAAP'!I56)/'Income - GAAP'!I$9 -> 0.084942711 | J56: =IF('Income - GAAP'!J56="",0,'Income - GAAP'!J56)/'Income - GAAP'!J$9 -> 0.10737386 | ... L56: =IF('Income - GAAP'!L56="",0,'Income - GAAP'!L56)/'Income - GAAP'!L$9 -> 0.10948478
A57: ='Income - GAAP'!A57 -> - Minority Interest | B57: ='Income - GAAP'!B57 -> MIN_NONCONTROL_INTEREST_CREDITS | C57: =IF('Income - GAAP'!C57="",0,'Income - GAAP'!C57)/'Income - GAAP'!C$9 -> 0 | D57: =IF('Income - GAAP'!D57="",0,'Income - GAAP'!D57)/'Income - GAAP'!D$9 -> 0 | E57: =IF('Income - GAAP'!E57="",0,'Income - GAAP'!E57)/'Income - GAAP'!E$9 -> 0 | F57: =IF('Income - GAAP'!F57="",0,'Income - GAAP'!F57)/'Income - GAAP'!F$9 -> 0 | G57: =IF('Income - GAAP'!G57="",0,'Income - GAAP'!G57)/'Income - GAAP'!G$9 -> 0 | H57: =IF('Income - GAAP'!H57="",0,'Income - GAAP'!H57)/'Income - GAAP'!H$9 -> 0 | I57: =IF('Income - GAAP'!I57="",0,'Income - GAAP'!I57)/'Income - GAAP'!I$9 -> 0 | J57: =IF('Income - GAAP'!J57="",0,'Income - GAAP'!J57)/'Income - GAAP'!J$9 -> 0 | ... L57: =IF('Income - GAAP'!L57="",0,'Income - GAAP'!L57)/'Income - GAAP'!L$9 -> 0
A58: ='Income - GAAP'!A58 -> Net Income, GAAP | B58: ='Income - GAAP'!B58 -> NET_INCOME | C58: =IF('Income - GAAP'!C58="",0,'Income - GAAP'!C58)/'Income - GAAP'!C$9 -> 0.039245872 | D58: =IF('Income - GAAP'!D58="",0,'Income - GAAP'!D58)/'Income - GAAP'!D$9 -> 0.0447484 | E58: =IF('Income - GAAP'!E58="",0,'Income - GAAP'!E58)/'Income - GAAP'!E$9 -> 0.037021754 | F58: =IF('Income - GAAP'!F58="",0,'Income - GAAP'!F58)/'Income - GAAP'!F$9 -> 0.0048910987 | G58: =IF('Income - GAAP'!G58="",0,'Income - GAAP'!G58)/'Income - GAAP'!G$9 -> 0.081376977 | H58: =IF('Income - GAAP'!H58="",0,'Income - GAAP'!H58)/'Income - GAAP'!H$9 -> 0.074997446 | I58: =IF('Income - GAAP'!I58="",0,'Income - GAAP'!I58)/'Income - GAAP'!I$9 -> 0.084942711 | J58: =IF('Income - GAAP'!J58="",0,'Income - GAAP'!J58)/'Income - GAAP'!J$9 -> 0.10737386 | ... L58: =IF('Income - GAAP'!L58="",0,'Income - GAAP'!L58)/'Income - GAAP'!L$9 -> 0.10948478
A59: ='Income - GAAP'!A59 -> check
A60: ='Income - GAAP'!A60 -> - Preferred Dividends | B60: ='Income - GAAP'!B60 -> IS_TOT_CASH_PFD_DVD | C60: =IF('Income - GAAP'!C60="",0,'Income - GAAP'!C60)/'Income - GAAP'!C$9 -> 0 | D60: =IF('Income - GAAP'!D60="",0,'Income - GAAP'!D60)/'Income - GAAP'!D$9 -> 0 | E60: =IF('Income - GAAP'!E60="",0,'Income - GAAP'!E60)/'Income - GAAP'!E$9 -> 0 | F60: =IF('Income - GAAP'!F60="",0,'Income - GAAP'!F60)/'Income - GAAP'!F$9 -> 0 | G60: =IF('Income - GAAP'!G60="",0,'Income - GAAP'!G60)/'Income - GAAP'!G$9 -> 0 | H60: =IF('Income - GAAP'!H60="",0,'Income - GAAP'!H60)/'Income - GAAP'!H$9 -> 0 | I60: =IF('Income - GAAP'!I60="",0,'Income - GAAP'!I60)/'Income - GAAP'!I$9 -> 0 | J60: =IF('Income - GAAP'!J60="",0,'Income - GAAP'!J60)/'Income - GAAP'!J$9 -> 0 | ... L60: =IF('Income - GAAP'!L60="",0,'Income - GAAP'!L60)/'Income - GAAP'!L$9 -> 0
A61: ='Income - GAAP'!A61 -> - Other Adjustments | B61: ='Income - GAAP'!B61 -> OTHER_ADJUSTMENTS | C61: =IF('Income - GAAP'!C61="",0,'Income - GAAP'!C61)/'Income - GAAP'!C$9 -> 0 | D61: =IF('Income - GAAP'!D61="",0,'Income - GAAP'!D61)/'Income - GAAP'!D$9 -> 0 | E61: =IF('Income - GAAP'!E61="",0,'Income - GAAP'!E61)/'Income - GAAP'!E$9 -> 0 | F61: =IF('Income - GAAP'!F61="",0,'Income - GAAP'!F61)/'Income - GAAP'!F$9 -> 0 | G61: =IF('Income - GAAP'!G61="",0,'Income - GAAP'!G61)/'Income - GAAP'!G$9 -> 0 | H61: =IF('Income - GAAP'!H61="",0,'Income - GAAP'!H61)/'Income - GAAP'!H$9 -> 0 | I61: =IF('Income - GAAP'!I61="",0,'Income - GAAP'!I61)/'Income - GAAP'!I$9 -> 0 | J61: =IF('Income - GAAP'!J61="",0,'Income - GAAP'!J61)/'Income - GAAP'!J$9 -> 0 | ... L61: =IF('Income - GAAP'!L61="",0,'Income - GAAP'!L61)/'Income - GAAP'!L$9 -> 0
A62: ='Income - GAAP'!A62 -> Net Income Avail to Common, GAAP | B62: ='Income - GAAP'!B62 -> EARN_FOR_COMMON | C62: =IF('Income - GAAP'!C62="",0,'Income - GAAP'!C62)/'Income - GAAP'!C$9 -> 0.039245872 | D62: =IF('Income - GAAP'!D62="",0,'Income - GAAP'!D62)/'Income - GAAP'!D$9 -> 0.0447484 | E62: =IF('Income - GAAP'!E62="",0,'Income - GAAP'!E62)/'Income - GAAP'!E$9 -> 0.037021754 | F62: =IF('Income - GAAP'!F62="",0,'Income - GAAP'!F62)/'Income - GAAP'!F$9 -> 0.0048910987 | G62: =IF('Income - GAAP'!G62="",0,'Income - GAAP'!G62)/'Income - GAAP'!G$9 -> 0.081376977 | H62: =IF('Income - GAAP'!H62="",0,'Income - GAAP'!H62)/'Income - GAAP'!H$9 -> 0.074997446 | I62: =IF('Income - GAAP'!I62="",0,'Income - GAAP'!I62)/'Income - GAAP'!I$9 -> 0.084942711 | J62: =IF('Income - GAAP'!J62="",0,'Income - GAAP'!J62)/'Income - GAAP'!J$9 -> 0.10737386 | ... L62: =IF('Income - GAAP'!L62="",0,'Income - GAAP'!L62)/'Income - GAAP'!L$9 -> 0.10948478

Sheet Cash Flow - Standardized
A1: Ticker | C1: =IF('Balance Sheet - Standardized'!C1="","",'Balance Sheet - Standardized'!C1) -> LNN | D1: ='Balance Sheet - Standardized'!D1 -> US | M1: Errors on check lines | N1: {=SUM(--ISERROR($C$16:$L$16),--ISERROR($C$22:$L$22),--ISERROR($C$25:$L$25),--ISERROR($C$34:$L$34),--ISERROR($C$38:$L$38),--ISERROR($C$43:$L$43),--ISERROR($C$47:$L$47),--ISERROR($C$54:$L$54),--ISERROR($C$58:$L$58),--ISERROR($C$62:$L$62),--ISERROR($C$68:$L$68), COUNT($C$16:$L$16) - COUNTIFS($C$16:$L$16,">-.1",$C$16:$L$16,"<.1"), COUNT($C$22:$L$22) - COUNTIFS($C$22:$L$22,">-.1", $C$22:$L$22,"<.1"), COUNT($C$25:$L$25) - COUNTIFS($C$25:$L$25,">-.1", $C$25:$L$25,"<.1"), COUNT($C$34:$L$34) - COUNTIFS($C$34:$L$34,">-.1", $C$34:$L$34,"<.1"), COUNT($C$38:$L$38) - COUNTIFS($C$38:$L$38,">-.1", $C$38:$L$38,"<.1"), COUNT($C$43:$L$43) - COUNTIFS($C$43:$L$43,">-.1", $C$43:$L$43,"<.1"), COUNT($C$47:$L$47) - COUNTIFS($C$47:$L$47,">-.1", $C$47:$L$47,"<.1"),COUNT($C$54:$L$54) - COUNTIFS($C$54:$L$54,">-.1", $C$54:$L$54,"<.1"),COUNT($C$58:$L$58) - COUNTIFS($C$58:$L$58,">-.1", $C$58:$L$58,"<.1"),COUNT($C$62:$L$62) - COUNTIFS($C$62:$L$62,">-.1", $C$62:$L$62,"<.1"),COUNT($C$68:$L$68) - COUNTIFS($C$68:$L$68,">-.1", $C$68:$L$68,"<.1"))} -> 0
A2: Start Year | C2: ='Balance Sheet - Standardized'!C2 -> FY 2016
A3: End Year | C3: ='Balance Sheet - Standardized'!C3 -> FY 2025
A7: In Millions of USD except Per Share | C7: ='Balance Sheet - Standardized'!C7 -> FY 2016 | D7: ='Balance Sheet - Standardized'!D7 -> FY 2017 | E7: ='Balance Sheet - Standardized'!E7 -> FY 2018 | F7: ='Balance Sheet - Standardized'!F7 -> FY 2019 | G7: ='Balance Sheet - Standardized'!G7 -> FY 2020 | H7: ='Balance Sheet - Standardized'!H7 -> FY 2021 | I7: ='Balance Sheet - Standardized'!I7 -> FY 2022 | J7: ='Balance Sheet - Standardized'!J7 -> FY 2023 | ... L7: ='Balance Sheet - Standardized'!L7 -> FY 2025
A8: 12 Months Ending | C8: ='Balance Sheet - Standardized'!C8 -> 42613 | D8: ='Balance Sheet - Standardized'!D8 -> 42978 | E8: ='Balance Sheet - Standardized'!E8 -> 43343 | F8: ='Balance Sheet - Standardized'!F8 -> 43708 | G8: ='Balance Sheet - Standardized'!G8 -> 44074 | H8: ='Balance Sheet - Standardized'!H8 -> 44439 | I8: ='Balance Sheet - Standardized'!I8 -> 44804 | J8: ='Balance Sheet - Standardized'!J8 -> 45169 | ... L8: ='Balance Sheet - Standardized'!L8 -> 45900
A9: Cash from Operating Activities | C9: 33.125 | D9: 39.449 | E9: 33.934 | F9: 3.797 | G9: 46.034 | H9: 43.968 | I9: 3.048 | J9: 119.707 | K9: 95.761 | L9: 132.91 | M9: =IF(OR(K9=0,K9=""),"",L9/K9-1) -> 0.38793455
A10: + Net Income | B10: CF_NET_INC | C10: 20.267 | D10: 23.179 | E10: 20.277 | F10: 2.172 | G10: 38.629 | H10: 42.572 | I10: 65.469 | J10: 72.379 | K10: 66.257 | L10: 74.052
A11: + CF Depreciation & Amortization | B11: CF_DEPR_AMORT | C11: 16.881 | D11: 16.678 | E11: 16.514 | F11: 14.018 | G11: 19.396 | H11: 19.177 | I11: 20.178 | J11: 19.282 | K11: 21.2 | L11: 20.896
A12: + Non-Cash Items | B12: NON_CASH_ITEMS_DETAILED | C12: 8.568 | D12: -3.111 | E12: 6.35 | F12: 6.842 | G12: 2.201 | H12: 3.618 | I12: 3.48 | J12: 11.734 | K12: 9.292 | L12: 9.515
A13: + Stock-Based Compensation | B13: CF_STOCK_BASED_COMPENSATION | C13: 3.06 | D13: 3.598 | E13: 3.891 | F13: 4.195 | G13: 5.616 | H13: 6.186 | I13: 5.458 | J13: 6.529 | K13: 6.392 | L13: 8.059
A14: + Deferred Income Taxes | B14: CF_DEF_INC_TAX | C14: -5.755 | D14: -0.903 | E14: -0.05 | F14: -5.686 | G14: 1.384 | H14: 1.911 | I14: -2.063 | J14: 0 | K14: -3.895 | L14: -1.433
A15: + Other Non-Cash Adj | B15: OTHER_NON_CASH_ADJ_LESS_DETAILED | C15: 11.263 | D15: -5.806 | E15: 2.509 | F15: 8.333 | G15: -4.799 | H15: -4.479 | I15: 0.085 | J15: 5.205 | K15: 6.795 | L15: 2.889
A16: check | C16: =ROUND(SUM(C13:C15)-IF(C12="",0,C12),1) -> 0 | D16: =ROUND(SUM(D13:D15)-IF(D12="",0,D12),1) -> 0 | E16: =ROUND(SUM(E13:E15)-IF(E12="",0,E12),1) -> 0 | F16: =ROUND(SUM(F13:F15)-IF(F12="",0,F12),1) -> 0 | G16: =ROUND(SUM(G13:G15)-IF(G12="",0,G12),1) -> 0 | H16: =ROUND(SUM(H13:H15)-IF(H12="",0,H12),1) -> 0 | I16: =ROUND(SUM(I13:I15)-IF(I12="",0,I12),1) -> 0 | J16: =ROUND(SUM(J13:J15)-IF(J12="",0,J12),1) -> 0 | ... L16: =ROUND(SUM(L13:L15)-IF(L12="",0,L12),1) -> 0
